Workbook

Sheet Instrucciones
A1: Base de usuarios del Rol de Instructores LP
A3: Usuarios | B3: Una fila por persona. Para agregar a alguien, escribe una fila nueva debajo de la última. Las celdas amarillas de la columna Correo corporativo están por completar.
A4: Rol | B4: Instructor o Administrador. Se elige de la lista.
A5: Activo | B5: SI o NO. Para dar de baja a alguien, cambia a NO en lugar de borrar la fila, así se conserva su historial.
A6: Registro | B6: Lo llena la aplicación en cada ingreso, salida o intento fallido. No hace falta editarla a mano.
A7: Ultimo_Acceso | B7: Se calcula sola desde Usuarios y Registro. No escribir aquí.
A8: Permisos | B8: Qué vistas ve cada rol. SI muestra la vista y NO la oculta.
A10: Ejemplo de fila en Usuarios | B10: BP 1234567 | Nombre Apellido | APELLIDO APELLIDO NOMBRE | nombre.apellido@latam.com | Instructor | A319/A320/A321/B767 | JSB | INS | SI
A11: Ejemplo de fila en Registro | B11: 27/09/2026 08:15:00 | 1234567 | Nombre Apellido | nombre.apellido@latam.com | Instructor | Ingreso | OK | Chrome en Windows
A12: Fuentes | B12: Un Google Sheet por mes (hoja ROL INS). Se agregan desde la app (Actualizar rol › Conectar Google Sheet) o escribiendo Mes (aaaa-mm) y el enlace. Activo = NO pausa la lectura.
A13: Solicitudes | B13: Pedidos de jefatura e instructores: BP, Nombre, Desde, Hasta, Tipo y Estado (asignado / no se asignó).
A14: Vigencias | B14: Experiencia reciente por BP (hoja BG INS). Escribe VENCIDO en la columna programada para generar una alerta.
A15: Acceso a la app | B15: Usuario = BP o correo corporativo. La primera vez, coordinación genera un código temporal (Usuarios y accesos) y la persona crea su contraseña. Las contraseñas no se guardan en este archivo.
... A23: Perfiles | B23: Perfiles de acceso de coordinación: por sección, Sin acceso, Ver o Gestionar. Se asignan en la columna Perfil de Usuarios (vacío = Coordinación completa). Se editan desde la app en Usuarios y accesos. La hoja Permisos aplica solo a instructores.

Sheet Perfiles
A1: Perfil | B1: Descripción | C1: Indicadores | D1: Seguimiento del mes | E1: Rol completo | F1: Equipo por día | G1: Por instructor | H1: Vacaciones | I1: Intercambios | J1: Actualizar rol | K1: Tipos y colores | L1: Usuarios y accesos
A2: Coordinación completa | B2: Ve y gestiona todo el panel de coordinación. | C2: Gestionar | D2: Gestionar | E2: Gestionar | F2: Gestionar | G2: Gestionar | H2: Gestionar | I2: Gestionar | J2: Gestionar | K2: Gestionar | L2: Gestionar
A3: Solo lectura | B3: Ve el panel completo sin poder aprobar, editar ni cambiar accesos. | C3: Ver | D3: Ver | E3: Ver | F3: Ver | G3: Ver | H3: Ver | I3: Ver | J3: Sin acceso | K3: Ver | L3: Sin acceso

Sheet Intercambios
A1: ID | B1: Mes | C1: Días | D1: Solicitante BP | E1: Solicitante | F1: Receptor BP | G1: Receptor | H1: Actividades solicitante | I1: Actividades receptor | J1: Estado | K1: Comentario solicitante | L1: Comentario receptor | M1: Comentario supervisor | N1: Creado | O1: Respondido receptor | P1: Decidido | Q1: Supervisor | R1: Aplicación | S1: Visto solicitante | T1: Visto receptor | U1: Revisado coordinación | V1: Revisor | W1: Comentario revisor | X1: Hilo correo
A2: imvfw4d116dhj | B2: 2026-10 | C2: 21 | D2: 3217561 | E2: Claudia Flores | F2: 2823133 | G2: Cesar Campos | H2: ["HB6\nCurso B767\n(08:30-17:30hrs)"] | I2: ["RESERVA IET"] | J2: Aprobado | L2: Acepto el cambio. Muchas gracias. | N2: 46314.69 | O2: 46314.693 | P2: 46315.558 | Q2: Virginia Sullca | R2: Aplicado en el Google Sheet y sincronizado · 2026-10-20 | S2: pendiente | T2: en_supervisor | U2: 46314.696 | V2: Virginia Sullca | X2: {"thread":"1a15683530d90c78","ultimo":"<CAOYCRE-No45S-o8SsuOSUtR3h9paq-EHRcqxgZ+NrdMORQLjcA@mail.gmail.com>","refs":"<CAOYCRE95wJ27hNa8yb5AcuX+zxRrztpf+nHr0b7aig02pMA6Nw@mail.gmail.com> <CAOYCRE9+TjnBVr5oZvgJZJDT4gjErR5VsYyKyOCp1s_o8KeN=g@mail.gmail.com> <CAOYCRE84LtL6AYzpBYE_3DwGx=f3hBeJe-NvR7XPFjzOpRH1Sg@mail.gmail.com> <CAOYCRE-No45S-o8SsuOSUtR3h9paq-EHRcqxgZ+NrdMORQLjcA@mail.gmail.com>","dest":["claudia.floresf@latam.com","cesar.campos@latam.com","antonella.cotrina@latam.com","virginia.sullca@latam.com","jorge.bodero@latam.com"]}

Sheet TiposActividad
A1: Orden | B1: Tipo | C1: Palabras clave | D1: Color fondo | E1: Color texto | F1: Activo | G1: Notas
A2: 1 | B2: Do | C2: DO | D2: #ffffff | E2: #000000 | F2: NO
A3: 2 | B3: Vacaciones | C3: VACACIONES | D3: #ffffcc | E3: #000000 | F3: NO
A4: 3 | B4: Lck b767 | C4: LCK B767; BLANCO; HABILITACIÓN * | D4: #ffc000 | E4: #000000 | F4: SI
A5: 4 | B5: Adm | C5: ADM; RESERVA IET; RESERVA IET TARDE | D5: #d9d9d9 | E5: #000000 | F5: NO
A6: 5 | B6: Lck a320f | C6: LCK A320F; REENTRENAMIENTO A320F; REENTRENAMIENTO A320F* | D6: #f7caac | E6: #000000 | F6: NO
A7: 6 | B7: Inicial g10 | C7: INICIAL G10 | D7: #a64d79 | E7: #ffffff | F7: NO
A8: 7 | B8: Taller voluntario de seguridad | C8: TALLER VOLUNTARIO DE SEGURIDAD; REUNIÓN INSTRUCTORES; DESAYUNO | D8: #ffff00 | E8: #000000 | F8: NO
A9: 8 | B9: Ho file tarde | C9: HO FILE TARDE; VUELO IDA LIM SCL; COBUS SCL A321XLR | D9: #999999 | E9: #000000 | F9: NO
A10: 9 | B10: Inicial g11 | C10: INICIAL G11 | D10: #00ff00 | E10: #000000 | F10: NO
A11: 10 | B11: Curso 50% | C11: CURSO 50%; IOSA | D11: #ff9900 | E11: #000000 | F11: NO
A12: 11 | B12: Rti: práctica | C12: RTI: PRÁCTICA; RTI: VIRTUAL | D12: #cce0f4 | E12: #000000 | F12: NO
A13: 12 | B13: Fds | C13: FDS | D13: #0000ff | E13: #ffffff | F13: NO
... A29: 28 | B29: Chequeo dgac b767 | C29: CHEQUEO DGAC B767 | D29: #e69138 | E29: #000000 | F29: NO

Sheet VacacionesProgramado
A1: BP | B1: Mes | C1: Días
A2: 29530 | B2: 2026-05 | C2: 8
A3: 29530 | B3: 2026-06 | C3: 7
A4: 29530 | B4: 2026-10 | C4: 15
A5: 29530 | B5: 2026-12 | C5: 11
A6: 71348 | B6: 2026-02 | C6: 7
A7: 967092 | B7: 2026-01 | C7: 15
A8: 967092 | B8: 2026-02 | C8: 7
A9: 967092 | B9: 2026-08 | C9: 24
A10: 1271571 | B10: 2026-02 | C10: 6
A11: 1271571 | B11: 2026-03 | C11: 1
A12: 1271571 | B12: 2026-05 | C12: 7
A13: 1271571 | B13: 2026-08 | C13: 7
... A69: 3852423 | B69: 2026-08 | C69: 16

Sheet VacacionesPeriodos
A1: BP | B1: Periodo | C1: Derecho | D1: Tomados (referencia)
A2: 29530 | B2: 2025-26 | C2: 40 | D2: 41
A3: 29530 | B3: 2026-27 | C3: 41
A4: 71348 | B4: 2025-26 | C4: 45 | D4: 7
A5: 71348 | B5: 2026-27 | C5: 45
A6: 967092 | B6: 2025-26 | C6: 45 | D6: 46
A7: 967092 | B7: 2026-27 | C7: 45
A8: 1271571 | B8: 2025-26 | C8: 45 | D8: 21
A9: 1271571 | B9: 2026-27 | C9: 45
A10: 2369624 | B10: 2025-26 | C10: 44 | D10: 42
A11: 2369624 | B11: 2026-27 | C11: 45
A12: 2369641 | B12: 2025-26 | C12: 44 | D12: 42
A13: 2369641 | B13: 2026-27 | C13: 45
A14: 2396710 | B14: 2025-26 | C14: 43 | D14: 31
A15: 2396710 | B15: 2026-27 | C15: 45
A16: 2415373 | B16: 2025-26 | C16: 44 | D16: 44
A17: 2415373 | B17: 2026-27 | C17: 45
A18: 2440915 | B18: 2025-26 | C18: 44 | D18: 44
A19: 2440915 | B19: 2026-27 | C19: 45
A20: 2604360 | B20: 2025-26 | C20: 41 | D20: 40
A21: 2604360 | B21: 2026-27 | C21: 42
A22: 2713993 | B22: 2025-26 | C22: 45 | D22: 41
A23: 2713993 | B23: 2026-27 | C23: 45
A24: 2823133 | B24: 2025-26 | C24: 40 | D24: 41
A25: 2823133 | B25: 2026-27 | C25: 41
A26: 2843319 | B26: 2025-26 | C26: 42 | D26: 42
A27: 2843319 | B27: 2026-27 | C27: 43
A28: 3134911 | B28: 2025-26 | C28: 41 | D28: 46
A29: 3134911 | B29: 2026-27 | C29: 42
A30: 3189967 | B30: 2025-26 | C30: 40 | D30: 41
A31: 3189967 | B31: 2026-27 | C31: 41
A32: 3217561 | B32: 2025-26 | C32: 40 | D32: 41
A33: 3217561 | B33: 2026-27 | C33: 41
A34: 3750335 | B34: 2025-26 | C34: 36 | D34: 35
A35: 3750335 | B35: 2026-27 | C35: 37
A36: 3779550 | B36: 2025-26 | C36: 38 | D36: 38
A37: 3779550 | B37: 2026-27 | C37: 39
A38: 3796947 | B38: 2025-26 | C38: 38 | D38: 8
A39: 3796947 | B39: 2026-27 | C39: 39
A40: 3841387 | B40: 2025-26 | C40: 37 | D40: 39
A41: 3841387 | B41: 2026-27 | C41: 38
A42: 3852423 | B42: 2025-26 | C42: 37 | D42: 39
A43: 3852423 | B43: 2026-27 | C43: 38

Sheet Vacaciones
A1: BP | B1: Nombre | C1: Fecha DGAC original | D1: Fecha DGAC 2025 | E1: Fecha DGAC 2026 | F1: Derecho 2025-26 | G1: Derecho 2026-27 | H1: Tomados 2025-26 | I1: Programado por mes 2026
A2: 29530 | B2: GUERRA SUAREZ JAZMIN | C2: 40567 | D2: 45681 | E2: 46046 | F2: 40 | G2: 41 | H2: 41 | I2: 5:8; 6:7; 10:15; 12:11
A3: 71348 | B3: MOZ MONTES KARLA LISSETTE | C3: 38223 | D3: 45893 | E3: 46258 | F3: 45 | G3: 45 | H3: 7 | I3: 2:7
A4: 967092 | B4: DAVILA BELLO MARIA ERIKA | C4: 38139 | D4: 45809 | E4: 46174 | F4: 45 | G4: 45 | H4: 46 | I4: 1:15; 2:7; 8:24
A5: 1271571 | B5: RONDON BARRUTIA CHRISTIAN ERIC | D5: 45950 | E5: 46315 | F5: 45 | G5: 45 | H5: 21 | I5: 2:6; 3:1; 5:7; 8:7
A6: 2369624 | B6: NAJAR CRUZ PATRICIA DEL PILAR | C6: 39187 | D6: 45762 | E6: 46127 | F6: 44 | G6: 45 | H6: 42 | I6: 1:6; 4:7; 8:7; 9:7; 10:15
A7: 2369641 | B7: TORRES POLO ELIZABETH DEL PILAR | C7: 39197 | D7: 45772 | E7: 46137 | F7: 44 | G7: 45 | H7: 42 | I7: 1:12; 6:8; 9:15; 11:7
A8: 2396710 | B8: CORREA GARCIA JUAN SEBASTIAN | D8: 45823 | E8: 46188 | F8: 43 | G8: 45 | H8: 31 | I8: 4:18; 6:8; 11:5
A9: 2415373 | B9: SALAS COSIO MILAGROS PATRICIA | C9: 39295 | D9: 45870 | E9: 46235 | F9: 44 | G9: 45 | H9: 44 | I9: 5:29; 10:15
A10: 2440915 | B10: FERNANDEZ GARCIA JUDITH JULIET | C10: 39356 | D10: 45931 | E10: 46296 | F10: 44 | G10: 45 | H10: 44 | I10: 1:7; 2:14; 8:15; 10:8
A11: 2604360 | B11: CARRASCO BENAVIDES ROSA MARIELLA | C11: 40301 | D11: 45780 | E11: 46145 | F11: 41 | G11: 42 | H11: 40 | I11: 2:10; 5:8; 9:15; 11:7
A12: 2713993 | B12: RUIZ RIOJA FIORELLA DEL PILAR | D12: 45689 | E12: 46054 | F12: 45 | G12: 45 | H12: 41 | I12: 3:5; 5:2; 7:1; 10:29; 11:4
A13: 2823133 | B13: CAMPOS CONCHE CESAR AUGUSTO | C13: 40546 | D13: 45660 | E13: 46025 | F13: 40 | G13: 41 | H13: 41 | I13: 6:15; 7:15; 12:11
A14: 2843319 | B14: SANTA CRUZ HUAMAN KAREN | C14: 40026 | D14: 45870 | E14: 46235 | F14: 42 | G14: 43 | H14: 42 | I14: 1:14; 7:12; 10:16
A15: 3134911 | B15: ZAPATA GARAYAR JAVIER RICARDO SALVADOR | C15: 40462 | D15: 45941 | E15: 46306 | F15: 41 | G15: 42 | H15: 46 | I15: 3:23; 10:23
A16: 3189967 | B16: SEGOVIA TAPIA RAY KEVIN | C16: 40546 | D16: 45660 | E16: 46025 | F16: 40 | G16: 41 | H16: 41 | I16: 6:7; 8:16; 9:18
A17: 3217561 | B17: FLORES FUENTES DAVILA CLAUDIA ALEXANDRA | C17: 40567 | D17: 45681 | E17: 46046 | F17: 40 | G17: 41 | H17: 41 | I17: 4:15; 9:15; 11:11
A18: 3750335 | B18: MENDEZ RUCOBA JEFFERSON JOHONATAN | C18: 42186 | D18: 45839 | E18: 46204 | F18: 36 | G18: 37 | H18: 35 | I18: 4:20; 9:8; 11:7
A19: 3779550 | B19: ACURIO DARGENT JENNIFERT MILAGROS | C19: 41470 | D19: 45853 | E19: 46218 | F19: 38 | G19: 39 | H19: 38 | I19: 4:8; 6:15; 11:15
A20: 3796947 | B20: RAFAEL ANTONIO NIETO | C20: 41526 | F20: 38 | G20: 39 | H20: 8 | I20: 9:8
A21: 3841387 | B21: CELIZ ROSSI GIANFRANCO PAOLO | C21: 41656 | D21: 45674 | E21: 46039 | F21: 37 | G21: 38 | H21: 39 | I21: 1:8; 6:7; 7:17; 8:7
A22: 3852423 | B22: UNGARO GUTIERREZ SARA GABRIELA | C22: 41835 | D22: 45853 | E22: 46218 | F22: 37 | G22: 38 | H22: 39 | I22: 3:8; 5:8; 6:7; 8:16

Sheet VacacionesDias
A1: BP | B1: Fecha
A2: 29530 | B2: 45299
A3: 29530 | B3: 45300
A4: 29530 | B4: 45301
A5: 29530 | B5: 45302
A6: 29530 | B6: 45303
A7: 29530 | B7: 45304
A8: 29530 | B8: 45305
A9: 29530 | B9: 45306
A10: 29530 | B10: 45307
A11: 29530 | B11: 45308
A12: 29530 | B12: 45309
A13: 29530 | B13: 45310
... A2307: 3852423 | B2307: 46257

Sheet VacacionesBloques
A1: BP | B1: Desde | C1: Hasta | D1: Días | E1: Registrado
A2: 29530 | B2: 46296 | C2: 46310 | D2: 15 | E2: 46230
A3: 29530 | B3: 46377 | C3: 46387 | D3: 11 | E3: 46230
A4: 1271571 | B4: 46279 | C4: 46313 | D4: 24 | E4: 46227
A5: 2369624 | B5: 46296 | C5: 46310 | D5: 15 | E5: 46230
A6: 2369624 | B6: 46266 | C6: 46272 | D6: 7 | E6: 46230
A7: 2369641 | B7: 46282 | C7: 46295 | D7: 14 | E7: 46230
A8: 2369641 | B8: 46349 | C8: 46356 | D8: 8 | E8: 46230
A9: 2415373 | B9: 46300 | C9: 46307 | D9: 8 | E9: 46234
A10: 2415373 | B10: 46308 | C10: 46314 | D10: 7 | E10: 46235
A11: 2440915 | B11: 46303 | C11: 46310 | D11: 8 | E11: 46230
A12: 2604360 | B12: 46281 | C12: 46295 | D12: 15 | E12: 46233
A13: 2604360 | B13: 46381 | C13: 46387 | D13: 7 | E13: 46233
... A23: 3779550 | B23: 46328 | C23: 46342 | D23: 15 | E23: 46237

Sheet SolicitudesVacaciones
A1: ID | B1: BP | C1: Nombre | D1: Días | E1: Cantidad | F1: Enviada | G1: Estado | H1: Decidida | I1: Decidida por | J1: Comentario instructor | K1: Comentario coordinación | L1: Respuesta instructor | M1: Motivo revisión | N1: Respondida | O1: Revisión atendida

Sheet Roles
A1: mes | B1: json | C1: actualizadoAt | D1: origen
A2: 2026-01 | B2: {"mes":"2026-01","fuente":"01 - Rol Instructores LP ENERO","hoja":"ENERO","instructores":[{"bp":"2713993","nombre":"Fiorella Ruiz","dias":["DO","HO FILE","FDS","FDS","LCK B767\n- LIM-MIA\n- LA 2694 (13:30-19:30 hrs)","Habilitación B767*\n- MIA-LIM\n- LA 2699 (23:10-05:00 hrs)","Blanco","Reentrenamiento A320F","RTI: PRÁCTICA\nA320F / B767\n(08:30-17:30 hrs)\nINS APOYO TM","FDS","FDS","LCK B787\n- LIM-SCL\n- LA 2697 (09:35-13:00 hrs)\nRecalificación B787\n- SCL-LIM\n- LA 2696 (16:00-19:45 hrs)","HO FILE","LCK B787\n- LIM-SCL\n- LA 2697 (09:35-13:00 hrs)\nHabilitación B787*\n- SCL-LIM\n- LA 2696 (16:00-19:45 hrs)","HO FILE TARDE","RTI: PRÁCTICA\nA320F / B767 / B787\n(08:30-17:30 hrs)\nINS TITULAR","FDS","FDS","LCK B767\n- LIM-MIA\n- LA 2694 (13:30-19:30 hrs)","Reentrenamiento B767\n- MIA-LIM\n- LA 2699 (23:10-05:00 hrs)","Blanco","Inicial G13\nCHEQUEO DGAC\nLA2258 - LA2259 \nLIM - CJA - LIM","HANDS ON B767","FDS","FDS","HO FILE","HO FILE","Inicial G13\nTALLER DÍA 1","HANDS ON B787","Chequeo DGAC B787\n- LIM-SCL\n- LA 2697 (09:35-13:00 hrs)\nHabilitación B787\n- SCL-LIM\n- LA 2696 (16:00-19:45 hrs)","FDS"],"bg":["#ffffff","#999999","#0000ff","#0000ff","#ffc000","#ffc000","#ffc000","#f7caac","#cce0f4","#0000ff","#0000ff","#e88888","#999999","#e88888","#999999","#cce0f4","#0000ff","#0000ff","#ffc000","#ffc000","#ffc000","#38761d","#ffff00","#0000ff","#0000ff","#999999","#999999","#38761d","#ffff00","#e88888","#0000ff"],"fg":["#000000","#000000","#ffffff","#ffffff","#000000","#000000","#000000","#000000","#000000","#ffffff","#ffffff","#000000","#000000","#000000","#000000","#000000","#ffffff","#ffffff","#000000","#000000","#000000","#ffffff","#000000","#ffffff","#ffffff","#000000","#000000","#ffffff","#000000","#000000","#ffffff"]},{"bp":"2396710","nombre":"Sebastian Correa","dias":["DO","Inicial G13 (Recuperatorio)","FDS","FDS","REVA ANUAL INSTRUCTORES\n ALUMNO","Habilitación B787\n- LIM-SCL\n- LA 2697 (09:35-13:00 hrs)\nReentrenamiento B787\n- SCL-LIM\n- LA 2696 (16:00-19:45 hrs)","HO FILE TARDE","HO FILE","HO FILE","FDS","FDS","Ditching Presencial B787 + HANDS ON\nTripulación de Mando\nLP\n(08:30-17:30 hrs)","Inicial G1","RTI: PRÁCTICA\nA320F / B767 / B787\n(08:30-17:30 hrs)\nINS APOYO","RTI: PRÁCTICA\nA320F / B767 / B787\n(08:30-17:30 hrs)\nINS APOYO TM","Inicial G1","FDS","FDS","LCK B787\n- LIM-SCL\n- LA 2697 (09:35-13:00 hrs)\nLCK B787\n- SCL-LIM\n- LA 2696 (16:00-19:45 hrs)","HO FILE TARDE","LCK B787\n- LIM-SCL\n- LA 2697 (09:35-13:00 hrs)\nHabilitación B787*\n- SCL-LIM\n- LA 2696 (16:00-19:45 hrs)","HO FILE TARDE","LCK A320F\nLIM-AQP-LIM\nLA 2123 (09:20-11:00 hrs)\nLA 2124 (11:35-13:10 hrs)\nLCK A320F\nLIM-CIX-LIM\nLA 2312 (14:25-15:55 hrs)\nLA 2313 (16:35-18:00 hrs)","FDS","FDS","Chequeo DGAC B787\n- LIM-SCL\n- LA 2697 (09:35-13:00 hrs)\nChequeo DGAC B787\n- SCL-LIM\n- LA 2696 (16:00-19:45 hrs)","HO FILE TARDE","Chequeo LATAM B787\n- LIM-SCL\n- LA 2697 (09:35-13:00 hrs)\nLCK B787\n- SCL-LIM\n- LA 2696 (16:00-19:45 hrs)","Inicial G2 (TARDE)","CURSO REFRESCO IDE","FDS"],"bg":["#ffffff","#38761d","#0000ff","#0000ff","#ff9900","#e88888","#999999","#999999","#999999","#0000ff","#0000ff","#ff4b4f","#fff2cc","#cce0f4","#cce0f4","#fff2cc","#0000ff","#0000ff","#e88888","#999999","#e88888","#999999","#f7caac","#0000ff","#0000ff","#e88888","#999999","#e88888","#b4a7d6","#00ffff","#0000ff"],"fg":["#000000","#ffffff","#ffffff","#ffffff","#000000","#000000","#000000","#000000","#000000","#ffffff","#ffffff","#ffffff","#000000","#000000","#000000","#000000","#ffffff","#ffffff","#000000","#000000","#000000","#000000","#000000","#ffffff","#ffffff","#000000","#000000","#000000","#ffffff","#000000","#ffffff"]},{"bp":"1271571","nombre":"Christian Rondon","dias":["DO","CAPACITACION RRVV","FDS","FDS","HO FILE","Inicial G13","LCK B787\n- LIM-SCL\n- LA 2697 (09:35-13:00 hrs)\nHABILITACIÓN B787\n- SCL-LIM\n- LA 2696 (16:00-19:45 hrs)","LEVANTAMIENTO INFORMACIÓN INSTRUCCION (TARDE)","REUNIÓN DE SEGURIDAD","FDS","FDS","REVA ANUAL INSTRUCTORES\n ALUMNO","Chequeo LATAM B787\n- LIM-SCL\n- LA 2697 (09:35-13:00 hrs)\nChequeo LATAM B787\n- SCL-LIM\n- LA 2696 (16:00-19:45 hrs)","HO FILE TARDE","ACT\nRRVV","RTI: PRÁCTICA\nA320F / B767 / B787\n(08:30-17:30 hrs)\nINS APOYO","FDS","FDS","Blanco Recojo","LCK B767\n- LIM-MIA\n- LA 2480 (00:15-06:15 hrs)","Chequeo LATAM B767\n- MIA-LIM\n- LA 2481 (15:55-21:40 hrs)","HO FILE TARDE","HANDS ON B787","FDS","FDS","LCK B767\n- LIM-MIA\n- LA 2694 (13:30-19:30 hrs)","Habilitación B767*\n- MIA-LIM\n- LA 2699 (23:10-05:00 hrs)","Blanco","LCK B787\n- LIM-SCL\n- LA 2697 (09:35-13:00 hrs)\nHabilitación B787*\n- SCL-LIM\n- LA 2696 (16:00-19:45 hrs)","CURSO REFRESCO IDE","FDS"],"bg":["#ffffff","#d0e0e3","#0000ff","#0000ff","#999999","#38761d","#e88888","#999999","#999999","#0000ff","#0000ff","#ff9900","#e88888","#999999","#ffff00","#cce0f4","#0000ff","#0000ff","#ffc000","#ffc000","#ffc000","#999999","#ffff00","#0000ff","#0000ff","#ffc000","#ffc000","#ffc000","#e88888","#00ffff","#0000ff"],"fg":["#000000","#000000","#ffffff","#ffffff","#000000","#ffffff","#000000","#000000","#000000","#ffffff","#ffffff","#000000","#000000","#000000","#000000","#000000","#ffffff","#ffffff","#000000","#000000","#000000","#000000","#000000","#ffffff","#ffffff","#000000","#000000","#000000","#000000","#000000","#ffffff"]},{"bp":"2843319","nombre":"Karen Santa Cruz","dias":["DO","CAPACITACION RRVV","DO","DO","Blanco Recojo","LCK B767\n- LIM-MIA\n- LA 2480 (00:15-06:15 hrs)","Acompañamiento de Servicio B767\n- MIA-LIM\n- LA 2481 (15:55-21:40 hrs)","Inicial G13 (Recuperatorio)","RTI: PRÁCTICA\nA320F / B767\n(08:30-17:30 hrs)\nINS APOYO","DO","DO","REVA ANUAL INSTRUCTORES INSTRUCTOR","AUDITORIA PROCAB","CURSO 50%","DO","VACACIONES","VACACIONES","VACACIONES","VACACIONES","VACACIONES","VACACIONES","VACACIONES","VACACIONES","VACACIONES","VACACIONES","VACACIONES","VACACIONES","VACACIONES","VACACIONES","CURSO REFRESCO IDE","HO FILE"],"bg":["#ffffff","#d0e0e3","#ffffff","#ffffff","#ffc000","#ffc000","#ffc000","#38761d","#cce0f4","#ffffff","#ffffff","#ff9900","#ffff00","#ffe599","#ffffff","#ffffcc","#ffffcc","#ffffcc","#ffffcc","#ffffcc","#ffffcc","#ffffcc","#ffffcc","#ffffcc","#ffffcc","#ffffcc","#ffffcc","#ffffcc","#ffffcc","#00ffff","#999999"],"fg":["#000000","#000000","#000000","#000000","#000000","#000000","#000000","#ffffff","#000000","#000000","#000000","#000000","#000000","#000000","#000000","#000000","#000000","#000000","#000000","#000000","#000000","#000000","#000000","#000000","#000000","#000000","#000000","#000000","#000000","#000000","#000000"]},{"bp":"3779550","nombre":"Jennifert Acurio","dias":["DO","DO","DO","DO","HO FILE","LCK A320F\nLIM-AQP-LIM\nLA 2123 (09:20-11:00 hrs)\nLA 2124 (11:35-13:10 hrs)","Inicial G1","Inicial G2","RTI: PRÁCTICA\nA320F / B767\n(08:30-17:30 hrs)\nINS TITULAR","DO","DO","Habilitación B787 (CST)\n- LIM-SCL\n- LA 2697 (09:35-13:00 hrs)\nHabilitación B787 (CST)\n- SCL-LIM\n- LA 2696 (16:00-19:45 hrs)","B","Reva de Servicio\n(08:30-17:30 hrs)\nDÍA 2","LCK B767\n- LIM-BOG\n- LA 2489 (13:00-16:15 hrs)\nLCK B767\n- BOG-LIM\n- LA 2488 (17:20-20:45 hrs)","HO FILE TARDE","DO","DO","HO FILE","Blanco Recojo","LCK B767\n- LIM-MIA\n- LA 2480 (00:15-06:15 hrs)","Acompañamiento de Servicio B767\n- MIA-LIM\n- LA 2695 (16:20-22:00 hrs)","HO FILE TARDE","DO","DO","HO FILE","LCK A320F (VIGILANCIA DGAC) + HAB A320F.\nLA2306 - LA2307\nLIM - PIU - LIM","HO FILE","RTI: PRÁCTICA\nA320F / B767\n(08:30-17:30 hrs)\nINS APOYO TM","CURSO REFRESCO IDE","DO"],"bg":["#ffffff","#ffffff","#ffffff","#ffffff","#999999","#f7caac","#fff2cc","#b4a7d6","#cce0f4","#ffffff","#ffffff","#e88888","#ffffff","#2f5496","#ffc000","#999999","#ffffff","#ffffff","#999999","#ffc000","#ffc000","#ffc000","#999999","#ffffff","#ffffff","#999999","#f7caac","#999999","#cce0f4","#00ffff","#ffffff"],"fg":["#000000","#000000","#000000","#000000","#000000","#000000","#000000","#ffffff","#000000","#000000","#000000","#000000","#000000","#ffffff","#000000","#000000","#000000","#000000","#000000","#000000","#000000","#000000","#000000","#000000","#000000","#000000","#000000","#000000","#000000","#000000","#000000"]},{"bp":"29530","nombre":"Jazmin Guerra","dias":["DO","HO FILE","DO","DO","Inicial G13","Inicial G1","Habilitación B787 (CST)\n- LIM-SCL\n- LA 2697 (09:35-13:00 hrs)\nHabilitación B787 (CST)\n- SCL-LIM\n- LA 2696 (16:00-19:45 hrs)","DO","DO","DO","DO","LCK B767\n- LIM-MIA\n- LA 2694 (13:30-19:30 hrs)","Habilitación 767*\n- MIA-LIM\n- LA 2699 (23:10-05:00 hrs)","Blanco","RTI: PRÁCTICA\nA320F / B767 / B787\n(08:30-17:30 hrs)\nINS APOYO TM","HO FILE","DO","DO","ACOMPAÑAMIENTO EN VUELO","LCK A320F + HAB. A320F\nLIM-CUZ-LIM\nLA2075/LA2076","Blanco Recojo","LCK B767\n- LIM-MIA\n- LA 2480 (00:15-06:15 hrs)","Habilitación B767\n- MIA-LIM\n- LA 2481 (15:55-21:40 hrs)","DO","DO","Situaciones de Emergencia B767\nTripulación de Mando\nLP\n(08:30-17:30 hrs)","Reva de Servicio\n(08:30-17:30 hrs)\nDÍA 1","Ditching Presencial B767 + HANDS ON\nTripulación de Mando\nLP\n(08:30-17:30 hrs)","HO FILE","CURSO REFRESCO IDE","DO"],"bg":["#ffffff","#999999","#ffffff","#ffffff","#38761d","#fff2cc","#e88888","#ffffff","#ffffff","#ffffff","#ffffff","#ffc000","#ffc000","#ffc000","#cce0f4","#999999","#ffffff","#ffffff","#a2c4c9","#f7caac","#ffc000","#ffc000","#ffc000","#ffffff","#ffffff","#ff4b4f","#2f5496","#ff4b4f","#999999","#00ffff","#ffffff"],"fg":["#000000","#000000","#000000","#000000","#ffffff","#000000","#000000","#000000","#000000","#000000","#000000","#000000","#000000","#000000","#000000","#000000","#000000","#000000","#ffffff","#000000","#000000","#000000","#000000","#000000","#000000","#ffffff","#ffffff","#ffffff","#000000","#000000","#000000"]},{"bp":"3217561","nombre":"Claudia Flores","dias":["DO","DO","DO","DO","LCK A320F\nLIM-AQP-LIM\nLA 2115 (13:55-15:25 hrs)\nLA 2114 (16:00-17:35 hrs)","REVA ANUAL INSTRUCTORES\n ALUMNO","LCK A320F\r\nLIM-TCQ-LIM\r\nLA 2245 (09:00-10:50 hrs)\r\nLA 2244 (11:25-13:15 hrs)\r\nLCK A320F\r\nLIM-TPP-LIM\r\nLA 2087 (14:10-15:35 hrs)\r\nLA 2088 (16:10-17:30 hrs)","Inicial G1","Inicial G1","DO","DO","TALLER VOLUNTARIO SEG","HANDS ON B767","HO FILE","Reva de Servicio\n(08:30-17:30 hrs)\nDÍA 1","HO FILE","DO","DO","LCK A320F\r\nLIM-AQP-LIM\r\nLA 2123 (09:20-11:00 hrs)\r\nLA 2124 (11:35-13:10 hrs)\r\nLCK A320F\r\nLIM-CUZ-LIM\r\nLA 2075 (14:25-15:50 hrs)\r\nLA 2076 (16:25-18:00 hrs)","LCK ALUMNO A320F (CCM)\nLIM-PCL-LIM\nLA 2360 (14:05-15:20 hrs)\nLA 2361 (15:55-17:10 hrs)\nLIM-TRU-LIM\nLA 2139 (18:00-19:10 hrs)\nLA 2140 (19:45-21:00 hrs)","HO FILE TARDE","Inicial G13\nCHEQUEO DGAC \nLA2306 - LA2307 \nLIM - PIU - LIM","Habilitación B767\n- LIM-BOG\n- LA 2489 (13:00-16:15 hrs)\nChequeo DGAC B767\n- BOG-LIM\n- LA 2488 (17:20-20:45 hrs)","DO","DO","LCK A320F\nLIM-AQP-LIM\nLA 2115 (13:55-15:25 hrs)\nLA 2114 (16:00-17:35 hrs)","HO FILE","LCK A320F\r\nLIM-AQP-LIM\r\nLA 2123 (09:20-11:00 hrs)\r\nLA 2124 (11:35-13:10 hrs)\r\nLCK A320F\r\nLIM-PCL-LIM\r\nLA 2360 (14:05-15:20 hrs)\r\nLA 2361 (15:55-17:10 hrs)","Inicial G1","CURSO REFRESCO IDE","DO"],"bg":["#ffffff","#ffffff","#ffffff","#ffffff","#f7caac","#ff9900","#f7caac","#fff2cc","#fff2cc","#ffffff","#ffffff","#ffff00","#ffff00","#999999","#2f5496","#999999","#ffffff","#ffffff","#f7caac","#f7caac","#999999","#38761d","#ffc000","#ffffff","#ffffff","#f7caac","#999999","#f7caac","#fff2cc","#00ffff","#ffffff"],"fg":["#000000","#000000","#000000","#000000","#000000","#000000","#000000","#000000","#000000","#000000","#000000","#000000","#000000","#000000","#ffffff","#000000","#000000","#000000","#000000","#000000","#000000","#ffffff","#000000","#000000","#000000","#000000","#000000","#000000","#000000","#000000","#000000"]},{"bp":"2963161","nombre":"Luis Bacigalupo","dias":["DO","CAPACITACION RRVV","DO","DO","REVA ANUAL INSTRUCTORES\n ALUMNO","VISITA AL CAE CON COMUNICACIONES INTERNAS Y EXTERNAS","VISITA AL CAE CON COMUNICACIONES INTERNAS Y EXTERNAS","DO","DO","DO","DO","Blanco Recojo","LCK B767\n- LIM-MIA\n- LA 2480 (00:15-06:15 hrs)","Pasajero 767\n- MIA-LIM\n- LA 2699 (23:10-05:30 hrs)","Blanco","CURSO 50%","DO","DO","Inicial G1","Reva de Servicio\n(08:30-17:30 hrs)\nDÍA 1","INICIAL G13 \nCHEQUEO DGAC\nLA2023 - LA2024\n LIM - PEM - LIM","LCK B767\n- LIM-BOG\n- LA 2489 (13:00-16:15 hrs)\nLCK B767\n- BOG-LIM\n- LA 2488 (17:20-20:45 hrs)","HO FILE TARDE","DO","DO","Inicial G13\nCHEQUEO LATAM\nLA2023 - LA2024 - LA2061 - LA2062\nLIM - PEM - LIM - CUZ - LIM","Blanco Recojo","LCK B767\n- LIM-MIA\n- LA 2480 (00:15-06:15 hrs)","Habilitación B767\n- MIA-LIM\n- LA 2695 (16:20-22:00 hrs)","HO FILE TARDE","DO"],"bg":["#ffffff","#d0e0e3","#ffffff","#ffffff","#ff9900","#999999","#999999","#ffffff","#ffffff","#ffffff","#ffffff","#ffc000","#ffc000","#ffc000","#ffc000","#ffe599","#ffffff","#ffffff","#fff2cc","#2f5496","#38761d","#ffc000","#999999","#ffffff","#ffffff","#38761d","#ffc000","#ffc000","#ffc000","#999999","#ffffff"],"fg":["#000000","#000000","#000000","#000000","#000000","#000000","#000000","#000000","#000000","#000000","#000000","#000000","#000000","#000000","#000000","#000000","#000000","#000000","#000000","#ffffff","#ffffff","#000000","#000000","#000000","#000000","#ffffff","#000000","#000000","#000000","#000000","#000000"]},{"bp":"71348","nombre":"Karla Moz","dias":["LP","LP","LP","LP","LP","LP","LP","LP","LP","LP","LP","LP","LP","LP","LP","LP","LP","LP","LP","LP","LP","LP","LP","LP","LP","LP","LP","LP","LP","LP","LP"],"bg":["#ffffff","#ffffff","#ffffff","#ffffff","#ffffff","#ffffff","#ffffff","#ffffff","#ffffff","#ffffff","#ffffff","#ffffff","#ffffff","#ffffff","#ffffff","#ffffff","#ffffff","#ffffff","#ffffff","#ffffff","#ffffff","#ffffff","#ffffff","#ffffff","#ffffff","#ffffff","#ffffff","#ffffff","#ffffff","#ffffff","#ffffff"],"fg":["#000000","#000000","#000000","#000000","#000000","#000000","#000000","#000000","#000000","#000000","#000000","#000000","#000000","#000000","#000000","#000000","#000000","#000000","#000000","#000000","#000000","#000000","#000000","#000000","#000000","#000000","#000000","#000000","#000000","#000000","#000000"]},{"bp":"967092","nombre":"Erika Dávila","dias":["VACACIONES","VACACIONES","VACACIONES","VACACIONES","VACACIONES","VACACIONES","VACACIONES","Reva de Servicio\n(08:30-17:30 hrs)\nDÍA 1","Reva de Servicio\n(08:30-17:30 hrs)\nDÍA 2","DO","DO","REVA ANUAL INSTRUCTORES\n ALUMNO","RTI: VIRTUAL\nA320F / B767 / B787\n(08:30-17:30 hrs)\nINS TITULAR","RTI: PRÁCTICA\nA320F / B767 / B787\n(08:30-17:30 hrs)\nINS TITULAR","RTI: PRÁCTICA\nA320F / B767 / B787\n(08:30-17:30 hrs)\nINS APOYO TM","HO FILE","DO","DO","CURSO 50%","CURSO 50%","Reva de Servicio\n(08:30-17:30 hrs)\nDÍA 2","Inicial G2","DO","VACACIONES","VACACIONES","VACACIONES","VACACIONES","VACACIONES","VACACIONES","VACACIONES","VACACIONES"],"bg":["#ffffcc","#ffffcc","#ffffcc","#ffffcc","#ffffcc","#ffffcc","#ffffcc","#2f5496","#2f5496","#ffffff","#ffffff","#ff9900","#cce0f4","#cce0f4","#cce0f4","#999999","#ffffff","#ffffff","#ffe599","#ffe599","#2f5496","#b4a7d6","#ffffff","#ffffcc","#ffffcc","#ffffcc","#ffffcc","#ffffcc","#ffffcc","#ffffcc","#ffffcc"],"fg":["#000000","#000000","#000000","#000000","#000000","#000000","#000000","#ffffff","#ffffff","#000000","#000000","#000000","#000000","#000000","#000000","#000000","#000000","#000000","#000000","#000000","#ffffff","#ffffff","#000000","#000000","#000000","#000000","#000000","#000000","#000000","#000000","#000000"]},{"bp":"2369641","nombre":"Elizabeth Torres","dias":["VACACIONES","VACACIONES","VACACIONES","VACACIONES","VACACIONES","VACACIONES","VACACIONES","VACACIONES","VACACIONES","VACACIONES","VACACIONES","VACACIONES","ENTREVISTAS","HO FILE","ACT\nRRVV","LCK A320F\nLIM-PCL-LIM\nLA2360/LA2361","DO","DO","HO FILE","Inicial G13\nCHEQUEO LATAM\nLA2125 - LA2126 - LA2308 - LA2309\t\nLIM - PIU - LIM - PIU - LIM","REVA ANUAL INSTRUCTORES\n ALUMNO","HABILITACIÓN A320F (CCM)\nLIM-TBP-LIM\nLA 2052 (14:00-16:00 hrs)\nLA 2051 (16:40-18:20 hrs)","LCK B767\n- LIM-BOG\n- LA 2489 (13:00-16:15 hrs)\nLCK B767\n- BOG-LIM\n- LA 2488 (17:20-20:45 hrs)","DO","DO","Blanco Recojo","LCK B767\n- LIM-MIA\n- LA 2480 (00:15-06:15 hrs)","Habilitación B767*\n- MIA-LIM\n- LA 2481 (15:55-21:40 hrs)","HO FILE TARDE","Reva de Servicio\n(08:30-17:30 hrs)\nDÍA 2","DO"],"bg":["#ffffcc","#ffffcc","#ffffcc","#ffffcc","#ffffcc","#ffffcc","#ffffcc","#ffffcc","#ffffcc","#ffffcc","#ffffcc","#ffffcc","#999999","#999999","#ffff00","#f7caac","#ffffff","#ffffff","#999999","#38761d","#ff9900","#f7caac","#ffc000","#ffffff","#ffffff","#ffc000","#ffc000","#ffc000","#999999","#2f5496","#ffffff"],"fg":["#000000","#000000","#000000","#000000","#000000","#000000","#000000","#000000","#000000","#000000","#000000","#000000","#000000","#000000","#000000","#000000","#000000","#000000","#000000","#ffffff","#000000","#000000","#000000","#000000","#000000","#000000","#000000","#000000","#000000","#ffffff","#000000"]},{"bp":"2369624","nombre":"Patricia del Pilar Najar","dias":["VACACIONES","VACACIONES","VACACIONES","VACACIONES","VACACIONES","VACACIONES","Reentrenamiento A320F \nAlumna","DO","Habilitación B767 (CCM)\n- LIM-MIA\n- LA 2694 (13:30-19:30 hrs)","Habilitación B767 (CCM)\n- MIA-LIM\n- LA 2699 (23:10-05:00 hrs)","Blanco","REVA ANUAL INSTRUCTORES\n ALUMNO","DO","ENTREVISTAS","ACT\nRRVV","INICIAL G13 (CHEQUEO DGAC) \n- LIM-PIU-LIM \n- LA2125 - LA2126 (08:00 - 10:15 hrs)\n\n INICIAL G13 (CHEQUEO DGAC) \n- LIM-PIU-LIM \n-LA2308 - LA2309 (13:10 - 15:25 hrs)","DO","DO","Inicial G13 \nCHEQUEO LATAM\nLA2052 - LA2051 - LA2135 - LA2136\nLIM - TBP - LIM - TRU - LIM","RESERVA IET TARDE","Reentrenamiento A320F\nLIM-AQP-LIM\n2123/2124","DO","DO","DO","DO","Inicial G1\nVISITA GUIADA","Inicial G1\nVISITA GUIADA","Blanco Recojo","LCK B767\n- LIM-MIA\n- LA 2480 (00:15-06:15 hrs)","Habilitación B767*\n- MIA-LIM\n- LA 2481 (17:55-23:40 hrs)","Blanco"],"bg":["#ffffcc","#ffffcc","#ffffcc","#ffffcc","#ffffcc","#ffffcc","#f7caac","#ffffff","#ffc000","#ffc000","#ffc000","#ff9900","#ffffff","#999999","#ffff00","#38761d","#ffffff","#ffffff","#38761d","#d9d9d9","#f7caac","#ffffff","#ffffff","#ffffff","#ffffff","#fff2cc","#fff2cc","#ffc000","#ffc000","#ffc000","#ffc000"],"fg":["#000000","#000000","#000000","#000000","#000000","#000000","#000000","#000000","#000000","#000000","#000000","#000000","#000000","#000000","#000000","#ffffff","#000000","#000000","#ffffff","#000000","#000000","#000000","#000000","#000000","#000000","#000000","#000000","#000000","#000000","#000000","#000000"]},{"bp":"3134911","nombre":"Javier Zapata","dias":["DO","Inicial G13","DO","DO","REVA ANUAL INSTRUCTORES\n ALUMNO","LCK ALUMNO A320F (CCM)\nLIM-AQP-LIM\nLA 2123 (09:20-11:00 hrs)\nLA 2124 (11:35-13:10 hrs)\nHABILITACIÓN A320F (A320F)\nLIM-AQP-LIM\nLA 2115 (13:55-15:25 hrs)\nLA 2114 (16:00-17:35 hrs)","HO FILE","DO","DO","DO","DO","Inicial G1","LCK B767\n- LIM-MIA\n- LA 2698 (08:25-14:20 hrs)","Habilitación B767\n- MIA-LIM\n- LA 2699 (23:10-05:00 hrs)","Blanco","Inicial G2","DO","DO","HO FILE","Inicial G2","Inicial G2","RTI: PRÁCTICA\nA320F / B767\n(08:30-17:30 hrs)\nINS APOYO TM","Inicial G13\nCHEQUEO DGAC\nLA2274 - LA2275\t\nLIM - CIX - LIM","DO","DO","Inicial G1","HO FILE","HO FILE","LCK B767\n- LIM-BOG\n- LA 2489 (13:00-16:15 hrs)\nLCK B767\n- BOG-LIM\n- LA 2488 (17:20-20:45 hrs)","Reentrenamiento A320F + Recalificación A320F\nLIM-PCL-LIM\n2360/2361","DO"],"bg":["#ffffff","#38761d","#ffffff","#ffffff","#ff9900","#f7caac","#999999","#ffffff","#ffffff","#ffffff","#ffffff","#fff2cc","#ffc000","#ffc000","#ffc000","#b4a7d6","#ffffff","#ffffff","#999999","#b4a7d6","#b4a7d6","#cce0f4","#38761d","#ffffff","#ffffff","#fff2cc","#999999","#999999","#ffc000","#f7caac","#ffffff"],"fg":["#000000","#ffffff","#000000","#000000","#000000","#000000","#000000","#000000","#000000","#000000","#000000","#000000","#000000","#000000","#000000","#ffffff","#000000","#000000","#000000","#ffffff","#ffffff","#000000","#ffffff","#000000","#000000","#000000","#000000","#000000","#000000","#000000","#000000"]},{"bp":"3750335","nombre":"Jefferson Mendez","dias":["DO","HO FILE","DO","DO","LCK A320F\r\nLIM-AQP-LIM\r\nLA 2123 (09:20-11:00 hrs)\r\nLA 2124 (11:35-13:10 hrs)\r\nLCK A320F\r\nLIM-TPP-LIM\r\nLA 2087 (14:10-15:35 hrs)\r\nLA 2088 (16:10-17:30 hrs)","REVA ANUAL INSTRUCTORES\nINSTRUCTOR","LCK A320F\r\nLIM-AQP-LIM\r\nLA 2123 (09:20-11:00 hrs)\r\nLA 2124 (11:35-13:10 hrs)\r\nLCK A320F\r\nLIM-PCL-LIM\r\nLA 2360 (14:05-15:20 hrs)\r\nLA 2361 (15:55-17:10 hrs)","DO","DO","DO","DO","LCK A320F\r\nLIM-TCQ-LIM\r\nLA 2245 (09:00-10:50 hrs)\r\nLA 2244 (11:25-13:15 hrs)\r\nLCK A320F\r\nLIM-TPP-LIM\r\nLA 2087 (14:10-15:35 hrs)\r\nLA 2088 (16:10-17:30 hrs)","Inicial G2","Blanco Recojo","LCK B767\n- LIM-MIA\n- LA 2480 (00:15-06:15 hrs)","Habilitación B767\n- MIA-LIM\n- LA 2481 (15:55-21:40 hrs)","DO","DO","TALLER VOLUNTARIO SEG","Reentrenamiento A320F\r\nLIM-AQP-LIM\r\nLA 2123 (09:20-11:00 hrs)\r\nLA 2124 (11:35-13:10 hrs)\r\nLCK A320F\r\nLIM-PCL-LIM\r\nLA 2360 (14:05-15:20 hrs)\r\nLA 2361 (15:55-17:10 hrs)","Inicial G1","Inicial G1\nVISITA GUIADA","Inicial G1\nVISITA GUIADA","DO","DO","LCK A320F\r\nLIM-AQP-LIM\r\nLA 2123 (09:20-11:00 hrs)\r\nLA 2124 (11:35-13:10 hrs)\r\nLCK A320F\r\nLIM-TPP-LIM\r\nLA 2087 (14:10-15:35 hrs)\r\nLA 2088 (16:10-17:30 hrs)","HO FILE","Reva de Servicio\n(08:30-17:30 hrs)\nDÍA 2","RTI: PRÁCTICA\nA320F / B767\n(08:30-17:30 hrs)\nINS TITULAR","LCK B767\n- LIM-BOG\n- LA 2489 (13:00-16:15 hrs)\nLCK B767\n- BOG-LIM\n- LA 2488 (17:20-20:45 hrs)","DO"],"bg":["#ffffff","#999999","#ffffff","#ffffff","#f7caac","#ff9900","#f7caac","#ffffff","#ffffff","#ffffff","#ffffff","#f7caac","#b4a7d6","#ffc000","#ffc000","#ffc000","#ffffff","#ffffff","#ffff00","#f7caac","#fff2cc","#fff2cc","#fff2cc","#ffffff","#ffffff","#f7caac","#999999","#2f5496","#cce0f4","#ffc000","#ffffff"],"fg":["#000000","#000000","#000000","#000000","#000000","#000000","#000000","#000000","#000000","#000000","#000000","#000000","#ffffff","#000000","#000000","#000000","#000000","#000000","#000000","#000000","#000000","#000000","#000000","#000000","#000000","#000000","#000000","#ffffff","#000000","#000000","#000000"]},{"bp":"3852423","nombre":"Gabriela Ungaro","dias":["DO","Inicial G13","DO","DO","REVA ANUAL INSTRUCTORES\n INSTRUCTOR","LCK A320F\r\nLIM-TCQ-LIM\r\nLA 2245 (09:00-10:50 hrs)\r\nLA 2244 (11:25-13:15 hrs)\r\nLCK A320F\r\nLIM-TPP-LIM\r\nLA 2087 (14:10-15:35 hrs)\r\nLA 2088 (16:10-17:30 hrs)","Reva de Servicio\n(08:30-17:30 hrs)\nDÍA 2","DO","DO","DO","DO","LCK A320F\nLIM-AQP-LIM\nLA 2123 (09:20-11:00 hrs)\nLA 2124 (11:35-13:10 hrs)\nLCK A320F\nLIM-CUZ-LIM\nLA 2075 (14:25-15:50 hrs)\nLA 2076 (16:25-18:00 hrs)","Inicial G13\nCHEQUEO LATAM\nLA2227 - LA2228 - LA2276 \nLIM - TRU - LIM - CUZ - LIM","DO","ACT\nRRVV","CHEQUEO DGAC A320F (50%)\nLIM-PIU-LIM\nLA 2306 (09:35-11:20 hrs)\nLA 2307 (11:55-13:25 hrs)","DO","DO","TALLER VOLUNTARIO SEG","Inicial G1","Inicial G13 \nCHEQUEO DGAC\nLA2238 - LA2239 \nLIM - CUZ - LIM","LCK A320F\nLIM-AQP-LIM\nLA 2123 (09:20-11:00 hrs)\nLA 2124 (11:35-13:10 hrs)\nLCK A320F\nLIM-TPP-LIM\nLA 2087 (14:10-15:35 hrs)\nLA 2088 (16:10-17:30 hrs)","Inicial G2","DO","DO","Recalificación A320F + Habilitación A320F\nLIM-CUZ-LIM\nLA 2238 (10:15-11:40 hrs)\nLA 2239 (12:15-13:45 hrs)","DESCANSO MÉDICO","DESCANSO MÉDICO","Inicial G1","LCK A320F\r\nLIM-PIU-LIM\r\nLA 2306 (09:35-11:20 hrs)\r\nLA 2307 (11:55-13:25 hrs)\r\nLCK A320F\r\nLIM-CIX-LIM\r\nLA 2312 (14:25-15:55 hrs)\r\nLA 2313 (16:35-18:00 hrs)","DO"],"bg":["#ffffff","#38761d","#ffffff","#ffffff","#ff9900","#f7caac","#2f5496","#ffffff","#ffffff","#ffffff","#ffffff","#f7caac","#38761d","#ffffff","#ffff00","#f7caac","#ffffff","#ffffff","#ffff00","#fff2cc","#38761d","#f7caac","#b4a7d6","#ffffff","#ffffff","#f7caac","#fce5cd","#fce5cd","#fff2cc","#f7caac","#ffffff"],"fg":["#000000","#ffffff","#000000","#000000","#000000","#000000","#ffffff","#000000","#000000","#000000","#000000","#000000","#ffffff","#000000","#000000","#000000","#000000","#000000","#000000","#000000","#ffffff","#000000","#ffffff","#000000","#000000","#000000","#000000","#000000","#000000","#000000","#000000"]},{"bp":"2604360","nombre":"Mariella Carrasco","dias":["DO","DO","DO","DO","Inicial G13","Reva de Servicio\n(08:30-17:30 hrs)\nDÍA 1","Reentrenamiento A320F + Habilitación A320F","HO FILE","Inicial G2","DO","DO","LCK A320F\r\nLIM-CIX-LIM\r\nLA 2274 (09:40-11:10 hrs)\r\nLA 2275 (11:45-13:05 hrs)\r\nLCK A320F\r\nLIM-AQP-LIM\r\nLA 2115 (13:55-15:25 hrs)\r\nLA 2114 (16:00-17:35 hrs)","HO FILE","Inicial G2","Inicial G13\nCHEQUEO LATAM\nLA2184 - LA2183 \nLIM - AYP - LIM","HO FILE","DO","DO","HO FILE","HO FILE","Inicial G13 \nCHEQUEO DGAC\nLA2260- LA2261 \nLIM - PEM- LIM","Inicial G13 \nCHEQUEO DGAC\nLA2081 - LA2082 \nLIM - TPP - LIM","Chequeo DGAC B767\n- LIM-BOG\n- LA 2489 (13:00-16:15 hrs)\nLCK ALUMNA B767 (CST)\n- BOG-LIM\n- LA 2488 (17:20-20:45 hrs)","DO","DO","HO FILE","LCK B767\n- LIM-MIA\n- LA 2698 (08:25-14:20 hrs)","Reentrenamiento B767\n- MIA-LIM\n- LA 2699 (23:10-05:00 hrs)","Blanco","LCK A320F\r\nLIM-AQP-LIM\r\nLA 2123 (09:20-11:00 hrs)\r\nLA 2124 (11:35-13:10 hrs)\r\nLCK A320F\r\nLIM-TPP-LIM\r\nLA 2087 (14:10-15:35 hrs)\r\nLA 2088 (16:10-17:30 hrs)","DO"],"bg":["#ffffff","#ffffff","#ffffff","#ffffff","#38761d","#2f5496","#f7caac","#999999","#b4a7d6","#ffffff","#ffffff","#f7caac","#999999","#b4a7d6","#38761d","#999999","#ffffff","#ffffff","#999999","#999999","#38761d","#38761d","#ffc000","#ffffff","#ffffff","#999999","#ffc000","#ffc000","#ffc000","#f7caac","#ffffff"],"fg":["#000000","#000000","#000000","#000000","#ffffff","#ffffff","#000000","#000000","#ffffff","#000000","#000000","#000000","#000000","#ffffff","#ffffff","#000000","#000000","#000000","#000000","#000000","#ffffff","#ffffff","#000000","#000000","#000000","#000000","#000000","#000000","#000000","#000000","#000000"]},{"bp":"2823133","nombre":"Cesar Campos","dias":["DO","CAPACITACION RRVV","DO","DO","Reentrenamiento B767\n- LIM-MIA\n- LA 2694 (13:30-19:30 hrs)","Habilitación B767*\n- MIA-LIM\n- LA 2699 (23:10-05:00 hrs)","Blanco","DO","DO","DO","DO","REVA ANUAL INSTRUCTORES\n ALUMNO","Inicial G13\nCHEQUEO LATAM\nLA2130 - LA2129 - LA2308 - LA2309\nLIM - CUZ - LIM - PIU - LIM","HO FILE","ACT\nRRVV","Reva de Servicio\n(08:30-17:30 hrs)\nDÍA 2","DO","DO","Inicial G13 \nCHEQUEO LATAM\nLA2130 - LA2129 - LA2308 - LA2309 \nLIM - CUZ - LIM - PIU - LIM","RTI: VIRTUAL\nA320F / B767\n(08:30-17:30 hrs)\nINS TITULAR","Inicial G13\nCHEQUEO LATAM\nLA2013 - LA2014 - LA2356 - LA2532\nLIM - CUZ - LIM - CUZ - LIM","RTI: PRÁCTICA\nA320F / B767\n(08:30-17:30 hrs)\nINS TITULAR","HO FILE","DO","DO","HANDS ON B767","HO FILE","Inicial G1","HO FILE","Inicial G2","DO"],"bg":["#ffffff","#d0e0e3","#ffffff","#ffffff","#ffc000","#ffc000","#ffc000","#ffffff","#ffffff","#ffffff","#ffffff","#ff9900","#38761d","#999999","#ffff00","#2f5496","#ffffff","#ffffff","#38761d","#cce0f4","#38761d","#cce0f4","#999999","#ffffff","#ffffff","#ffff00","#999999","#fff2cc","#999999","#b4a7d6","#ffffff"],"fg":["#000000","#000000","#000000","#000000","#000000","#000000","#000000","#000000","#000000","#000000","#000000","#000000","#ffffff","#000000","#000000","#ffffff","#000000","#000000","#ffffff","#000000","#ffffff","#000000","#000000","#000000","#000000","#000000","#000000","#000000","#000000","#ffffff","#000000"]},{"bp":"3189967","nombre":"Kevin Segovia","dias":["DO","HO FILE","DO","DO","HABILITACIÓN A320F (A320F)\nLIM-CJA-LIM\nLA 2291 (05:10-06:30 hrs)\nLA 2290 (07:10-08:10 hrs)\nLCK ALUMNO A320F (CCM)\nLIM-AQP-LIM\nLA 2123 (09:20-11:00 hrs)\nLA 2124 (11:35-13:10 hrs)","REVA ANUAL INSTRUCTORES\n ALUMNO","RTI: VIRTUAL\nA320F / B767\n(08:30-17:30 hrs)\nINS CRM","DO","DO","DO","DO","CURSO 50%","CHEQUEO LATAM A320F (50%)\nLIM-TCQ-LIM\nLA 2245 (09:00-10:50 hrs)\nLA 2244 (11:25-13:15 hrs)","Inicial G1","Inicial G2","ENTREVISTAS","DO","DO","Inicial G13\nCHEQUEO LATAM\nLA2125 - LA2126 - LA2312 - LA2313 \nLIM - PIU - LIM - CIX - LIM","Inicial G13 \n(Recuperatorio)","Habilitación B767 (CCM)\n- LIM-ATL\n- LA 2482 (12:15-19:35 hrs)","Habilitación B767 (CCM)\n- ATL-LIM\n- LA 2483 (22:15-05:00 hrs)","Blanco","DO","DO","CURSO 50%","Inicial G2 (VISITA GUIADA)","Inicial G2 (VISITA GUIADA)","Inicial G2 (VISITA GUIADA)","HO FILE","DO"],"bg":["#ffffff","#999999","#ffffff","#ffffff","#f7caac","#ff9900","#cce0f4","#ffffff","#ffffff","#ffffff","#ffffff","#ffe599","#f7caac","#fff2cc","#b4a7d6","#999999","#ffffff","#ffffff","#38761d","#38761d","#ffc000","#ffc000","#ffc000","#ffffff","#ffffff","#ffe599","#b4a7d6","#b4a7d6","#b4a7d6","#999999","#ffffff"],"fg":["#000000","#000000","#000000","#000000","#000000","#000000","#000000","#000000","#000000","#000000","#000000","#000000","#000000","#000000","#ffffff","#000000","#000000","#000000","#ffffff","#ffffff","#000000","#000000","#000000","#000000","#000000","#000000","#ffffff","#ffffff","#ffffff","#000000","#000000"]},{"bp":"2415373","nombre":"Milagros Salas","dias":["DO","HO FILE","DO","DO","Inicial G1","REVA ANUAL INSTRUCTORES\n ALUMNO","Inicial G2","DO","DO","DO","DO","Inicial G2","Reva de Servicio\n(08:30-17:30 hrs)\nDÍA 1","Inicial G1","DESCANSO MÉDICO","DESCANSO MÉDICO","DO","DO","Inicial G2","Inicial G13\nCHEQUEO LATAM\nLA2147 - LA2148 - LA2087 - LA2088\nLIM - JUL - LIM - TPP - LIM","REVA ANUAL INSTRUCTORES INSTRUCTOR","Reva de Servicio\n(08:30-17:30 hrs)\nDÍA 1","Reva de Servicio\n(08:30-17:30 hrs)\nDÍA 2","DO","DO","Habilitación B767 (CCM)\n- LIM-ATL\n- LA 2482 (12:15-19:35 hrs)","Habilitación B767 (CCM)\n- ATL-LIM\n- LA 2483 (22:15-05:00 hrs)","Blanco","RTI: PRÁCTICA\nA320F / B767\n(08:30-17:30 hrs)\nINS APOYO","Inicial G13\nTALLER DÍA 2","DO"],"bg":["#ffffff","#999999","#ffffff","#ffffff","#fff2cc","#ff9900","#b4a7d6","#ffffff","#ffffff","#ffffff","#ffffff","#b4a7d6","#2f5496","#fff2cc","#fce5cd","#fce5cd","#ffffff","#ffffff","#b4a7d6","#38761d","#ff9900","#2f5496","#2f5496","#ffffff","#ffffff","#ffc000","#ffc000","#ffc000","#cce0f4","#38761d","#ffffff"],"fg":["#000000","#000000","#000000","#000000","#000000","#000000","#ffffff","#000000","#000000","#000000","#000000","#ffffff","#ffffff","#000000","#000000","#000000","#000000","#000000","#ffffff","#ffffff","#000000","#ffffff","#ffffff","#000000","#000000","#000000","#000000","#000000","#000000","#ffffff","#000000"]},{"bp":"2440915","nombre":"Judith Fernandez","dias":["VACACIONES","VACACIONES","VACACIONES","VACACIONES","VACACIONES","VACACIONES","VACACIONES","DO","DO","DO","DO","REVA ANUAL INSTRUCTORES\n ALUMNO","CURSO 50%","HO FILE","Chequeo LATAM B767\n- LIM-BOG\n- LA 2489 (13:00-16:15 hrs)\nHabilitación B767*\n- BOG-LIM\n- LA 2488 (17:20-20:45 hrs)","HO FILE TARDE","DO","DO","Inicial G13\nCHEQUEO LATAM\nLA2147 - LA2148 - LA2087 - LA2088\t\nLIM - JUL - LIM - TPP - LIM","RTI: VIRTUAL\nA320F / B767\n(08:30-17:30 hrs)\nINS CRM","CURSO 50%","RTI: PRÁCTICA\nA320F / B767\n(08:30-17:30 hrs)\nINS APOYO","CURSO 50%","DO","DO","HO FILE","RTI: VIRTUAL\nA320F / B767\n(08:30-17:30 hrs)\nINS CRM","Inicial G1","RTI: PRÁCTICA\nA320F / B767\n(08:30-17:30 hrs)\nINS TITULAR","DO","DO"],"bg":["#ffffcc","#ffffcc","#ffffcc","#ffffcc","#ffffcc","#ffffcc","#ffffcc","#ffffff","#ffffff","#ffffff","#ffffff","#ff9900","#ffe599","#999999","#ffc000","#999999","#ffffff","#ffffff","#38761d","#cce0f4","#ffe599","#cce0f4","#ffe599","#ffffff","#ffffff","#999999","#cce0f4","#fff2cc","#cce0f4","#ffffff","#ffffff"],"fg":["#000000","#000000","#000000","#000000","#000000","#000000","#000000","#000000","#000000","#000000","#000000","#000000","#000000","#000000","#000000","#000000","#000000","#000000","#ffffff","#000000","#000000","#000000","#000000","#000000","#000000","#000000","#000000","#000000","#000000","#000000","#000000"]},{"bp":"3796947","nombre":"Rafael Nieto","dias":["SICK","SICK","SICK","SICK","SICK","CUMP","CUMP","SICK","SICK","SICK","SICK","SICK","SICK","SICK","SICK","SICK","SICK","SICK","SICK","SICK","SICK","SICK","SICK","SICK","SICK","SICK","SICK","SICK","SICK","SICK","SICK"],"bg":["#ffffff","#ffffff","#ffffff","#ffffff","#ffffff","#ffc0cb","#ffc0cb","#ffffff","#ffffff","#ffffff","#ffffff","#ffffff","#ffffff","#ffffff","#ffffff","#ffffff","#ffffff","#ffffff","#ffffff","#ffffff","#ffffff","#ffffff","#ffffff","#ffffff","#ffffff","#ffffff","#ffffff","#ffffff","#ffffff","#ffffff","#ffffff"],"fg":["#000000","#000000","#000000","#000000","#000000","#000000","#000000","#000000","#000000","#000000","#000000","#000000","#000000","#000000","#000000","#000000","#000000","#000000","#000000","#000000","#000000","#000000","#000000","#000000","#000000","#000000","#000000","#000000","#000000","#000000","#000000"]},{"bp":"3841387","nombre":"Gianfranco Celiz","dias":["DO","CURSO 50%","DO","DO","REVA ANUAL INSTRUCTORES\n ALUMNO","Inicial G13","RTI: VIRTUAL\nA320F / B767\n(08:30-17:30 hrs)\nINS TITULAR","DO","DO","DO","DO","TALLER VOLUNTARIO SEG","RTI: VIRTUAL\nA320F / B767 / B787\n(08:30-17:30 hrs)\nINS CRM","HO FILE","DO","VACACIONES","VACACIONES","VACACIONES","VACACIONES","VACACIONES","VACACIONES","VACACIONES","VACACIONES","DO","DO","Inicial G2","RTI: VIRTUAL\nA320F / B767\n(08:30-17:30 hrs)\nINS TITULAR","HO FILE","Reva de Servicio\n(08:30-17:30 hrs)\nDÍA 1","Inicial G1","DO"],"bg":["#ffffff","#ffe599","#ffffff","#ffffff","#ff9900","#38761d","#cce0f4","#ffffff","#ffffff","#ffffff","#ffffff","#ffff00","#cce0f4","#999999","#ffffff","#ffffcc","#ffffcc","#ffffcc","#ffffcc","#ffffcc","#ffffcc","#ffffcc","#ffffcc","#ffffff","#ffffff","#b4a7d6","#cce0f4","#999999","#2f5496","#fff2cc","#ffffff"],"fg":["#000000","#000000","#000000","#000000","#000000","#ffffff","#000000","#000000","#000000","#000000","#000000","#000000","#000000","#000000","#000000","#000000","#000000","#000000","#000000","#000000","#000000","#000000","#000000","#000000","#000000","#ffffff","#000000","#000000","#ffffff","#000000","#000000"]}]} | C2: 46318.36 | D2: Google Sheet
A3: 2026-02 | B3: {"mes":"2026-02","fuente":"02 - Rol Instructores LP FEBRERO","hoja":"FEBRERO","instructores":[{"bp":"2713993","nombre":"Fiorella Ruiz","dias":["FDS","HO FILE","Inicial G3","Inicial G2","RTI: PRÁCTICA\nA320F / B767 / B787\n(08:30-17:30 hrs)\nINS APOYO","HO FILE","FDS","FDS","TALLER 2026 - CONSTRUIR","HANDS ON\nB787","Inicial G13\nTALLER DÍA 3","LCK ALUMNA B767 (CST)\n- LIM-BOG\n- LA 2489 (13:00-16:15 hrs)\nLCK B767\n- BOG-LIM\n- LA 2488 (17:20-20:45 hrs)","REUNIÓN INSTRUCTORES\nTARDE","FDS","FDS","LCK B787\n- LIM-SCL\n- LA 2697 (09:35-13:00 hrs)\nReentrenamiento B787*\n- SCL-LIM\n- LA 2696 (16:00-19:45 hrs)","Webinar Rediseño Servicio BC\nTARDE","HO FILE","HABILITACIÓN A320F (CST)\nLIM-TRU-LIM\nLA 2227 (11:40-12:55 hrs)\nLA 2228 (13:20-14:45 hrs)","Reentrenamiento B767\n- LIM-BOG\n- LA 2486 (13:00-16:15 hrs)\nLCK B767\n- BOG-LIM\n- LA 2487 (17:20-20:45 hrs)","FDS","FDS","TALLER VOLUNTARIO","RTI: VIRTUAL\nA320F / B767\n(08:30-17:30 hrs)\nINS CRM","Blanco Recojo","LCK B767\n- LIM-MIA\n- LA 2480 (00:15-06:15 hrs)","Chequeo DGAC B767\n- MIA-LIM\n- LA 2481 (15:55-21:40 hrs)","FDS"],"bg":["#0000ff","#999999","#93c47d","#a64d79","#cce0f4","#999999","#0000ff","#0000ff","#ffff00","#ffff00","#38761d","#ffc000","#ffff00","#0000ff","#0000ff","#e88888","#f4ed99","#999999","#f7caac","#ffc000","#0000ff","#0000ff","#ffff00","#cce0f4","#ffc000","#ffc000","#ffc000","#0000ff"],"fg":["#ffffff","#000000","#000000","#ffffff","#000000","#000000","#ffffff","#ffffff","#000000","#000000","#ffffff","#000000","#000000","#ffffff","#ffffff","#000000","#000000","#000000","#000000","#000000","#ffffff","#ffffff","#000000","#000000","#000000","#000000","#000000","#ffffff"]},{"bp":"2396710","nombre":"Sebastian Correa","dias":["FDS","LCK B767\n- LIM-MIA\n- LA 2694 (13:30-19:30 hrs)","Chequeo LATAM B767\n- MIA-LIM\n- LA 2699 (23:10-05:00 hrs)","Blanco","RTI: PRÁCTICA\nB767\n(08:30-17:30 hrs)\nINS TITULAR","LCK A320F\nLIM-AQP-LIM\nLA 2119 (08:40-10:10 hrs)\nLA 2118 (10:45-12:10 hrs)\nLCK A320F\nLIM-PIU-LIM\nLA 2308 (13:10-14:50 hrs)\nLA 2309 (15:25-16:55 hrs)","FDS","FDS","TALLER 2026 - CONSTRUIR","LCK A320F\nLIM-CUZ-LIM\nLA 2232 (08:35-10:05 hrs)\nLA 2233 (10:40-12:15 hrs)","Blanco Recojo","LCK B767\n- LIM-MIA\n- LA 2480 (00:15-06:15 hrs)","Chequeo LATAM B767 + Reentrenamiento B767\n- MIA-LIM\n- LA 2481 (15:55-21:40 hrs)","FDS","FDS","Recalifcación A320F + Habilitación A320F\nLIM-CUZ-LIM\nLA 2232 (08:35-10:05 hrs)\nLA 2233 (10:40-12:15 hrs)","Inicial G2 Chequeo LATAM\nLIM-LIM-CUZ-LIM\nLA2130 08:00-08:35\nLA2130 10:00-11:45\nLA2129 12:40-14:00","RTI: PRÁCTICA\nA320F / B767 / B787\n(08:30-17:30 hrs)\nAPOYO TM","LCK A320F\nLIM-AQP-LIM\nLA 2119 (08:40-10:10 hrs)\nLA 2118 (10:45-12:10 hrs)\nLCK A320F\nLIM-PIU-LIM\nLA 2308 (13:10-14:50 hrs)\nLA 2309 (15:25-16:55 hrs)","Chequeo BI Anual INST B767\n- LIM-BOG\n- LA 2486 (13:00-16:15 hrs)\nHabilitación B767\n- BOG-LIM\n- LA 2487 (17:20-20:45 hrs)","FDS","FDS","LCK B767\n- LIM-MIA\n- LA 2698 (08:25-14:20 hrs)","Recalificación B767\n- MIA-LIM\n- LA 2481 (15:55-21:40 hrs)","Inicial G3 TARDE","LCK B787\n- LIM-SCL\n- LA 2697 (09:35-13:00 hrs)\nHabilitación B787*\n- SCL-LIM\n- LA 2696 (16:00-19:45 hrs)","Webinar Rediseño Servicio BC\nTARDE","FDS"],"bg":["#0000ff","#ffc000","#ffc000","#ffc000","#cce0f4","#f7caac","#0000ff","#0000ff","#ffff00","#f7caac","#ffc000","#ffc000","#ffc000","#0000ff","#0000ff","#f7caac","#a64d79","#cce0f4","#f7caac","#ffc000","#0000ff","#0000ff","#ffc000","#ffc000","#93c47d","#e88888","#f4ed99","#0000ff"],"fg":["#ffffff","#000000","#000000","#000000","#000000","#000000","#ffffff","#ffffff","#000000","#000000","#000000","#000000","#000000","#ffffff","#ffffff","#000000","#ffffff","#000000","#000000","#000000","#ffffff","#ffffff","#000000","#000000","#000000","#000000","#000000","#ffffff"]},{"bp":"1271571","nombre":"Christian Rondon","dias":["FDS","RTI ALUMNO","RTI: VIRTUAL\nA320F / B767 / B787\n(08:30-17:30 hrs)\nINS TITULAR\n*Se habilita","RTI: PRÁCTICA\nA320F / B767 / B787\n(08:30-17:30 hrs)\nINS TITULAR\n*Se habilita","RTI: PRÁCTICA\nA320F / B767 / B787\n(08:30-17:30 hrs)\nINS TITULAR\n*Se habilita","LCK B787\n- LIM-SCL\n- LA 2697 (09:35-13:00 hrs)\nHabilitación 787*\n- SCL-LIM\n- LA 2696 (16:00-19:45 hrs)","FDS","FDS","TALLER 2026 - CONSTRUIR","RTI ALUMNO","RTI: PRÁCTICA\nA320F / B767 / B787\n(08:30-17:30 hrs)\nINS APOYO","LCK B787\n- LIM-SCL\n- LA 2697 (09:35-13:00 hrs)\nHabilitación B787*\n- SCL-LIM\n- LA 2696 (16:00-19:45 hrs)","REUNIÓN INSTRUCTORES\nTARDE","FDS","FDS","Blanco Recojo","LCK B767\n- LIM-MIA\n- LA 2480 (00:15-06:15 hrs)","Chequeo LATAM B767\n- MIA-LIM\n- LA 2481 (15:55-21:40 hrs)","HABILITACIÓN A320F (CST)\nLIM-AYP-LIM\nLA 2186 (15:20-16:20 hrs)\nLA 2185 (17:00-17:50 hrs)","Chequeo BI Anual IDE B767\n- LIM-BOG\n- LA 2486 (13:00-16:15 hrs)\nHabilitación B767\n- BOG-LIM\n- LA 2487 (17:20-20:45 hrs)","FDS","FDS","VACACIONES","VACACIONES","VACACIONES","VACACIONES","VACACIONES","VACACIONES"],"bg":["#0000ff","#ffffff","#cce0f4","#cce0f4","#cce0f4","#e88888","#0000ff","#0000ff","#ffff00","#ffffff","#cce0f4","#e88888","#ffff00","#0000ff","#0000ff","#ffc000","#ffc000","#ffc000","#f7caac","#ffc000","#0000ff","#0000ff","#ffffcc","#ffffcc","#ffffcc","#ffffcc","#ffffcc","#ffffcc"],"fg":["#ffffff","#000000","#000000","#000000","#000000","#000000","#ffffff","#ffffff","#000000","#000000","#000000","#000000","#000000","#ffffff","#ffffff","#000000","#000000","#000000","#000000","#000000","#ffffff","#ffffff","#000000","#000000","#000000","#000000","#000000","#000000"]},{"bp":"2843319","nombre":"Karen Santa Cruz","dias":["DO","Blanco Recojo","LCK B767\n- LIM-MIA\n- LA 2480 (00:15-06:15 hrs)","Chequeo LATAM B767\n- MIA-LIM\n- LA 2481 (15:55-21:40 hrs)","Recalificación A320F + Reentrenamiento A320F\nLIM-CJA-LIM\nLA2297/LA2296","Inicial G2","DO","DO","TALLER 2026 - CONSTRUIR","HO FILE","LCK A320F (VIGILANCIA DGAC)\nLIM-CUZ-LIM\nLA 2232 (08:35-10:05 hrs)\nLA 2233 (10:40-12:15 hrs)\nLCK A320F\nLIM-CIX-LIM\nLA 2312 (13:25-14:50 hrs)\nLA 2313 (15:30-16:50 hrs)","RTI: PRÁCTICA\nA320F / B767 / B787\n(08:30-17:30 hrs)\nINS APOYO","Webinar Rediseño Servicio BC (Mañana) + Inicial G3","DO","DO","Inicial G13\nGRADUACIÓN","LCK B767\n- LIM-MIA\n- LA 2698 (08:25-14:20 hrs)","Chequeo LATAM B767\n- MIA-LIM\n- LA 2699 (23:10-05:00 hrs)","Blanco","HABILITACIÓN A320F (CST)\nLIM-CUZ-LIM\nLA 2007 (09:15-10:45 hrs)\nLA 2008 (11:30-12:55 hrs)","DO","DO","DO","DO","INICIAL G1 DGAC\nLIM-CUZ-LIM\nLA2316 08:00-09:25\nLA2317 10:00-11:40\nLIM-PIU-LIM\nLA2308 13:10-14:50\nLA2309 15:25-15:55","Reentrenamiento A320F\nLIM-PCL-LIM\nLA2360/LA2361","INICIAL G1 (CHEQUEO LATAM)\nLIM-TBP-LIM\nLA2052 10:25-12:20\nLA2051 13:00-14:40\nLIM-TRU-LIM\nLA2135 15:30-16:40\nLA2136 17:15-18:25","DO"],"bg":["#ffffff","#ffc000","#ffc000","#ffc000","#f7caac","#a64d79","#ffffff","#ffffff","#ffff00","#999999","#f7caac","#cce0f4","#93c47d","#ffffff","#ffffff","#38761d","#ffc000","#ffc000","#ffc000","#f7caac","#ffffff","#ffffff","#ffffff","#ffffff","#fff2cc","#f7caac","#fff2cc","#ffffff"],"fg":["#000000","#000000","#000000","#000000","#000000","#ffffff","#000000","#000000","#000000","#000000","#000000","#000000","#000000","#000000","#000000","#ffffff","#000000","#000000","#000000","#000000","#000000","#000000","#000000","#000000","#000000","#000000","#000000","#000000"]},{"bp":"3779550","nombre":"Jennifert Acurio","dias":["DO","HO FILE","DITCHING TM\nINS","TALLER VOLUNTARIO","CAPACITACION SOBRE CAFÉ\n(Pasajera)\n- LIM - BOG\n- LA4901 (08:50 - 12:05)","CAPACITACION SOBRE CAFÉ\n(Pasajera)\n- BOG- LIM\n- LA4910 (18:35 - 21:35)","DO","DO","TALLER 2026 - CONSTRUIR","TALLER VOLUNTARIO","HO FILE","Inicial G1 - G2\nSUSTITUTORIO \nPRÁCTICAS CALICADAS","REUNIÓN INSTRUCTORES","DO","DO","CURSO ESTANDARIZACIÓN","Blanco Recojo","LCK B767\n- LIM-MIA\n- LA 2480 (00:15-06:15 hrs)","Habilitación B767\n- MIA-LIM\n- LA 2695 (16:20-22:00 hrs)","DO","DO","DO","Inicial G2 Chequeo Latam\nLIM-CUZ-LIM\nLA2232 08:35-10:05\nLA2233 10:40-12:15\nLIM-IQT-LIM\nLA2234 13:45-15:35\nLA2235 16:10-17:55","INICIAL G1 DGAC\nLIM-CUZ-LIM\nLA2266 11:10-12:35\nLA2267 13:10-14:50","INICIAL G1 DGAC\nLIM-PIU-LIM\nLA2316 11:50-13:30\nLA2317 14:05-15:40","Inicial G13\nTALLER DE SERVICIO\nDIA 4 Y 5\n(Recuperatorio)","LCK B767\n- LIM-BOG\n- LA 2486 (13:00-16:15 hrs)\nRecalificación B767\n- BOG-LIM\n- LA 2487 (17:20-20:45 hrs)","DO"],"bg":["#ffffff","#999999","#92d050","#ffff00","#bf9000","#bf9000","#ffffff","#ffffff","#ffff00","#ffff00","#999999","#fff2cc","#ffff00","#ffffff","#ffffff","#ffff00","#ffc000","#ffc000","#ffc000","#ffffff","#ffffff","#ffffff","#a64d79","#fff2cc","#fff2cc","#38761d","#ffc000","#ffffff"],"fg":["#000000","#000000","#000000","#000000","#ffffff","#ffffff","#000000","#000000","#000000","#000000","#000000","#000000","#000000","#000000","#000000","#000000","#000000","#000000","#000000","#000000","#000000","#000000","#ffffff","#000000","#000000","#ffffff","#000000","#000000"]},{"bp":"29530","nombre":"Jazmin Guerra","dias":["DO","LCK A320F\nLIM-CUZ-LIM\nLA 2232 (08:35-10:05 hrs)\nLA 2233 (10:40-12:15 hrs)\nLCK A320F\nLIM-PIU-LIM\nLA 2308 (13:10-14:50 hrs)\nLA 2309 (15:25-16:55 hrs)","Inicial G2","Reva de Servicio\n(08:30-17:30 hrs)\nDÍA 2","DO","DO","DO","DO","TALLER 2026 - CONSTRUIR","LCK A320F\nLIM-AQP-LIM\nLA 2119 (08:40-10:10 hrs)\nLA 2118 (10:45-12:10 hrs)","HO FILE","LCK A320F\nLIM-AQP-LIM\nLA 2119 (08:40-10:10 hrs)\nLA 2118 (10:45-12:10 hrs)\nLCK A320F\nLIM-PIU-LIM\nLA 2308 (13:10-14:50 hrs)\nLA 2309 (15:25-16:55 hrs)","REUNIÓN INSTRUCTORES","DO","DO","HABILITACIÓN A320F (CCM)\nLIM-CUZ-AQP-LIM\nLA 2005 (06:00-07:25 hrs)\nLA 2328 (08:00-09:05 hrs)\nLA 2104 (09:45-11:15 hrs)","Inicial G2 Chequeo LATAM\nLIM-JUL-LIM\nLA2147 08:45-10:25\nLA2148 11:00-12:45\nLIM-AQP-LIM\nLA2115 13:45-15:15\nLA2114 15:50-17:25","Blanco Recojo","LCK B767\n- LIM-MIA\n- LA 2480 (00:15-06:15 hrs)","Chequeo DGAC B767\n- MIA-LIM\n- LA 2481 (15:55-21:40 hrs)","DO","DO","TALLER VOLUNTARIO","LCK A320F\r\nLIM-CUZ-LIM\r\nLA 2232 (08:35-10:05 hrs)\r\nLA 2233 (10:40-12:15 hrs)\r\nLCK A320F\r\nLIM-CUZ-LIM\r\nLA 2075 (13:25-14:50 hrs)\r\nLA 2076 (15:25-16:45 hrs)","Inicial G2 Chequeo Latam\nLIM-CUZ-LIM\nLA2232 08:35 - 10:05\nLA2233 10:40 - 12:15\nLIM-IQT-LIM\nLA2075 14:25-15:50\nLA2076 16:25-18:00","LCK B767\n- LIM-BOG\n- LA 2486 (13:00-16:15 hrs)\nChequeo DGAC B767\n- BOG-LIM\n- LA 2487 (23:50-03:00 hrs)","Blanco","DO"],"bg":["#ffffff","#f7caac","#a64d79","#2f5496","#ffffff","#ffffff","#ffffff","#ffffff","#ffff00","#f7caac","#999999","#f7caac","#ffff00","#ffffff","#ffffff","#f7caac","#a64d79","#ffc000","#ffc000","#ffc000","#ffffff","#ffffff","#ffff00","#f7caac","#a64d79","#ffc000","#ffc000","#ffffff"],"fg":["#000000","#000000","#ffffff","#ffffff","#000000","#000000","#000000","#000000","#000000","#000000","#000000","#000000","#000000","#000000","#000000","#000000","#ffffff","#000000","#000000","#000000","#000000","#000000","#000000","#000000","#ffffff","#000000","#000000","#000000"]},{"bp":"3217561","nombre":"Claudia Flores","dias":["DO","Inicial G2","LCK B767\n- LIM-MIA\n- LA 2698 (08:25-14:20 hrs)","Chequeo LATAM B767\n- MIA-LIM\n- LA 2699 (23:10-05:00 hrs)","Blanco","Habilitación 787 (CST)\n- LIM-SCL\n- LA 2697 (09:35-13:00 hrs)\nHabilitación 787 (CST)\n- SCL-LIM\n- LA 2696 (16:00-19:45 hrs)","DO","DO","TALLER 2026 - CONSTRUIR","DESCANSO MÉDICO","DESCANSO MÉDICO","ENTREVISTAS","REUNIÓN INSTRUCTORES","DO","DO","Inicial G2 Chequeo LATAM\nLIM-JUL-LIM\nLA2209 07:30-09:05\nLA2210 09:40-11:25\nLIM-TPP-LIM\nLA2087 14:10-15:35\nLA2088 16:10-17:30","RTI: VIRTUAL\nA320F / B767 / B787\n(08:30-17:30 hrs)\nINS CRM","Inicial G13\nTALLER DE SERVICIO\nDIA 5","HANDS ON\nB767","DO","DO","DO","DO","Inicial G2 Chequeo Latam\nLIM-CUZ-LIM\nLA2130 08:00-09:25\nLA2129 10:00-11:40\nLIM-CUZ-LIM\nLA2234 13:45 - 15:35\nLA2235 16:10 - 17:55","Reva de Servicio\n(08:30-17:30 hrs)\nDÍA 2","Inicial G2 Chequeo Latam\nLIM-CUZ-LIM\nLA2232 08:35-10:05\nLA2233 10:40-12:15\nLIM-CIX-LIM\nLA2312 13:25-14:50\nLA2313 15:25-16:45","Inicial G2 Chequeo Latam\nLIM-CUZ-LIM\nLA2238 10:15-11:40\nLA2239 12:15-13:45\nLIM-PIU-LIM\nLA2338 15:00-16:40\nLA2339 17:15-18:45","DO"],"bg":["#ffffff","#a64d79","#ffc000","#ffc000","#ffc000","#e88888","#ffffff","#ffffff","#ffff00","#fce5cd","#fce5cd","#999999","#ffff00","#ffffff","#ffffff","#a64d79","#cce0f4","#38761d","#ffff00","#ffffff","#ffffff","#ffffff","#ffffff","#a64d79","#2f5496","#a64d79","#a64d79","#ffffff"],"fg":["#000000","#ffffff","#000000","#000000","#000000","#000000","#000000","#000000","#000000","#000000","#000000","#000000","#000000","#000000","#000000","#ffffff","#000000","#ffffff","#000000","#000000","#000000","#000000","#000000","#ffffff","#ffffff","#ffffff","#ffffff","#000000"]},{"bp":"2963161","nombre":"Luis Bacigalupo","dias":["DO","AUDITORÍA NB*\nLIM-IQT-LIM\nLA 2234 (17:40-19:30 hrs)\nLA 2235 (20:05-21:50 hrs)","Reva de Servicio\n(08:30-17:30 hrs)\nDÍA 1","LCK A320F\nLIM-AQP-LIM\nLA 2119 (08:40-10:10 hrs)\nLA 2118 (10:45-12:10 hrs)\nLCK A320F\nLIM-CIX-LIM\nLA 2312 (13:25-14:50 hrs)\nLA 2313 (15:30-16:50 hrs)","HO FILE","Inicial G2","DO","DO","TALLER 2026 - CONSTRUIR","ENTREVISTAS","LCK A320F\nLIM-AQP-LIM\nLA 2119 (08:40-10:10 hrs)\nLA 2118 (10:45-12:10 hrs)\nLCK A320F\nLIM-PIU-LIM\nLA 2308 (13:10-14:50 hrs)\nLA 2309 (15:25-16:55 hrs)","Inicial G2 - G1\nSUSTITUTORIO \nPRÁCTICAS CALICADAS","REUNIÓN INSTRUCTORES","DO","DO","LCK A320F\nLIM-AQP-LIM\nLA 2119 (08:40-10:10 hrs)\nLA 2118 (10:45-12:10 hrs)","Inicial G3","RTI: PRÁCTICA\nA320F / B767 / B787\n(08:30-17:30 hrs)\nINS APOYO","HO FILE","DO","DO","DO","DO","HO FILE","Habilitación B787 (CST)\n- LIM-SCL\n- LA 2697 (09:35-13:00 hrs)\nHabilitación B787 (CST)\n- SCL-LIM\n- LA 2696 (16:00-19:45 hrs)","HO FILE","DO","DO"],"bg":["#ffffff","#ffff00","#2f5496","#f7caac","#999999","#a64d79","#ffffff","#ffffff","#ffff00","#999999","#f7caac","#a64d79","#ffff00","#ffffff","#ffffff","#f7caac","#93c47d","#cce0f4","#999999","#ffffff","#ffffff","#ffffff","#ffffff","#999999","#e88888","#999999","#ffffff","#ffffff"],"fg":["#000000","#000000","#ffffff","#000000","#000000","#ffffff","#000000","#000000","#000000","#000000","#000000","#ffffff","#000000","#000000","#000000","#000000","#000000","#000000","#000000","#000000","#000000","#000000","#000000","#000000","#000000","#000000","#000000","#000000"]},{"bp":"71348","nombre":"Karla Moz","dias":["VACACIONES","VACACIONES","VACACIONES","VACACIONES","VACACIONES","VACACIONES","VACACIONES","LP","LP","LP","LP","LP","LP","LP","LP","LP","LP","LP","LP","LP","LP","LP","LP","LP","LP","LP","LP","LP"],"bg":["#ffffcc","#ffffcc","#ffffcc","#ffffcc","#ffffcc","#ffffcc","#ffffcc","#ffffff","#ffffff","#ffffff","#ffffff","#ffffff","#ffffff","#ffffff","#ffffff","#ffffff","#ffffff","#ffffff","#ffffff","#ffffff","#ffffff","#ffffff","#ffffff","#ffffff","#ffffff","#ffffff","#ffffff","#ffffff"],"fg":["#000000","#000000","#000000","#000000","#000000","#000000","#000000","#000000","#000000","#000000","#000000","#000000","#000000","#000000","#000000","#000000","#000000","#000000","#000000","#000000","#000000","#000000","#000000","#000000","#000000","#000000","#000000","#000000"]},{"bp":"967092","nombre":"Erika Dávila","dias":["VACACIONES","VACACIONES","VACACIONES","VACACIONES","VACACIONES","VACACIONES","VACACIONES","DO","TALLER 2026 - CONSTRUIR","RTI: VIRTUAL\nA320F / B767 / B787\n(08:30-17:30 hrs)\nINS TITULAR","RTI: PRÁCTICA\nA320F / B767 / B787\n(08:30-17:30 hrs)\nINS TITULAR","RTI: PRÁCTICA\nA320F / B767 / B787\n(08:30-17:30 hrs)\nINS APOYO TM","Habilitación B787 (CC)\n- LIM-SCL\n- LA 2697 (09:35-13:00 hrs)\nHabilitación B787 (CC)\n- SCL-LIM\n- LA 2696 (16:00-19:45 hrs)","DO","DO","INICIAL G1 (CHEQUEO LATAM)\nLIM-PIU-LIM\nLA2304 07:10-08:50\nLA2305 09:30-11:05\nLIM-AQP-LIM\nLA2055 12:30-14:00\nLA2056 14:35-16:10","RTI: VIRTUAL\nA320F / B767 / B787\n(08:30-17:30 hrs)\nINS TITULAR","RTI: PRÁCTICA\nA320F / B767 / B787\n(08:30-17:30 hrs)\nINS TITULAR","HO FILE","RTI: PRÁCTICA\nA320F / B767 / B787\n(08:30-17:30 hrs)\nINS TITULAR","DO","DO","Habilitación B767 (CCM)\n- LIM-ATL\n- LA 2482 (12:15-19:35 hrs)","Habilitación B767 (CCM)\n- ATL-LIM\n- LA 2483 (22:15-05:00 hrs)","Blanco","Reva de Servicio\n(08:30-17:30 hrs)\nDÍA 1","Reva de Servicio\n(08:30-17:30 hrs)\nDÍA 2","DO"],"bg":["#ffffcc","#ffffcc","#ffffcc","#ffffcc","#ffffcc","#ffffcc","#ffffcc","#ffffff","#ffff00","#cce0f4","#cce0f4","#cce0f4","#e88888","#ffffff","#ffffff","#fff2cc","#cce0f4","#cce0f4","#999999","#cce0f4","#ffffff","#ffffff","#ffc000","#ffc000","#ffc000","#2f5496","#2f5496","#ffffff"],"fg":["#000000","#000000","#000000","#000000","#000000","#000000","#000000","#000000","#000000","#000000","#000000","#000000","#000000","#000000","#000000","#000000","#000000","#000000","#000000","#000000","#000000","#000000","#000000","#000000","#000000","#ffffff","#ffffff","#000000"]},{"bp":"2369641","nombre":"Elizabeth Torres","dias":["DO","LCK B767\n- LIM-MIA\n- LA 2698 (08:25-14:20 hrs)","Acompañamiento de Servicio B767\n- MIA-LIM\n- LA 2481 (15:55-21:40 hrs)","HO FILE TARDE","INICIAL G1","Inicial G2","DO","DO","TALLER 2026 - CONSTRUIR","HO FILE","HABILITACIÓN A320F (CCM)\nLIM-CUZ-LIM\nLA 2130 (08:00-09:25 hrs)\nLA 2129 (10:00-11:40 hrs)\nLCK ALUMNO A320F (CCM)\nLIM-PIU-LIM\nLA 2308 (13:10-14:50 hrs)\nLA 2309 (15:25-16:55 hrs)","CURSO 50%\nReentranamiento A320F\nLIM - CIX - LIM\nLA 2312 (13:25-14:50 hrs)\nLA 2313 (15:25-16:45 hrs)","Reva de Servicio\n(08:30-17:30 hrs)\nDÍA 2","DO","DO","LCK B767\n- LIM-MIA\n- LA 2698 (08:25-14:20 hrs)","Chequeo LATAM B767 + Reentrenamiento B767\n- MIA-LIM \n- LA 2481 (15:55-21:40 hrs)","HO FILE TARDE\n(NO TOCAR)","DO","DO","DO","DO","Blanco Recojo","LCK B767\n- LIM-MIA\n- LA 2480 (00:15-06:15 hrs)","Chequeo DGAC B767\n- MIA-LIM\n- LA 2481 (15:55-21:40 hrs)","Webinar Rediseño Servicio BC\nTARDE","RTI: PRÁCTICA\nA320F / B767\n(08:30-17:30 hrs)\nINS APOYO","DO"],"bg":["#ffffff","#ffc000","#ffc000","#999999","#fff2cc","#a64d79","#ffffff","#ffffff","#ffff00","#999999","#f7caac","#ffe599","#2f5496","#ffffff","#ffffff","#ffc000","#ffc000","#999999","#ffffff","#ffffff","#ffffff","#ffffff","#ffc000","#ffc000","#ffc000","#f4ed99","#cce0f4","#ffffff"],"fg":["#000000","#000000","#000000","#000000","#000000","#ffffff","#000000","#000000","#000000","#000000","#000000","#000000","#ffffff","#000000","#000000","#000000","#000000","#000000","#000000","#000000","#000000","#000000","#000000","#000000","#000000","#000000","#000000","#000000"]},{"bp":"2369624","nombre":"Patricia del Pilar Najar","dias":["DO","DO","DO","DO","DO","DO","DO","DO","TALLER 2026 - CONSTRUIR","Inicial G3","HO FILE","Inicial G3","INICIAL G13 (DGAC) + REENT. A320F\nLA2232 - LA2233 \nLIM - CUZ - LIM\n+\nCURSO 50% (RECA 50%)\nLA2061- LA2062\nLIM - CUZ - LIM","DO","DO","LCK B767\n- LIM-MIA\n- LA 2694 (13:30-19:30 hrs)","Habilitación B767*\n- MIA-LIM\n- LA 2699 (23:10-05:00 hrs)","Blanco","INICIAL G1 (CHEQUEO LATAM)\nLIM-JUL-LIM\nLA2209 07:30-09:05\nLA2210 09:40-11:25\nLIM-AQP-LIM\nLA2055 12:30-14:00\nLA2056 14:45-16:10","RTI: PRÁCTICA\nA320F / B767 / B787\n(08:30-17:30 hrs)\nINS APOYO","DO","DO","INICIAL G1 LATAM\nLIM-TCQ-LIM\nLA2071 10:30-12:20\nLA2072 12:55-14:45","LCK B767\n- LIM-MIA\n- LA 2698 (08:25-14:20 hrs)","Chequeo DGAC B767\n- MIA-LIM\n- LA 2699 (23:10-05:00 hrs)","Blanco","TTT RRVV\nALUMNO","DO"],"bg":["#ffffff","#ffffff","#ffffff","#ffffff","#ffffff","#ffffff","#ffffff","#ffffff","#ffff00","#93c47d","#999999","#93c47d","#38761d","#ffffff","#ffffff","#ffc000","#ffc000","#ffc000","#fff2cc","#cce0f4","#ffffff","#ffffff","#fff2cc","#ffc000","#ffc000","#ffc000","#674ea7","#ffffff"],"fg":["#000000","#000000","#000000","#000000","#000000","#000000","#000000","#000000","#000000","#000000","#000000","#000000","#ffffff","#000000","#000000","#000000","#000000","#000000","#000000","#000000","#000000","#000000","#000000","#000000","#000000","#000000","#000000","#000000"]},{"bp":"3134911","nombre":"Javier Zapata","dias":["DO","HO FILE","Blanco Recojo","LCK B767\n- LIM-MIA\n- LA 2480 (00:15-06:15 hrs)","Chequeo DGAC B767\n- MIA-LIM\n- LA 2695 (16:20-22:00 hrs)","Reentrenamiento A320F + Recalificación A320F\nLIM-CUZ-LIM\n2276/2277","DO","DO","TALLER 2026 - CONSTRUIR","LCK A320F (VIGILANCIA DGAC)\nLIM-AQP-LIM\nLA 2123 (09:25-11:00 hrs)\nLA 2124 (11:35-13:10 hrs)\nLCK A320F\nLIM-PCL-LIM\nLA 2360 (14:05-15:20 hrs)\nLA 2361 (15:55-17:10 hrs)","Reva de Servicio\n(08:30-17:30 hrs)\nDÍA 2","LCK A320F\r\nLIM-AQP-LIM\r\nLA 2123 (09:25-11:00 hrs)\r\nLA 2124 (11:35-13:10 hrs)\r\nLCK A320F\r\nLIM-TPP-LIM\r\nLA 2087 (14:10-15:35 hrs)\r\nLA 2088 (16:10-17:30 hrs)","LCK B767\n- LIM-BOG\n- LA 2489 (13:00-16:15 hrs)\nChequeo DGAC B767\n- BOG-LIM\n- LA 2488 (17:20-20:45 hrs)","DO","DO","Inicial G3","LCK A320F*\nLIM-AQP-LIM\nLA 2119 (08:40-10:10 hrs)\nLA 2118 (10:45-12:10 hrs)\nLCK A320F\nLIM-PIU-LIM\nLA 2308 (13:10-14:50 hrs)\nLA 2309 (15:25-16:55 hrs)","INICIAL G1 DGAC \nLIM - TPP - LIM\nLA2087 (14:10 - 15:35)\nLA2088 (16:10 - 17:30)","Inicial G3","Inicial G2 (Chequeo DGAC)\nLIM-CJA-LIM\nLA2258 08:05-09:25\nLA2259 10:05-11:15","DO","DO","DO","HO FILE","DO","DO","DO","DO"],"bg":["#ffffff","#999999","#ffc000","#ffc000","#ffc000","#f7caac","#ffffff","#ffffff","#ffff00","#f7caac","#2f5496","#f7caac","#ffc000","#ffffff","#ffffff","#93c47d","#f7caac","#fff2cc","#93c47d","#a64d79","#ffffff","#ffffff","#ffffff","#999999","#ffffff","#ffffff","#ffffff","#ffffff"],"fg":["#000000","#000000","#000000","#000000","#000000","#000000","#000000","#000000","#000000","#000000","#ffffff","#000000","#000000","#000000","#000000","#000000","#000000","#000000","#000000","#ffffff","#000000","#000000","#000000","#000000","#000000","#000000","#000000","#000000"]},{"bp":"3750335","nombre":"Jefferson Mendez","dias":["DO","Inicial G3","LCK A320F\nLIM-CUZ-LIM\nLA 2232 (08:35-10:05 hrs)\nLA 2233 (10:40-12:15 hrs)\nLCK A320F\nLIM-PIU-LIM\nLA 2308 (13:10-14:50 hrs)\nLA 2309 (15:25-16:55 hrs)","Blanco Recojo","LCK B767\n- LIM-MIA\n- LA 2480 (00:15-06:15 hrs)","Chequeo DGAC B767\n- MIA-LIM\n- LA 2481 (15:55-21:40 hrs)","DO","DO","TALLER 2026 - CONSTRUIR","HABILITACIÓN A320F (CCM)\nLIM - UIO - LIM\nLA 2482 (08:50-11:05 hrs)\nLA 2483 (12:15-14:30 hrs)","Situaciones de Emergencia B767\nTripulación de Mando\nLP\n(08:30-17:30 hrs)","LCK B767\n- LIM-BOG\n- LA 2489 (13:00-16:15 hrs)\nChequeo DGAC B767\n- BOG-LIM\n- LA 2488 (17:20-20:45 hrs)","REUNIÓN INSTRUCTORES\nTARDE","DO","DO","Ditching Presencial B767 + HANDS ON\nTripulación de Mando\nLP\n(08:30-17:30 hrs)","Situaciones de Emergencia A320F\nTripulación de Mando\nLP\n(08:30-17:30 hrs)","LCK A320F\nLIM-AQP-LIM\nLA 2119 (08:40-10:10 hrs)\nLA 2118 (10:45-12:10 hrs)\nRecalificación A320F*\nLIM-PIU-LIM\nLA 2308/LA 2309","Inicial G2 Chequeo DGAC\nLIM-CUZ-LIM\nLA2075 14:25-15:50\nLA2076 16:25-18:00","DO","DO","DO","DO","LCK A320F\nLIM-AQP-LIM\nLA 2119 (08:40-10:10 hrs)\nLA 2118 (10:45-12:10 hrs)\nLCK A320F\nLIM-PIU-LIM\nLA 2308 (13:10-14:50 hrs)\nLA 2309 (15:25-16:55 hrs)","REUNIÓN EMBAJADORES","HO FILE","Inicial G3","DO"],"bg":["#ffffff","#93c47d","#f7caac","#ffc000","#ffc000","#ffc000","#ffffff","#ffffff","#ffff00","#f7caac","#ff4b4f","#ffc000","#ffff00","#ffffff","#ffffff","#ff4b4f","#ff4b4f","#f7caac","#a64d79","#ffffff","#ffffff","#ffffff","#ffffff","#f7caac","#ffff00","#999999","#93c47d","#ffffff"],"fg":["#000000","#000000","#000000","#000000","#000000","#000000","#000000","#000000","#000000","#000000","#ffffff","#000000","#000000","#000000","#000000","#ffffff","#ffffff","#000000","#ffffff","#000000","#000000","#000000","#000000","#000000","#000000","#000000","#000000","#000000"]},{"bp":"3852423","nombre":"Gabriela Ungaro","dias":["DO","Inicial G2","INICIAL G1","Inicial G2","INICIAL G1","LCK B767\n- LIM-BOG\n- LA 2489 (13:00-16:15 hrs)\nLCK B767\n- BOG-LIM\n- LA 2488 (17:20-20:45 hrs)","DO","DO","TALLER 2026 - CONSTRUIR","Blanco Recojo","LCK B767\n- LIM-MIA\n- LA 2480 (00:15-06:15 hrs)","Habilitación B767\n- MIA-LIM\n- LA 2695 (16:20-22:00 hrs)","REUNIÓN INSTRUCTORES\nTARDE","DO","DO","Inicial G13\nGRADUACIÓN","Reva de Servicio\n(08:30-17:30 hrs)\nDÍA 1","Inicial G2 Chequeo DGAC\nLIM-CUZ-LIM\nLA2232 08:35-10:05\nLA2233 10:40-12:15\nLIM-CIX-LIM\nLA2312 13:25-14:50\nLA2313 15:30-16:50","LCK B767\n- LIM-BOG\n- LA 2486 (13:00-16:15 hrs)\nChequeo DGAC B767\n- BOG-LIM\n- LA 2487 (17:20-20:45 hrs)","DO","DO","DO","DO","Blanco Recojo","LCK B767\n- LIM-MIA\n- LA 2480 (00:15-06:15 hrs)","Habilitación B767*\n- MIA-LIM\n- LA 2695 (16:20-22:00 hrs)","Recalificación A320F\nLIM-CUZ-LIM\nLA2276/LA2277","DO"],"bg":["#ffffff","#a64d79","#fff2cc","#a64d79","#fff2cc","#ffc000","#ffffff","#ffffff","#ffff00","#ffc000","#ffc000","#ffc000","#ffff00","#ffffff","#ffffff","#38761d","#2f5496","#a64d79","#ffc000","#ffffff","#ffffff","#ffffff","#ffffff","#ffc000","#ffc000","#ffc000","#f7caac","#ffffff"],"fg":["#000000","#ffffff","#000000","#ffffff","#000000","#000000","#000000","#000000","#000000","#000000","#000000","#000000","#000000","#000000","#000000","#ffffff","#ffffff","#ffffff","#000000","#000000","#000000","#000000","#000000","#000000","#000000","#000000","#000000","#000000"]},{"bp":"2604360","nombre":"Mariella Carrasco","dias":["DO","HO FILE","INICIAL G1","TALLER VOLUNTARIO","LCK B767\n- LIM-BOG\n- LA 2489 (13:00-16:15 hrs)\nChequeo DGAC B767\n- BOG-LIM\n- LA 2488 (17:20-20:45 hrs)","DO","DO","VACACIONES","VACACIONES","VACACIONES","VACACIONES","VACACIONES","VACACIONES","VACACIONES","VACACIONES","VACACIONES","VACACIONES","Ditching Presencial A320F + HANDS ON\nTripulación de Mando\nLP\n(08:30-17:30 hrs)","Reva de Servicio\n(08:30-17:30 hrs)\nDÍA 1","INICIAL G1 (CHEQUEO LATAM)\nLIM-CUZ-LIM\nLA2209 08:00-09:25\nLA2210 10:00-11:40\nLIM-AQP-LIM\nLA2055 12:30-14:00\nLA2056 14:45-16:10","DO","DO","LCK B767\n- LIM-MIA\n- LA 2694 (13:30-19:30 hrs)","Chequeo DGAC B767\n- MIA-LIM\n- LA 2699 (23:10-05:00 hrs)","Blanco","Inicial G3","Inicial G3","DO"],"bg":["#ffffff","#999999","#fff2cc","#ffff00","#ffc000","#ffffff","#ffffff","#ffffcc","#ffffcc","#ffffcc","#ffffcc","#ffffcc","#ffffcc","#ffffcc","#ffffcc","#ffffcc","#ffffcc","#ff4b4f","#2f5496","#fff2cc","#ffffff","#ffffff","#ffc000","#ffc000","#ffc000","#93c47d","#93c47d","#ffffff"],"fg":["#000000","#000000","#000000","#000000","#000000","#000000","#000000","#000000","#000000","#000000","#000000","#000000","#000000","#000000","#000000","#000000","#000000","#ffffff","#ffffff","#000000","#000000","#000000","#000000","#000000","#000000","#000000","#000000","#000000"]},{"bp":"2823133","nombre":"Cesar Campos","dias":["DO","HO FILE\n(NO TOCAR)","RTI: VIRTUAL\nA320F / B767 / B787\n(08:30-17:30 hrs)\nINS CRM","Inicial G3","Inicial G3","Inicial G3","DO","DO","TALLER 2026 - CONSTRUIR","HANDS ON\nB767","INICIAL G13 \nCHEQUEO LATAM\nLA2245 - LA2244 - LA2061 - LA2062\nLIM - TCQ - LIM - CUZ - LIM","Reva de Servicio\n(08:30-17:30 hrs)\nDÍA 1","Reentrenamiento A320F\nLIM-CUZ-LIM\nLA2007/LA2008","DO","DO","HANDS ON\nB767","HABILITACIÓN A320F (CCM)\nLIM-CUZ-PEM\nLA 2077 (09:45-11:15 hrs)\nLA 2358 (11:50-12:55 hrs)\nPEM-CUZ-LIM\nLA 2359 (13:35-14:20 hrs)\nLA 2078 (14:55-16:30 hrs)","Reva de Servicio\n(08:30-17:30 hrs)\nDÍA 2","HO FILE","INICIAL G1 (CHEQUEO LATAM)\nLIM-PEM-LIM\nLA2023 08:30-10:15\nLA2024 10:55-12:25\nLIM-CUZ-LIM\nLA2061 13:55-15:20\nLA2062 15:55-17:25","DO","DO","DO","Reva de Servicio\n(08:30-17:30 hrs)\nDÍA 1","RTI: VIRTUAL\nA320F / B767\n(08:30-17:30 hrs)\nINS CRM","DESAYUNO SAB\nMT","TTT RRVV\nINSTRUCTOR","DO"],"bg":["#ffffff","#999999","#cce0f4","#93c47d","#93c47d","#93c47d","#ffffff","#ffffff","#ffff00","#ffff00","#38761d","#2f5496","#f7caac","#ffffff","#ffffff","#ffff00","#f7caac","#2f5496","#999999","#fff2cc","#ffffff","#ffffff","#ffffff","#2f5496","#cce0f4","#ffff00","#674ea7","#ffffff"],"fg":["#000000","#000000","#000000","#000000","#000000","#000000","#000000","#000000","#000000","#000000","#ffffff","#ffffff","#000000","#000000","#000000","#000000","#000000","#ffffff","#000000","#000000","#000000","#000000","#000000","#ffffff","#000000","#000000","#000000","#000000"]},{"bp":"3189967","nombre":"Kevin Segovia","dias":["DO","INICIAL G1","Inicial G2","HO FILE","CAPACITACION SOBRE CAFÉ\n(Pasajero)\n- BOG - LIM\n- LA4901 - LA4910 (08:50 - 12:05)","CAPACITACION SOBRE CAFÉ\n(Pasajero)\n- BOG- LIM\n- LA4910 (18:35 - 21:35)","DO","DO","TALLER 2026 - CONSTRUIR","RTI: VIRTUAL\nA320F / B767 / B787\n(08:30-17:30 hrs)\nINS CRM","Inicial G3","RTI: PRÁCTICA\nA320F / B767 / B787\n(08:30-17:30 hrs)\nINS TITULAR","Inicial G13\nTALLER DE SERVICIO\nDIA 4","DO","DO","Chequeo LATAM + Reentrenamiento B767\n- LIM-MIA\n- LA 2698 (08:25-14:20 hrs)","Reentrenamiento B767\n- MIA-LIM\n- LA 2481 (15:55-21:40 hrs)","Webinar Rediseño Servicio BC\nTARDE","INICIAL G1 (CHEQUEO LATAM)\nLIM-PEM-LIM\nLA2023 08:20-10:10\nLA2024 10:50-12:25\nLIM-AQP-LIM\nLA2115 13:45-15:15\nLA2114 15:50-17:25","DO","DO","DO","DO","RTI: VIRTUAL\nA320F / B767\n(08:30-17:30 hrs)\nINS TITULAR","REUNIÓN EMBAJADORES","Inicial G3","TTT RRVV\nALUMNO","DO"],"bg":["#ffffff","#fff2cc","#a64d79","#999999","#bf9000","#bf9000","#ffffff","#ffffff","#ffff00","#cce0f4","#93c47d","#cce0f4","#38761d","#ffffff","#ffffff","#ffc000","#ffc000","#f4ed99","#fff2cc","#ffffff","#ffffff","#ffffff","#ffffff","#cce0f4","#ffff00","#93c47d","#674ea7","#ffffff"],"fg":["#000000","#000000","#ffffff","#000000","#ffffff","#ffffff","#000000","#000000","#000000","#000000","#000000","#000000","#ffffff","#000000","#000000","#000000","#000000","#000000","#000000","#000000","#000000","#000000","#000000","#000000","#000000","#000000","#000000","#000000"]},{"bp":"2415373","nombre":"Milagros Salas","dias":["DO","INICIAL G1","DITCHING TM\nTC","RTI: PRÁCTICA\nA320F / B767 / B787\n(08:30-17:30 hrs)\nINS APOYO","DO","DO","DO","DO","TALLER 2026 - CONSTRUIR","Reva de Servicio\n(08:30-17:30 hrs)\nDÍA 1","HANDS ON\nB767","HANDS ON\nB767","Curso HB6","DO","DO","Inicial G2 Chequeo LATAM\nLIM-JUL-LIM\nLA2147 08:45-10:25\nLA2148 11:00-12:45\nLIM-TPP-LIM\nLA2087 14:10-15:35\nLA2088 16:10-17:30","HO FILE","Inicial G3","Inicial G13\nTALLER DE SERVICIO\nDIA 1\n(Recuperatorio)","Inicial G13\nTALLER DE SERVICIO\nDIA 2 Y 3\n(Recuperatorio)","DO","DO","Chequeo LATAM B767\n- LIM-MIA\n- LA 2698 (08:25-14:20 hrs)","Chequeo LATAM B767\n- MIA-LIM\n- LA 2481 (15:55-21:40 hrs)","Webinar Rediseño Servicio BC\nTARDE","RTI: PRÁCTICA\nA320F / B767\n(08:30-17:30 hrs)\nINS APOYO","TTT RRVV\nALUMNO","DO"],"bg":["#ffffff","#fff2cc","#92d050","#cce0f4","#ffffff","#ffffff","#ffffff","#ffffff","#ffff00","#2f5496","#ffff00","#ffff00","#274e13","#ffffff","#ffffff","#a64d79","#999999","#93c47d","#38761d","#38761d","#ffffff","#ffffff","#ffc000","#ffc000","#f4ed99","#cce0f4","#674ea7","#ffffff"],"fg":["#000000","#000000","#000000","#000000","#000000","#000000","#000000","#000000","#000000","#ffffff","#000000","#000000","#ffffff","#000000","#000000","#ffffff","#000000","#000000","#ffffff","#ffffff","#000000","#000000","#000000","#000000","#000000","#000000","#000000","#000000"]},{"bp":"2440915","nombre":"Judith Fernandez","dias":["VACACIONES","VACACIONES","VACACIONES","VACACIONES","VACACIONES","VACACIONES","VACACIONES","VACACIONES","VACACIONES","VACACIONES","VACACIONES","VACACIONES","VACACIONES","VACACIONES","DO","Habilitación B767 (CCM)\n- LIM-ATL\n- LA 2482 (12:15-19:35 hrs)","Habilitación B767 (CCM)\n- ATL-LIM\n- LA 2483 (22:15-05:00 hrs)","Blanco","HABILITACIÓN A320F (CCM)\nLIM-CUZ-AQP-LIM\nLA 2005 (06:00-07:25 hrs)\nLA 2328 (08:00-09:05 hrs)\nLA 2104 (09:45-11:15 hrs)","DO","DO","DO","Inicial G3\nVISITA GUIADA","Inicial G3\nVISITA GUIADA","Inicial G3\nVISITA GUIADA","RTI: PRÁCTICA\nA320F / B767\n(08:30-17:30 hrs)\nINS TITULAR","TTT RRVV\nALUMNO","DO"],"bg":["#ffffcc","#ffffcc","#ffffcc","#ffffcc","#ffffcc","#ffffcc","#ffffcc","#ffffcc","#ffffcc","#ffffcc","#ffffcc","#ffffcc","#ffffcc","#ffffcc","#ffffff","#ffc000","#ffc000","#ffc000","#f7caac","#ffffff","#ffffff","#ffffff","#93c47d","#93c47d","#93c47d","#cce0f4","#674ea7","#ffffff"],"fg":["#000000","#000000","#000000","#000000","#000000","#000000","#000000","#000000","#000000","#000000","#000000","#000000","#000000","#000000","#000000","#000000","#000000","#000000","#000000","#000000","#000000","#000000","#000000","#000000","#000000","#000000","#000000","#000000"]},{"bp":"3796947","nombre":"Rafael Nieto","dias":["SICK","SICK","SICK","SICK","SICK","SICK","SICK","SICK","SICK","SICK","SICK","SICK","SICK","SICK","SICK","SICK","SICK","SICK","SICK","SICK","SICK","SICK","SICK","SICK","SICK","SICK","SICK","SICK"],"bg":["#ffffff","#ffffff","#ffffff","#ffffff","#ffffff","#ffffff","#ffffff","#ffffff","#ffffff","#ffffff","#ffffff","#ffffff","#ffffff","#ffffff","#ffffff","#ffffff","#ffffff","#ffffff","#ffffff","#ffffff","#ffffff","#ffffff","#ffffff","#ffffff","#ffffff","#ffffff","#ffffff","#ffffff"],"fg":["#000000","#000000","#000000","#000000","#000000","#000000","#000000","#000000","#000000","#000000","#000000","#000000","#000000","#000000","#000000","#000000","#000000","#000000","#000000","#000000","#000000","#000000","#000000","#000000","#000000","#000000","#000000","#000000"]},{"bp":"3841387","nombre":"Gianfranco Celiz","dias":["DO","Chequeo LATAM B767\n- LIM-MIA\n- LA 2698 (08:25-14:20 hrs)","Chequeo LATAM B767\n- MIA-LIM\n- LA 2481 (15:55-21:40 hrs)","Reentrenamiento A320F\nLIM-CJA-LIM\nLA2297/LA2296","Reva de Servicio\n(08:30-17:30 hrs)\nDÍA 1","Reva de Servicio\n(08:30-17:30 hrs)\nDÍA 2","DO","DO","TALLER 2026 - CONSTRUIR","TALLER VOLUNTARIO","Curso HB6","Curso HB6","Curso HB6","DO","DO","Habilitación B767 (CCM)\n- LIM-LAX\n- LA 2476 (12:00-18:00 hrs)","Habilitación B767 (CCM)\n- LAX-LIM\n- LA 2477 (20:30-08:10 hrs)","Blanco","DESAYUNO SAB +\nEntrevistas","Reva de Servicio\n(08:30-17:30 hrs)\nDÍA 2","DO","DO","DO","DO","RTI: VIRTUAL\nA320F / B767\n(08:30-17:30 hrs)\nINS TITULAR","HO FILE","RTI: PRÁCTICA\nA320F / B767\n(08:30-17:30 hrs)\nINS TITULAR","DO"],"bg":["#ffffff","#ffc000","#ffc000","#f7caac","#2f5496","#2f5496","#ffffff","#ffffff","#ffff00","#ffff00","#274e13","#274e13","#274e13","#ffffff","#ffffff","#ffc000","#ffc000","#ffc000","#ffff00","#2f5496","#ffffff","#ffffff","#ffffff","#ffffff","#cce0f4","#999999","#cce0f4","#ffffff"],"fg":["#000000","#000000","#000000","#000000","#ffffff","#ffffff","#000000","#000000","#000000","#000000","#ffffff","#ffffff","#ffffff","#000000","#000000","#000000","#000000","#000000","#000000","#ffffff","#000000","#000000","#000000","#000000","#000000","#000000","#000000","#000000"]}]} | C3: 46318.36 | D3: Google Sheet
A4: 2026-03 | B4: {"mes":"2026-03","fuente":"03 - Rol Instructores LP MARZO","hoja":"MARZO","instructores":[{"bp":"2713993","nombre":"Fiorella Ruiz","dias":["FDS","HO FILE","LCK B767\n- LIM-ATL\n- LA 2482 (12:15-19:35 hrs)","Habilitación B767*\n- ATL-LIM\n- LA 2483 (22:15-05:00 hrs)","Blanco","RENOVACIÓN INS A320F\nLIM-PIU-LIM\nLA 2306 (09:35-11:20 hrs)\nLA 2307 (11:55-13:25 hrs)","FDS","FDS","PREPARACIÓN\nAUDITORÍA\nPRE IOSA","PREPARACIÓN\nAUDITORÍA\nPRE IOSA","DO","RECURRENTE AUDITOR 2026\n(Pasajero)\nLIM-SCL\nLA 2697 (09:50-15:30 hrs)","RECURRENTE AUDITOR 2026","RECURRENTE AUDITOR 2026\n(Pasajero)\nSCL-LIM\nLA 640 (13:40-15:30 hrs)","FDS","HANDS ON B767","TALLER VOLUNTARIO DE SEGURIDAD","LCK B767\n- LIM-MIA\n- LA 2694 (13:30-19:25 hrs)","Reentrenamiento B767\n- MIA-LIM\n- LA 2695 (16:55-22:40 hrs)","PREPARACIÓN\nAUDITORÍA\nPRE IOSA TARDE","FDS","FDS","VACACIONES","VACACIONES","VACACIONES","VACACIONES","VACACIONES","FDS","FDS","DESCANSO MÉDICO","DESCANSO MÉDICO"],"bg":["#0000ff","#999999","#ffc000","#ffc000","#ffc000","#f4cccc","#0000ff","#0000ff","#ffff00","#ffff00","#0000ff","#fff2cc","#fff2cc","#fff2cc","#0000ff","#ffff00","#ffff00","#ffc000","#ffc000","#ffff00","#0000ff","#0000ff","#ffffcc","#ffffcc","#ffffcc","#ffffcc","#ffffcc","#0000ff","#0000ff","#e6b8af","#e6b8af"],"fg":["#ffffff","#000000","#000000","#000000","#000000","#000000","#ffffff","#ffffff","#000000","#000000","#ffffff","#000000","#000000","#000000","#ffffff","#000000","#000000","#000000","#000000","#000000","#ffffff","#ffffff","#000000","#000000","#000000","#000000","#000000","#ffffff","#ffffff","#000000","#000000"]},{"bp":"2396710","nombre":"Sebastian Correa","dias":["FDS","LCK B767\n- LIM-MIA\n- LA 2698 (08:25-14:20 hrs)","Reentrenamiento B767*\n- MIA-LIM\n- LA 2695 (16:45-22:40 hrs)","Inicial G2 Chequeo DGAC (TARDE)\nLIM-CJA-LIM\nLA2297 15:20-16:40\nLA2296 17:20-18:25","INICIAL G2 Chequeo DGAC\nLIM-CUZ-LIM\nLA 2232 (08:35-10:05 hrs)\nLA 2233 (10:40-12:15 hrs)\nLCK A320F\nLIM-PIU-LIM\nLA 2308 (13:10-14:50 hrs)\nLA 2309 (15:25-16:55 hrs)","HO FILE","FDS","FDS","CUMP","LCK A320F\nLIM-CUZ-LIM\nLA 2232 (08:35-10:05 hrs)\nLA 2233 (10:40-12:15 hrs)\nLCK A320F\nLIM-PIU-LIM\nLA 2308 (13:10-14:50 hrs)\nLA 2309 (15:25-16:55 hrs)","Reva de Servicio\n(08:30-17:30 hrs)\nDÍA 1","Reva de Servicio\n(08:30-17:30 hrs)\nDÍA 2","REUNIÓN INSTRUCTORES","FDS","FDS","LCK B767\n- LIM-MIA\n- LA 2694 (13:30-19:25 hrs)","Habilitación B767*\n- MIA-LIM\n- LA 2699 (23:10-05:00 hrs)","Blanco","Inicial G3 - Taller de Servicio (Día 1)","LCK A320F (VIGILANCIA DGAC)\nLIM-CUZ-LIM\nLA 2232 (08:35-10:05 hrs)\nLA 2233 (10:40-12:15 hrs)\nLCK A320F\nLIM-PIU-LIM\nLA 2308 (13:10-14:50 hrs)\nLA 2309 (15:25-16:55 hrs)","FDS","FDS","LCK B767\n- LIM-ATL\n- LA 2482 (12:15-19:35 hrs)","Habilitación B767*\n- ATL-LIM\n- LA 2483 (22:15-05:00 hrs)","Blanco","RTI: PRÁCTICA\nA320F / B767 / B787\n(08:30-17:30 hrs)\nINS APOYO","LCK A320F\nLIM-CUZ-LIM\nLA 2537 (09:15-10:50 hrs)\nLA 2008 (11:25-12:55 hrs)\nLCK A320F + Habilitación A320F\nLIM-AQP-LIM\nLA 2115 (13:55-15:25 hrs)\nLA 2114 (16:00-17:35 hrs)","FDS","FDS","Chequeo LATAM INICIAL G3\nLIM-AQP-LIM\nLA2119 08:30 -10:00\nLA2118 10:55-12:35\nLIM-TPP-LIM\nLA2087 14:00-15:30\nLA2088 16:05-17:30","LF"],"bg":["#0000ff","#ffc000","#ffc000","#a64d79","#f7caac","#999999","#0000ff","#0000ff","#ffc0cb","#f7caac","#2f5496","#2f5496","#ffe599","#0000ff","#0000ff","#ffc000","#ffc000","#ffc000","#93c47d","#f7caac","#0000ff","#0000ff","#ffc000","#ffc000","#ffc000","#cce0f4","#f7caac","#0000ff","#0000ff","#93c47d","#999999"],"fg":["#ffffff","#000000","#000000","#ffffff","#000000","#000000","#ffffff","#ffffff","#000000","#000000","#ffffff","#ffffff","#000000","#ffffff","#ffffff","#000000","#000000","#000000","#000000","#000000","#ffffff","#ffffff","#000000","#000000","#000000","#000000","#000000","#ffffff","#ffffff","#000000","#000000"]},{"bp":"1271571","nombre":"Christian Rondon","dias":["VACACIONES","HO FILE","LCK A320F\nLIM-CUZ-LIM\nLA 2232 (08:35-10:05 hrs)\nLA 2233 (10:40-12:15 hrs)\nLCK A320F + Habilitación A320F\nLIM-PIU-LIM\nLA 2308 (13:10-14:50 hrs)\nLA 2309 (15:25-16:55 hrs)","HO FILE","HO FILE","HO FILE","FDS","FDS","LCK A320F\nLIM-AQP-LIM\nLA 2123 (09:20-11:00 hrs)\nLA 2124 (11:35-13:10 hrs)\nLCK A320F + Habilitación A320F\nLIM-TPP-LIM\nLA 2087 (14:10-15:35 hrs)\nLA 2088 (16:10-17:30 hrs)","Curso 50%","Inicial G4","LCK A320F\r\nLIM-AQP-LIM\r\nLA 2123 (09:20-11:00 hrs)\r\nLA 2124 (11:35-13:10 hrs)\r\nLCK A320F\r\nLIM-TPP-LIM\r\nLA 2087 (14:10-15:35 hrs)\r\nLA 2088 (16:10-17:30 hrs)","REUNIÓN INSTRUCTORES","FDS","FDS","LCK A320F\r\nLIM-CUZ-LIM\r\nLA 2232 (08:35-10:05 hrs)\r\nLA 2233 (10:40-12:15 hrs)\r\nLCK A320F\r\nLIM-CIX-LIM\r\nLA 2312 (13:25-14:50 hrs)\r\nLA 2313 (15:25-16:45 hrs)","Reva de Servicio\n(08:30-17:30 hrs)\nDÍA 1","Reva de Servicio\n(08:30-17:30 hrs)\nDÍA 2","HO FILE","LCK B787\n- LIM-SCL\n- LA 2697 (09:35-13:00 hrs)\nLCK B787\n- SCL-LIM\n- LA 2696 (16:00-19:45 hrs)","FDS","FDS","HO FILE - REVISION MTC","LCK A320F\nLIM-CUZ-LIM\nLA 2232 (08:35-10:05 hrs)\nLA 2233 (10:40-12:15 hrs)\nLCK A320F\nLIM-PIU-LIM\nLA 2308 (13:10-14:50 hrs)\nLA 2309 (15:25-16:55 hrs)","Reva de Servicio\n(08:30-17:30 hrs)\nDÍA 2","RECA A320F (50%)\nLIM-CUZ-LIM\nLA 2119 (08:00-09:30 hrs)\nLA 2118 (10:15-11:45 hrs)\nRECA A320F (50%) + HAB A320F*\nLIM-AQP-LIM\nLA 2308 (13:10-14:50 hrs)\nLA 2309 (15:25-16:55 hrs)","Inicial G5","FDS","FDS","LCK B767\n- LIM-ATL\n- LA 2482 (12:15-19:35 hrs)","Blanco"],"bg":["#ffffcc","#999999","#f7caac","#999999","#999999","#999999","#0000ff","#0000ff","#f7caac","#ff4b4f","#ffc0cb","#f7caac","#ffe599","#0000ff","#0000ff","#f7caac","#2f5496","#2f5496","#999999","#e88888","#0000ff","#0000ff","#999999","#f7caac","#2f5496","#ea9999","#00b0f0","#0000ff","#0000ff","#ffc000","#ffc000"],"fg":["#000000","#000000","#000000","#000000","#000000","#000000","#ffffff","#ffffff","#000000","#000000","#000000","#000000","#000000","#ffffff","#ffffff","#000000","#ffffff","#ffffff","#000000","#000000","#ffffff","#ffffff","#000000","#000000","#ffffff","#000000","#000000","#ffffff","#ffffff","#000000","#000000"]},{"bp":"2843319","nombre":"Karen Santa Cruz","dias":["DO","DESCANSO MÉDICO","HO FILE","HANDS ON B767","Habilitación B787 (CST)\n- LIM-SCL\n- LA 2697 (09:35-13:00 hrs)\nHabilitación B787 (CST)\n- SCL-LIM\n- LA 2696 (16:00-19:45 hrs)","HO FILE\nTARDE","DO","DO","PREPARACIÓN\nAUDITORÍA\nPRE IOSA","LCK B767\n- LIM-ATL\n- LA 2482 (12:15-19:35 hrs)","Habilitación B767*\n- ATL-LIM\n- LA 2483 (22:15-05:00 hrs)","Blanco","REUNIÓN INSTRUCTORES","DO","DO","DO","DO","LCK A320F + Habilitación A320F\nLIM-CUZ-LIM\nLA2075 / LA2076","HANDS ON B767","PREPARACIÓN\nAUDITORÍA\nPRE IOSA TARDE","DO","DO","LEP / Licencia","LEP / Licencia","LEP / Licencia","LEP / Licencia","LEP / Licencia","DO","DO","HO FILE (NO TOCAR)","HO FILE - REVISION MTC"],"bg":["#ffffff","#e6b8af","#999999","#ffff00","#e88888","#999999","#ffffff","#ffffff","#ffff00","#ffc000","#ffc000","#ffc000","#ffe599","#ffffff","#ffffff","#ffffff","#ffffff","#f7caac","#ffff00","#ffff00","#ffffff","#ffffff","#999999","#999999","#999999","#999999","#999999","#ffffff","#ffffff","#999999","#999999"],"fg":["#000000","#000000","#000000","#000000","#000000","#000000","#000000","#000000","#000000","#000000","#000000","#000000","#000000","#000000","#000000","#000000","#000000","#000000","#000000","#000000","#000000","#000000","#000000","#000000","#000000","#000000","#000000","#000000","#000000","#000000","#000000"]},{"bp":"3779550","nombre":"Jennifert Acurio","dias":["DO","HO FILE","Reva de Servicio\n(08:30-17:30 hrs)\nDÍA 1","Reva de Servicio\n(08:30-17:30 hrs)\nDÍA 2","HANDS ON B767","DO","DO","DO","DO","LCK B767\n- LIM-MIA\n- LA 2698 (08:25-14:20 hrs)","Acompañamiento de Servicio B767\n- MIA-LIM\n- LA 2481 (15:55-21:40 hrs)","Webinar Rediseño Servicio BC\nTARDE","REUNIÓN INSTRUCTORES","DO","DO","Reentrenamiento A320F\r\nLIM-AQP-LIM\r\nLA 2109 (10:30-12:00 hrs)\r\nLA 2108 (12:40-14:15 hrs)","HO FILE ( NO TOCAR)","LCK B767\n- LIM-ATL\n- LA 2482 (12:15-19:35 hrs)","Habilitación B767\n- ATL-LIM\n- LA 2483 (22:15-05:00 hrs)","Blanco","DO","DO","LCK A320F (VIGILANCIA DGAC)\nLIM-CUZ-LIM\nLA 2232 (08:35-10:05 hrs)\nLA 2233 (10:40-12:15 hrs)\nLCK A320F\nLIM-CIX-LIM\nLA 2312 (13:25-14:50 hrs)\nLA 2313 (15:25-16:45 hrs)","Inicial G5","RTI: PRÁCTICA\nA320F / B767 / B787\n(08:30-17:30 hrs)\nINS APOYO","LCK A320F\nLIM-CUZ-LIM\nLA 2232 (08:35-10:05 hrs)\nLA 2233 (10:40-12:15 hrs)\nLCK A320F\nLIM-CIX-LIM\nLA 2312 (13:25-14:50 hrs)\nLA 2313 (15:30-16:50 hrs)","Reva de Servicio\n(08:30-17:30 hrs)\nDÍA 2","DO","DO","HO FILE - REVISION MTC","LCK B767\n- LIM-MIA\n- LA 2698 (08:15-14:20 hrs)"],"bg":["#ffffff","#999999","#2f5496","#2f5496","#ffff00","#ffffff","#ffffff","#ffffff","#ffffff","#ffc000","#ffc000","#f4ed99","#ffe599","#ffffff","#ffffff","#f7caac","#999999","#ffc000","#ffc000","#ffc000","#ffffff","#ffffff","#f7caac","#00b0f0","#cce0f4","#f7caac","#2f5496","#ffffff","#ffffff","#999999","#ffc000"],"fg":["#000000","#000000","#ffffff","#ffffff","#000000","#000000","#000000","#000000","#000000","#000000","#000000","#000000","#000000","#000000","#000000","#000000","#000000","#000000","#000000","#000000","#000000","#000000","#000000","#000000","#000000","#000000","#ffffff","#000000","#000000","#000000","#000000"]},{"bp":"29530","nombre":"Jazmin Guerra","dias":["DO","LCK B767\n- LIM-MIA\n- LA 2694 (13:30-19:25 hrs)","Habilitación B767\n- MIA-LIM\n- LA 2699 (23:10-05:00 hrs)","Blanco","RTI: PRÁCTICA\nA320F / B767\n(08:30-17:30 hrs)\nINS APOYO TM","DO","DO","DO","DO","Inicial G2 - Taller de Servicio (Día 3)","Reentrenamiento B767\n- LIM-MIA\n- LA 2694 (13:30-19:25 hrs)","LCK B767\n- MIA-LIM\n- LA 2695 (16:55-22:40 hrs)","REUNIÓN INSTRUCTORES","DO","DO","LCK A320F + Habilitación A320F\nLIM-AQP-LIM\nLA 2123 (09:20-11:00 hrs)\nLA 2124 (11:35-13:10 hrs)\nLCK A320F\nLIM-CUZ-LIM\nLA 2075 (14:25-15:55 hrs)\nLA 2076 (16:30-18:00 hrs)","CURSO ESTANDARIZACIÓN","LCK A320F\r\nLIM-CUZ-LIM\r\nLA 2232 (08:35-10:05 hrs)\r\nLA 2233 (10:40-12:15 hrs)\r\nLCK A320F\r\nLIM-CIX-LIM\r\nLA 2312 (13:25-14:50 hrs)\r\nLA 2313 (15:30-16:50 hrs)","RTI: PRÁCTICA\nA320F / B767\n(08:30-17:30 hrs)\nINS APOYO TM","RTI: PRÁCTICA\nA320F / B767\n(08:30-17:30 hrs)\nINS APOYO","DO","DO","LCK A320F\nLIM-TPP-LIM\nLA 2087 (14:10-15:35 hrs)\nLA 2088 (16:10-17:30 hrs)","Reva de Servicio\n(08:30-17:30 hrs)\nDÍA 1","LCK B767\n- LIM-MIA\n- LA 2694 (13:30-19:25 hrs)","Habilitación B767*\n- MIA-LIM\n- LA 2695 (16:55-22:40 hrs)","Recalificación A320F+ Chequeo DGAC (Inicial G3)\nLIM-PCL-LIM\nLA2360/LA2361","DO","DO","Inicial G2 - Taller de Servicio (Día 5)","Inicial G4"],"bg":["#ffffff","#ffc000","#ffc000","#ffc000","#cce0f4","#ffffff","#ffffff","#ffffff","#ffffff","#a64d79","#ffc000","#ffc000","#ffe599","#ffffff","#ffffff","#f7caac","#ffd966","#f7caac","#cce0f4","#cce0f4","#ffffff","#ffffff","#f7caac","#2f5496","#ffc000","#ffc000","#f7caac","#ffffff","#ffffff","#a64d79","#ffc0cb"],"fg":["#000000","#000000","#000000","#000000","#000000","#000000","#000000","#000000","#000000","#ffffff","#000000","#000000","#000000","#000000","#000000","#000000","#000000","#000000","#000000","#000000","#000000","#000000","#000000","#ffffff","#000000","#000000","#000000","#000000","#000000","#ffffff","#000000"]},{"bp":"3217561","nombre":"Claudia Flores","dias":["DO","Curso 50%","Curso 50%","Inicial G2 Chequeo DGAC\nLIM-CUZ-LIM\nLA2013 07:35-09:00\nLA2014 09:35-11:10\r\nLIM-CIX-LIM\nLA2682 12:35-14:00\nLA2683 14:35-15:55","Reva de Servicio\n(08:30-17:30 hrs)\nDÍA 1","Inicial G3","DO","DO","LCK B767\n- LIM-MIA\n- LA 2698 (08:25-14:20 hrs)","Habilitación B767*\n- MIA-LIM\n- LA 2695 (16:55-22:40 hrs)","LCK A320F\nLIM-CJA-LIM\nLA2297/LA2296","DO","DO","DO","DO","LCK B767\n- LIM-ATL\n- LA 2482 (12:15-19:35 hrs)","Acompañamiento de Servicio\n- ATL-LIM\n- LA 2483 (22:15-05:00 hrs)","Blanco","PREPARACIÓN\nAUDITORÍA\nPRE IOSA","PREPARACIÓN\nAUDITORÍA\nPRE IOSA","DO","DO","HANDS ON B767","HABILATACIÓN A320F (CST)\nLIM-AQP-LIM\nLA 2109 (10:20-11:50 hrs)\nLA 2108 (14:40-14:15 hrs)","LCK A320F\nLIM-CUZ-LIM\nLA2130/LA2129\n\nInicial G3 Chequeo DGAC\nLIM-CIX-LIM\nLA2682/LA2683","Reva de Servicio\n(08:30-17:30 hrs)\nDÍA 1","Inicial G4","DO","DO","HANDS ON B767","Chequeo LATAM INICIAL G3\nLIM-AQP-LIM\nLA2238 10:10 -11:35\nLA2239 12:15-13:50\nLIM-PEM-LIM\nLA2264 14:55-16:40\nLA2265 17:20-18:55"],"bg":["#ffffff","#ff4b4f","#ff4b4f","#a64d79","#2f5496","#93c47d","#ffffff","#ffffff","#ffc000","#ffc000","#f7caac","#ffffff","#ffffff","#ffffff","#ffffff","#ffc000","#ffc000","#ffc000","#ffff00","#ffff00","#ffffff","#ffffff","#ffff00","#f7caac","#93c47d","#2f5496","#ffc0cb","#ffffff","#ffffff","#ffff00","#93c47d"],"fg":["#000000","#000000","#000000","#ffffff","#ffffff","#000000","#000000","#000000","#000000","#000000","#000000","#000000","#000000","#000000","#000000","#000000","#000000","#000000","#000000","#000000","#000000","#000000","#000000","#000000","#000000","#ffffff","#000000","#000000","#000000","#000000","#000000"]},{"bp":"2963161","nombre":"Luis Bacigalupo","dias":["VACACIONES","VACACIONES","VACACIONES","VACACIONES","VACACIONES","VACACIONES","VACACIONES","DO","HO FILE","HO FILE","HO FILE","HO FILE","HO FILE","DO","DO","HO FILE","HO FILE","HO FILE","PREPARACIÓN\nAUDITORÍA\nPRE IOSA","PREPARACIÓN\nAUDITORÍA\nPRE IOSA","DO","DO","HO FILE","HO FILE","HO FILE","HO FILE","HO FILE","DO","DO","ACTIVIDAD CRM","RESERVA IET"],"bg":["#ffffcc","#ffffcc","#ffffcc","#ffffcc","#ffffcc","#ffffcc","#ffffcc","#ffffff","#d9d9d9","#d9d9d9","#d9d9d9","#d9d9d9","#d9d9d9","#ffffff","#ffffff","#d9d9d9","#d9d9d9","#d9d9d9","#ffff00","#ffff00","#ffffff","#ffffff","#999999","#d9d9d9","#d9d9d9","#d9d9d9","#d9d9d9","#ffffff","#ffffff","#ffff00","#d9d9d9"],"fg":["#000000","#000000","#000000","#000000","#000000","#000000","#000000","#000000","#000000","#000000","#000000","#000000","#000000","#000000","#000000","#000000","#000000","#000000","#000000","#000000","#000000","#000000","#000000","#000000","#000000","#000000","#000000","#000000","#000000","#000000","#000000"]},{"bp":"71348","nombre":"Karla Moz","dias":["LP","LP","LP","LP","LP","LP","LP","LP","LP","LP","LP","LP","LP","LP","LP","LP","LP","LP","LP","LP","LP","LP","LP","LP","LP","LP","LP","LP","LP","LP","LP"],"bg":["#ffffff","#ffffff","#ffffff","#ffffff","#ffffff","#ffffff","#ffffff","#ffffff","#ffffff","#ffffff","#ffffff","#ffffff","#ffffff","#ffffff","#ffffff","#ffffff","#ffffff","#ffffff","#ffffff","#ffffff","#ffffff","#ffffff","#ffffff","#ffffff","#ffffff","#ffffff","#ffffff","#ffffff","#ffffff","#ffffff","#ffffff"],"fg":["#000000","#000000","#000000","#000000","#000000","#000000","#000000","#000000","#000000","#000000","#000000","#000000","#000000","#000000","#000000","#000000","#000000","#000000","#000000","#000000","#000000","#000000","#000000","#000000","#000000","#000000","#000000","#000000","#000000","#000000","#000000"]},{"bp":"967092","nombre":"Erika Dávila","dias":["DO","HABILITACIÓN A320F (CCM)\nLIM-CUZ-AQP-LIM\nLA 2005 (06:00-07:25 hrs)\nLA 2328 (08:00-09:05 hrs)\nLA 2104 (09:45-11:15 hrs)","HO FILE","INICIAL G1\nTALLER DE SERVICIO DIA 2","Curso 50%","Curso 50%","DO","DO","HANDS ON B787","Reva de Servicio\n(08:30-17:30 hrs)\nDÍA 1","Reva de Servicio\n(08:30-17:30 hrs)\nDÍA 2","RTI: PRÁCTICA\nA320F / B767\n(08:30-17:30 hrs)\nINS APOYO TM","REUNIÓN INSTRUCTORES","DO","DO","TALLER VOLUNTARIO DE SEGURIDAD","HANDS ON B787","HANDS ON B787","RTI: PRÁCTICA\nA320F / B767\n(08:30-17:30 hrs)\nINS APOYO","RTI: PRÁCTICA\nA320F / B767\n(08:30-17:30 hrs)\nINS APOYO TM","DO","DO","Chequeo LATAM INICIAL G3\nLIM-CUZ-LIM\nLA2130 08:00-09:25\nLA2129 10:00-11:35\nLIM-CIX-LIM\nLA2682 12:35-14:00\nLA2683 14:35-15:55","RTI: VIRTUAL\nA320F / B767/B787\n(08:30-17:30 hrs)\nINS TITULAR","RTI: PRÁCTICA\nA320F / B767 / B787\n(08:30-17:30 hrs)\nINS TITULAR","RTI: PRÁCTICA\nA320F / B767 / B787\n(08:30-17:30 hrs)\nINS TITULAR","DO","DO","DO","DO","HO FILE - REVISION MTC"],"bg":["#ffffff","#f7caac","#999999","#fff2cc","#ff4b4f","#ff4b4f","#ffffff","#ffffff","#ffff00","#2f5496","#2f5496","#cce0f4","#ffe599","#ffffff","#ffffff","#ffff00","#ffff00","#ffff00","#cce0f4","#cce0f4","#ffffff","#ffffff","#93c47d","#cce0f4","#cce0f4","#cce0f4","#ffffff","#ffffff","#ffffff","#ffffff","#999999"],"fg":["#000000","#000000","#000000","#000000","#000000","#000000","#000000","#000000","#000000","#ffffff","#ffffff","#000000","#000000","#000000","#000000","#000000","#000000","#000000","#000000","#000000","#000000","#000000","#000000","#000000","#000000","#000000","#000000","#000000","#000000","#000000","#000000"]},{"bp":"2369641","nombre":"Elizabeth Torres","dias":["DO","Inicial G2 Chequeo DGAC\nLIM-CUZ-LIM\nLA2130 08:00-09:25\nLA2129 10:00-11:40\nLIM-PIU-LIM\nLA2308 13:10-14:50\nLA2309 15:25-16:55","HO FILE","Blanco","Inicial G3","INICIAL G1\nTALLER DE SERVICIO DIA 3","DO","DO","Curso 50%","Reentrenamiento A320F\nLIM-PIU-LIM\nLA2306/LA2307","LCK B767\n- LIM-ATL\n- LA 2482 (12:15-19:35 hrs)","Habilitación B767*\n- ATL-LIM\n- LA 2483 (22:15-05:00 hrs)","Blanco","DO","DO","CURSO CRM \nRENOVACIÓN IDE","Inicial G4","Curso 50%","Inicial G4\nVISITA GUIADA","Inicial G4\nVISITA GUIADA","DO","DO","Webinar Rediseño Servicio BC","LCK B767\n- LIM-ATL\n- LA 2482 (12:15-19:35 hrs)","Acompañamiento de Servicio B767\n- ATL-LIM\n- LA 2483 (22:15-05:00 hrs)","Blanco","DO","DO","DO","DO","Chequeo LATAM INICIAL G3\nLIM-JUL-LIM\nLA2207 11:35 -13:10\nLA2208 13:50-15:35"],"bg":["#ffffff","#a64d79","#999999","#ffffff","#93c47d","#fff2cc","#ffffff","#ffffff","#ff4b4f","#f7caac","#ffc000","#ffc000","#ffc000","#ffffff","#ffffff","#ffff00","#ffc0cb","#ff4b4f","#ffc0cb","#ffc0cb","#ffffff","#ffffff","#f4ed99","#ffc000","#ffc000","#ffc000","#ffffff","#ffffff","#ffffff","#ffffff","#93c47d"],"fg":["#000000","#ffffff","#000000","#000000","#000000","#000000","#000000","#000000","#000000","#000000","#000000","#000000","#000000","#000000","#000000","#000000","#000000","#000000","#000000","#000000","#000000","#000000","#000000","#000000","#000000","#000000","#000000","#000000","#000000","#000000","#000000"]},{"bp":"2369624","nombre":"Patricia Najar","dias":["DO","HO FILE","Inicial G3","LCK B767\n- LIM-ATL\n- LA 2482 (12:15-19:35 hrs)","Habilitación B767*\n- ATL-LIM\n- LA 2483 (22:15-05:00 hrs)","Blanco","DO","DO","PREPARACIÓN\nAUDITORÍA\nPRE IOSA","PREPARACIÓN\nAUDITORÍA\nPRE IOSA","DO","RECURRENTE AUDITOR 2026\n(Pasajero)\nLIM-SCL\nLA 2697 (09:50-15:30 hrs)","RECURRENTE AUDITOR 2026","RECURRENTE AUDITOR 2026\n(Pasajero)\nSCL-LIM\nLA 640 (13:40-15:30 hrs)","DO","CURSO CRM \nRENOVACIÓN IDE","LCK A320F\r\nLIM-AQP-LIM\r\nLA 2123 (09:20-11:00 hrs)\r\nLA 2124 (11:35-13:10 hrs)\r\nLCK A320F\r\nLIM-PCL-LIM\r\nLA 2360 (14:05-15:20 hrs)\r\nLA 2361 (16:00-17:10 hrs)","Inicial G2 - Taller de Realidad Virtual","LCK A320F\r\nLIM-TCQ-LIM\r\nLA 2245 (09:00-10:50 hrs)\r\nLA 2244 (11:25-13:15 hrs)\r\nLCK A320F\r\nLIM-TPP-LIM\r\nLA 2087 (14:10-15:35 hrs)\r\nLA 2088 (16:10-17:30 hrs)","HO FILE\nMTC","DO","DO","LCK B767\n- LIM-MIA\n- LA 2698 (08:25-14:20 hrs)","Recalificación B767\n- MIA-LIM\n- LA 2695 (16:55-22:40 hrs)","HO FILE TARDE - REVISION MTC","DO","DO","DO","DO","Inicial G4","HANDS ON B767"],"bg":["#ffffff","#999999","#93c47d","#ffc000","#ffc000","#ffc000","#ffffff","#ffffff","#ffff00","#ffff00","#ffffff","#fff2cc","#fff2cc","#fff2cc","#ffffff","#ffff00","#f7caac","#a64d79","#f7caac","#999999","#ffffff","#ffffff","#ffc000","#ffc000","#999999","#ffffff","#ffffff","#ffffff","#ffffff","#ffc0cb","#ffff00"],"fg":["#000000","#000000","#000000","#000000","#000000","#000000","#000000","#000000","#000000","#000000","#000000","#000000","#000000","#000000","#000000","#000000","#000000","#ffffff","#000000","#000000","#000000","#000000","#000000","#000000","#000000","#000000","#000000","#000000","#000000","#000000","#000000"]},{"bp":"3134911","nombre":"Javier Zapata","dias":["VACACIONES","VACACIONES","VACACIONES","VACACIONES","VACACIONES","VACACIONES","VACACIONES","VACACIONES","VACACIONES","VACACIONES","VACACIONES","VACACIONES","VACACIONES","VACACIONES","VACACIONES","VACACIONES","VACACIONES","VACACIONES","VACACIONES","VACACIONES","VACACIONES","VACACIONES","VACACIONES","HO FILE - REVISION MTC","LCK B767\n- LIM-ATL\n- LA 2482 (12:15-19:35 hrs)","Habilitación B767*\n- ATL-LIM\n- LA 2483 (22:15-05:00 hrs)","Blanco","DO","DO","HO FILE - REVISION MTC","Chequeo LATAM INICIAL G3\nLIM-CUZ-LIM\nLA2130 08:00 -09:20\nLA2129 10:05-11:40\nLIM-PIU-LIM\nLA2308 13:00-14:45\nLA2309 15:25-16:55"],"bg":["#ffffcc","#ffffcc","#ffffcc","#ffffcc","#ffffcc","#ffffcc","#ffffcc","#ffffcc","#ffffcc","#ffffcc","#ffffcc","#ffffcc","#ffffcc","#ffffcc","#ffffcc","#ffffcc","#ffffcc","#ffffcc","#ffffcc","#ffffcc","#ffffcc","#ffffcc","#ffffcc","#999999","#ffc000","#ffc000","#ffc000","#ffffff","#ffffff","#999999","#93c47d"],"fg":["#000000","#000000","#000000","#000000","#000000","#000000","#000000","#000000","#000000","#000000","#000000","#000000","#000000","#000000","#000000","#000000","#000000","#000000","#000000","#000000","#000000","#000000","#000000","#000000","#000000","#000000","#000000","#000000","#000000","#000000","#000000"]},{"bp":"3750335","nombre":"Jefferson Mendez","dias":["DO","LCK B767\n- LIM-ATL\n- LA 2482 (12:15-19:35 hrs)","Habilitación B767*\n- ATL-LIM\n- LA 2483 (22:15-05:00 hrs)","Blanco","Inicial G2 Chequeo DGAC\nLIM-JUL-LIM\nLA2147 08:45-10:25\nLA2148 11:05-12:45\r\nLIM-TPP-LIM\nLA2087 14:10-15:35\nLA2088 16:10-17:30","HO FILE","DO","DO","LCK B767\n- LIM-MIA\n- LA 2694 (13:30-19:25 hrs)","Acompañamiento de Servicio B767\n- MIA-LIM\n- LA 2699 (23:10-05:00 hrs)","Blanco","DESAYUNO SAB","REUNIÓN INSTRUCTORES","DO","DO","LCK B767\n- LIM-MIA\n- LA 2698 (08:25-14:20 hrs)","Reentrenamiento B767\n- MIA-LIM\n- LA 2695 (16:55-22:40 hrs)","Recalificación A320F + Acompañamiento de Servicio A320F\nLIM-CJA-LIM\n2297/2296","DO","DO","DO","DO","HO FILE - REVISION MTC","CUMP","CUMP","Inicial G4","Chequeo LATAM INICIAL G3\nLIM-JUL-LIM\nLA2147 08:55-10:30\nLA2148 11:05-12:45\nLIM-TPP-LIM\nLA2087 14:10-15:35\nLA2088 16:10-17:30","DO","DO","LCK B767\n- LIM-MIA\n- LA 2698 (08:15-14:20 hrs)","Acompañamiento de Servicio B767\n- MIA-LIM\n- LA 2695 (16:10-22:00 hrs)"],"bg":["#ffffff","#ffc000","#ffc000","#ffc000","#a64d79","#999999","#ffffff","#ffffff","#ffc000","#ffc000","#ffc000","#ffff00","#ffe599","#ffffff","#ffffff","#ffc000","#ffc000","#f7caac","#ffffff","#ffffff","#ffffff","#ffffff","#999999","#ffc0cb","#ffc0cb","#ffc0cb","#93c47d","#ffffff","#ffffff","#ffc000","#ffc000"],"fg":["#000000","#000000","#000000","#000000","#ffffff","#000000","#000000","#000000","#000000","#000000","#000000","#000000","#000000","#000000","#000000","#000000","#000000","#000000","#000000","#000000","#000000","#000000","#000000","#000000","#000000","#000000","#000000","#000000","#000000","#000000","#000000"]},{"bp":"3852423","nombre":"Gabriela Ungaro","dias":["DO","INICIAL G1 DGAC\nLIM-PIU-LIM\nLA2306 09:35-11:20\nLA2307 11:55-13:25","LCK B767\n- LIM-MIA\n- LA 2698 (08:25-14:20 hrs)","Chequeo DGAC\n- MIA-LIM\n- LA 2481 (15:55-21:40 hrs)","Inicial G2 Chequeo DGAC\nLIM-CUZ-LIM\nLA2075 14:25-15:55\nLA2076 16:30-18:00","LCK A320F\nLIM-CUZ-LIM\nLA 2232 (08:35-10:05 hrs)\nLA 2233 (10:40-12:15 hrs)\nHABILITACIÓN A320F (CCM)\nLIM-PIU-LIM\nLA 2308 (13:10-14:50 hrs)\nLA 2309 (15:25-16:55 hrs)","DO","DO","LCK B767\n- LIM-ATL\n- LA 2482 (12:15-19:35 hrs)","Habilitación B767*\n- ATL-LIM\n- LA 2483 (22:15-05:00 hrs)","Blanco","LCK A320F\r\nLIM-CUZ-LIM\r\nLA 2232 (08:35-10:05 hrs)\r\nLA 2233 (10:40-12:15 hrs)\r\nLCK A320F\r\nLIM-PIU-LIM\r\nLA 2308 (13:10-14:50 hrs)\r\nLA 2309 (15:25-16:55 hrs)","REUNIÓN INSTRUCTORES","DO","DO","HO FILE","LCK B767\n- LIM-MIA\n- LA 2698 (08:25-14:20 hrs)","Chequeo DGAC\n- MIA-LIM\n- LA 2481 (15:55-21:40 hrs)","Webinar Rediseño Servicio BC\nTARDE","HO FILE (NO TOCAR)","DO","DO","TALLER VOLUNTARIO DE SEGURIDAD","VACACIONES","VACACIONES","VACACIONES","VACACIONES","VACACIONES","VACACIONES","VACACIONES","VACACIONES"],"bg":["#ffffff","#fff2cc","#ffc000","#ffc000","#a64d79","#f7caac","#ffffff","#ffffff","#ffc000","#ffc000","#ffc000","#f7caac","#ffe599","#ffffff","#ffffff","#999999","#ffc000","#ffc000","#f4ed99","#999999","#ffffff","#ffffff","#ffff00","#ffffcc","#ffffcc","#ffffcc","#ffffcc","#ffffcc","#ffffcc","#ffffcc","#ffffcc"],"fg":["#000000","#000000","#000000","#000000","#ffffff","#000000","#000000","#000000","#000000","#000000","#000000","#000000","#000000","#000000","#000000","#000000","#000000","#000000","#000000","#000000","#000000","#000000","#000000","#000000","#000000","#000000","#000000","#000000","#000000","#000000","#000000"]},{"bp":"2604360","nombre":"Mariella Carrasco","dias":["DO","Inicial G3","Inicial G3","LCK B767\n- LIM-MIA\n- LA 2694 (13:30-19:25 hrs)","Habilitación B767*\n- MIA-LIM\n- LA 2695 (16:55-22:40 hrs)","HO FILE\nTARDE","DO","DO","PREPARACIÓN\nAUDITORÍA\nPRE IOSA","PREPARACIÓN\nAUDITORÍA\nPRE IOSA","DO","RECURRENTE AUDITOR 2026\n(Pasajero)\nLIM-SCL\nLA 2697 (09:50-15:30 hrs)","RECURRENTE AUDITOR 2026","RECURRENTE AUDITOR 2026\n(Pasajero)\nSCL-LIM\nLA 640 (13:40-15:30 hrs)","DO","HO FILE","LCK B767\n- LIM-ATL\n- LA 2482 (12:15-19:35 hrs)","Habilitación B767*\n- ATL-LIM\n- LA 2483 (22:15-05:00 hrs)","Blanco","Inicial G3 - Taller de Servicio (Día 2)","DO","DO","TALLER VOLUNTARIO DE SEGURIDAD","LCK B767\n- LIM-MIA\n- LA 2698 (08:25-14:20 hrs)","Chequeo DGAC\n- MIA-LIM\n- LA 2481 (15:55-21:40 hrs)","HO FILE TARDE - REVISION MTC","DO","DO","DO","DO","HABILITACIÓN A320F (CCM)\nLIM-CUZ-AQP-LIM\nLA 2005 (06:00-07:20 hrs)\nLA 2328 (08:00-09:05 hrs)\nLA 2104 (09:45-11:25 hrs)"],"bg":["#ffffff","#93c47d","#93c47d","#ffc000","#ffc000","#999999","#ffffff","#ffffff","#ffff00","#ffff00","#ffffff","#fff2cc","#fff2cc","#fff2cc","#ffffff","#999999","#ffc000","#ffc000","#ffc000","#93c47d","#ffffff","#ffffff","#ffff00","#ffc000","#ffc000","#999999","#ffffff","#ffffff","#ffffff","#ffffff","#f7caac"],"fg":["#000000","#000000","#000000","#000000","#000000","#000000","#000000","#000000","#000000","#000000","#000000","#000000","#000000","#000000","#000000","#000000","#000000","#000000","#000000","#000000","#000000","#000000","#000000","#000000","#000000","#000000","#000000","#000000","#000000","#000000","#000000"]},{"bp":"2823133","nombre":"Cesar Campos","dias":["DO","Inicial Chequeo Latam\nLIM-PEM-LIM\nLA2260 10:20-12:05\nLA2261 12:45-14:20","Inicial G2 Chequeo Latam\nLIM-JUL-LIM\nLA2147 08:45-10:25\nLA2148 11:05-12:45\nLIM-TPP-LIM\nLA2087 14:10-15:35\nLA2088 16:10-17:30","Inicial G3","RTI: PRÁCTICA\nA320F / B767\n(08:30-17:30 hrs)\nINS TITULAR","Reva de Servicio\n(08:30-17:30 hrs)\nDÍA 2","DO","DO","INICIAL G1\nTALLER DE SERVICIO DIA 4","INICIAL G1\nTALLER DE SERVICIO DIA 5","INICIAL G1\nTALLER DE REALIDAD VIRTUAL","RTI: PRÁCTICA\nA320F / B767\n(08:30-17:30 hrs)\nINS TITULAR","REUNIÓN INSTRUCTORES","DO","DO","HANDS ON B767 \nALUMNO","RTI: VIRTUAL\nA320F / B767\n(08:30-17:30 hrs)\nINS TITULAR","Inicial G2 - Taller de Realidad Virtual","RTI: PRÁCTICA\nA320F / B767\n(08:30-17:30 hrs)\nINS TITULAR","HO FILE \nMTC","DO","DO","Chequeo LATAM INICIAL G3\nLIM-TCQ-LIM\nLA2071 10:30-12:20\nLA2072 12:55-14:45","RTI: VIRTUAL\nA320F / B767 / B787\n(08:30-17:30 hrs)\nINS CRM","Inicial G4","DO","DO","DO","DO","LCK ALUMNO B767 (CCM)\n- LIM-MIA\n- LA 2698 (08:15-14:20 hrs)","LCK ALUMNO B767 (CCM)\n- MIA-LIM\n- LA 2695 (16:10-22:00 hrs)"],"bg":["#ffffff","#a64d79","#a64d79","#93c47d","#cce0f4","#2f5496","#ffffff","#ffffff","#fff2cc","#fff2cc","#fff2cc","#cce0f4","#ffe599","#ffffff","#ffffff","#ffff00","#cce0f4","#a64d79","#cce0f4","#999999","#ffffff","#ffffff","#93c47d","#cce0f4","#ffc0cb","#ffffff","#ffffff","#ffffff","#ffffff","#ffc000","#ffc000"],"fg":["#000000","#ffffff","#ffffff","#000000","#000000","#ffffff","#000000","#000000","#000000","#000000","#000000","#000000","#000000","#000000","#000000","#000000","#000000","#ffffff","#000000","#000000","#000000","#000000","#000000","#000000","#000000","#000000","#000000","#000000","#000000","#000000","#000000"]},{"bp":"3189967","nombre":"Kevin Segovia","dias":["DO","Inicial G2 Chequeo Latam\nLIM-JUL-LIM\nLA2147 08:45-10:25\nLA2148 11:05-12:45\r\nLIM-TPP-LIM\nLA2087 14:10-15:35\nLA2088 16:10-17:30","RTI: VIRTUAL\nA320F / B767\n(08:30-17:30 hrs)\nINS CRM","Inicial G3","RTI: PRÁCTICA\nA320F / B767\n(08:30-17:30 hrs)\nINS APOYO","HO FILE","DO","DO","PREPARACIÓN\nAUDITORÍA\nPRE IOSA","RTI: VIRTUAL\nA320F / B767\n(08:30-17:30 hrs)\nINS CRM","Inicial G2 - Taller de Servicio (Día 4)","RTI: PRÁCTICA\nA320F / B767\n(08:30-17:30 hrs)\nINS APOYO","REUNIÓN INSTRUCTORES","DO","DO","HANDS ON B767 \nALUMNO","RTI: VIRTUAL\nA320F / B767\n(08:30-17:30 hrs)\nINS CRM","RTI: VIRTUAL\nA320F / B767\n(08:30-17:30 hrs)\nINS TITULAR","Reva de Servicio\n(08:30-17:30 hrs)\nDÍA 1","Reva de Servicio\n(08:30-17:30 hrs)\nDÍA 2","DO","DO","HO FILE - REVISION MTC","LCK ALUMNO B767 (CCM)\n- LIM-MIA\n- LA 2698 (08:25-14:20 hrs)","LCK ALUMNO B767 (CCM)\n- MIA-LIM\n- LA 2481 (15:55-21:40 hrs)","HO FILE TARDE - REVISION MTC","DO","DO","DO","DO","Inicial G5"],"bg":["#ffffff","#a64d79","#cce0f4","#93c47d","#cce0f4","#999999","#ffffff","#ffffff","#ffff00","#cce0f4","#a64d79","#cce0f4","#ffe599","#ffffff","#ffffff","#ffff00","#cce0f4","#cce0f4","#2f5496","#2f5496","#ffffff","#ffffff","#999999","#ffc000","#ffc000","#999999","#ffffff","#ffffff","#ffffff","#ffffff","#00b0f0"],"fg":["#000000","#ffffff","#000000","#000000","#000000","#000000","#000000","#000000","#000000","#000000","#ffffff","#000000","#000000","#000000","#000000","#000000","#000000","#000000","#ffffff","#ffffff","#000000","#000000","#000000","#000000","#000000","#000000","#000000","#000000","#000000","#000000","#000000"]},{"bp":"2415373","nombre":"Milagros Salas","dias":["DO","HO FILE","RTI: VIRTUAL\nA320F / B767\n(08:30-17:30 hrs)\nINS TITULAR","Inicial G2 Chequeo Latam\nLIM-JUL-LIM\nLA2147 08:45-10:25\nLA2148 11:05-12:45\nLIM-CUZ-LIM\nLA2075 14:25-15:55\nLA2076 16:30-18:00","DO","DO","DO","DO","Inicial G2 - Taller de Servicio (Día 2)","RTI: VIRTUAL\nA320F / B767\n(08:30-17:30 hrs)\nINS TITULAR","HANDS ON B767","HABILITACIÓN A320F (CCM)\nLIM-UIO-LIM\nLA 2382 (08:50-11:05 hrs)\nLA 2383 (12:15-14:30 hrs)","REUNIÓN INSTRUCTORES","DO","DO","Inicial G5","Inicial G5","Inicial G5","Inicial G5","Inicial G5","DO","DO","Inicial G5","REENT A320F (50%)\nLIM-CUZ-LIM\nLA 2013 (07:35-09:00 hrs)\nLA 2014 (09:35-11:10 hrs)\nREENT A320F (50%) + HAB A320F*\nLIM-AQP-LIM\nLA 2055 (12:30-14:00 hrs)\nLA 2056 (14:35-16:10 hrs)","Inicial G5","Inicial G5","CEREMONIA GRADUACIÓN\nG1 & G2","DO","DO","Chequeo LATAM INICIAL G3\nLIM-CUZ-LIM\nLA2130 08:00 -09:20\nLA2129 10:05-11:40\nLIM-PIU-LIM\nLA2308 13:00-14:45\nLA2309 15:25-16:55","Reva de Servicio\n(08:30-17:30 hrs)\nDÍA 1"],"bg":["#ffffff","#999999","#cce0f4","#a64d79","#ffffff","#ffffff","#ffffff","#ffffff","#a64d79","#cce0f4","#ffff00","#f7caac","#ffe599","#ffffff","#ffffff","#00b0f0","#00b0f0","#00b0f0","#00b0f0","#00b0f0","#ffffff","#ffffff","#00b0f0","#ea9999","#00b0f0","#00b0f0","#ffd966","#ffffff","#ffffff","#93c47d","#2f5496"],"fg":["#000000","#000000","#000000","#ffffff","#000000","#000000","#000000","#000000","#ffffff","#000000","#000000","#000000","#000000","#000000","#000000","#000000","#000000","#000000","#000000","#000000","#000000","#000000","#000000","#000000","#000000","#000000","#000000","#000000","#000000","#000000","#ffffff"]},{"bp":"2440915","nombre":"Judith Fernandez","dias":["DO","HO FILE","INICIAL G1\nTALLER DE SERVICIO DIA 1","Curso 50%","Inicial G3","Inicial G2 - Taller de Servicio (Día 1)","DO","DO","LCK ALUMNO B767 (CCM)\n- LIM-MIA\n- LA 2694 (13:30-19:25 hrs)","LCK ALUMNO B767 (CCM)\n- MIA-LIM\n- LA 2699 (23:10-05:00 hrs)","Blanco","Reva de Servicio\n(08:30-17:30 hrs)\nDÍA 1","Reva de Servicio\n(08:30-17:30 hrs)\nDÍA 2","DO","DO","TALLER VOLUNTARIO DE SEGURIDAD","TALLER VOLUNTARIO DE SEGURIDAD","RTI: VIRTUAL\nA320F / B767\n(08:30-17:30 hrs)\nINS CRM - TM","Inicial G4","RTI: PRÁCTICA\nA320F / B767\n(08:30-17:30 hrs)\nINS TITULAR","DO","DO","Inicial G4\nVISITA GUIADA","Inicial G4\nVISITA GUIADA","Reva de Servicio\n(08:30-17:30 hrs)\nDÍA 1","Reva de Servicio\n(08:30-17:30 hrs)\nDÍA 2","DO","DO","DO","DO","HO FILE - REVISION MTC"],"bg":["#ffffff","#999999","#fff2cc","#ff4b4f","#93c47d","#a64d79","#ffffff","#ffffff","#ffc000","#ffc000","#ffc000","#2f5496","#2f5496","#ffffff","#ffffff","#ffff00","#ffff00","#cce0f4","#ffc0cb","#cce0f4","#ffffff","#ffffff","#ffc0cb","#ffc0cb","#2f5496","#2f5496","#ffffff","#ffffff","#ffffff","#ffffff","#999999"],"fg":["#000000","#000000","#000000","#000000","#000000","#ffffff","#000000","#000000","#000000","#000000","#000000","#ffffff","#ffffff","#000000","#000000","#000000","#000000","#000000","#000000","#000000","#000000","#000000","#000000","#000000","#ffffff","#ffffff","#000000","#000000","#000000","#000000","#000000"]},{"bp":"3796947","nombre":"Rafael Nieto","dias":["SICK","SICK","SICK","SICK","SICK","SICK","SICK","SICK","SICK","SICK","SICK","SICK","SICK","SICK","SICK","SICK","SICK","SICK","SICK","SICK","SICK","SICK","SICK","SICK","SICK","SICK","SICK","SICK","SICK","SICK","SICK"],"bg":["#ffffff","#ffffff","#ffffff","#ffffff","#ffffff","#ffffff","#ffffff","#ffffff","#ffffff","#ffffff","#ffffff","#ffffff","#ffffff","#ffffff","#ffffff","#ffffff","#ffffff","#ffffff","#ffffff","#ffffff","#ffffff","#ffffff","#ffffff","#ffffff","#ffffff","#ffffff","#ffffff","#ffffff","#ffffff","#ffffff","#ffffff"],"fg":["#000000","#000000","#000000","#000000","#000000","#000000","#000000","#000000","#000000","#000000","#000000","#000000","#000000","#000000","#000000","#000000","#000000","#000000","#000000","#000000","#000000","#000000","#000000","#000000","#000000","#000000","#000000","#000000","#000000","#000000","#000000"]},{"bp":"3841387","nombre":"Gianfranco Celiz","dias":["DO","Inicial G4","Inicial G4","Inicial G4","Inicial G4","Inicial G4","DO","DO","Inicial G4","Inicial G4","Curso 50%","HABILITACIÓN A320F (CCM)\nLIM-CJA-LIM\nLA 2295 (06:55-08:15 hrs)\nLA 2294 (08:55-10:00 hrs)\nLIM-AYP-LIM\nLA 2184 (10:50-11:50 hrs)\nLA 2183 (12:30-13:25 hrs)","Inicial G4","DO","DO","Inicial G4","HANDS ON B767","Inicial G4","Reentrenamiento A320F*\nLIM-CUZ-LIM\nLA2266/LA2267","DO","DO","DO","DO","Inicial G3\nTALLER DIA 2","Inicial G4","Inicial G4","Inicial G4","DO","DO","Inicial G4","Inicial G4"],"bg":["#ffffff","#ffc0cb","#ffc0cb","#ffc0cb","#ffc0cb","#ffc0cb","#ffffff","#ffffff","#ffc0cb","#ffc0cb","#ff4b4f","#f7caac","#ffc0cb","#ffffff","#ffffff","#ffc0cb","#ffff00","#ffc0cb","#f7caac","#ffffff","#ffffff","#ffffff","#ffffff","#93c47d","#ffc0cb","#ffc0cb","#ffc0cb","#ffffff","#ffffff","#ffc0cb","#ffc0cb"],"fg":["#000000","#000000","#000000","#000000","#000000","#000000","#000000","#000000","#000000","#000000","#000000","#000000","#000000","#000000","#000000","#000000","#000000","#000000","#000000","#000000","#000000","#000000","#000000","#000000","#000000","#000000","#000000","#000000","#000000","#000000","#000000"]}]} | C4: 46318.36 | D4: Google Sheet
A5: 2026-04 | B5: {"mes":"2026-04","fuente":"04 - Rol Instructores LP ABRIL 26","hoja":"ABRIL","instructores":[{"bp":"2713993","nombre":"Fiorella Ruiz","dias":["DESCANSO MÉDICO","FERIADO","FERIADO","FDS","FDS","LCK A320F\nLIM-CUZ-LIM\nLA 2007 (09:10-10:35 hrs)\nLA 2008 (11:20-12:55 hrs)","Habilitación B787 (CST)\n- LIM-SCL\n- LA 2697 (09:35-13:00 hrs)\nAcompañamiento de Servicio B787*\n- SCL-LIM\n- LA 2696 (16:00-19:45 hrs)","TTT CRM","Reva de Servicio\n(08:30-17:30 hrs)\nDÍA 1","Chequeo DGAC INICIAL G3\nLIM-CUZ-LIM\nLA2028 15:30 -16:55\nLA2029 17:30 -19:10","FDS","FDS","HO FILE\nMTC","CURSO ESTANDARIZACIÓN TARDE","Acompañamiento de Servicio B767*\n- LIM-ATL\n- LA 2482 (12:05-19:35 hrs)","LCK B767\n- ATL-LIM\n- LA 2483 (22:15-05:00 hrs)","Blanco","FDS","FDS","Habilitación B767\n- LIM-ATL\n- LA 2482 (12:05-19:35 hrs)","LCK B767\n- ATL-LIM\n- LA 2483 (22:15-05:00 hrs)","Blanco","Inicial G4 CHEQUEO DGAC\nLIM-PIU-LIM\nLA2306 09:30-11:15\nLA2307 11:55-13:25","LCK B787\n- LIM-SCL\n- LA 2697 (09:35-13:00 hrs)\nRecalificación B787\n- SCL-LIM\n- LA 2696 (16:00-19:45 hrs)","FDS","FDS","LCK B787\n- LIM-SCL\n- LA 2697 (09:35-13:00 hrs)\nLCK B787\n- SCL-LIM\n- LA 2696 (16:00-19:45 hrs)","PRO CAB","LCK A320F \nLIM-CUZ-LIM\nLA 2274 (09:35-11:10 hrs)\nLA 2275 (11:45-13:05 hrs)","LCK A320F\nLIM-CUZ-LIM\nLA 2007 (09:10-10:35 hrs)\nLA 2008 (11:20-12:55 hrs)\nLCK A320F\nLIM-CUZ-LIM\nLA 2232 (13:55-15:20 hrs)\nLA 2197 (15:55-17:35 hrs)"],"bg":["#e6b8af","#0000ff","#0000ff","#0000ff","#0000ff","#f7caac","#e88888","#ffff00","#2f5496","#93c47d","#0000ff","#0000ff","#999999","#ffff00","#ffc000","#ffc000","#ffc000","#0000ff","#0000ff","#ffc000","#ffc000","#ffc000","#ffc0cb","#e88888","#0000ff","#0000ff","#e88888","#ffe599","#f7caac","#f7caac"],"fg":["#000000","#ffffff","#ffffff","#ffffff","#ffffff","#000000","#000000","#000000","#ffffff","#000000","#ffffff","#ffffff","#000000","#000000","#000000","#000000","#000000","#ffffff","#ffffff","#000000","#000000","#000000","#000000","#000000","#ffffff","#ffffff","#000000","#000000","#000000","#000000"]},{"bp":"2396710","nombre":"Sebastian Correa","dias":["LF","LF","LF","LF","LF","LF","LF","LF","LF","DESCANSO MÉDICO","FDS","FDS","VACACIONES","VACACIONES","VACACIONES","VACACIONES","VACACIONES","VACACIONES","VACACIONES","VACACIONES","VACACIONES","VACACIONES","VACACIONES","VACACIONES","VACACIONES","VACACIONES","VACACIONES","VACACIONES","VACACIONES","VACACIONES"],"bg":["#cfe2f3","#cfe2f3","#cfe2f3","#cfe2f3","#cfe2f3","#cfe2f3","#cfe2f3","#cfe2f3","#cfe2f3","#e6b8af","#0000ff","#0000ff","#ffffcc","#ffffcc","#ffffcc","#ffffcc","#ffffcc","#ffffcc","#ffffcc","#ffffcc","#ffffcc","#ffffcc","#ffffcc","#ffffcc","#ffffcc","#ffffcc","#ffffcc","#ffffcc","#ffffcc","#ffffcc"],"fg":["#000000","#000000","#000000","#000000","#000000","#000000","#000000","#000000","#000000","#000000","#ffffff","#ffffff","#000000","#000000","#000000","#000000","#000000","#000000","#000000","#000000","#000000","#000000","#000000","#000000","#000000","#000000","#000000","#000000","#000000","#000000"]},{"bp":"1271571","nombre":"Christian Rondon","dias":["Habilitación B767*\n- ATL-LIM\n- LA 2483 (22:15-05:00 hrs)","FERIADO","FERIADO","FDS","FDS","LCK B787\n- LIM-SCL\n- LA 2697 (09:35-13:00 hrs)\nLCK B787\n- SCL-LIM\n- LA 2696 (16:00-19:45 hrs)","RESERVA IET\nTARDE","LCK A320F\nLIM-AQP-LIM\nLA 2119 (08:30-10:00 hrs)\nLA 2118 (10:55-12:35 hrs)","TTT REVA SVC","TTT REVA SVC","FDS","FDS","Reentrenamiento B767\n- LIM-MIA\n- LA 2694 (13:30-19:35 hrs)","LCK B767\n- MIA-LIM\n- LA 2699 (23:15-05:00 hrs)","Blanco","LDS","DO","FDS","FDS","Reentrenamiento B767\n- LIM-MIA\n- LA 2694 (13:30-19:35 hrs)","LCK B767\n- MIA-LIM\n- LA 2699 (23:15-05:00 hrs)","Blanco","LCK B767\n- LIM-SCL\n- LA 2413 (12:05-15:35 hrs)\nLCK B767\n- SCL-LIM\n- LA 2412 (17:05-20:55 hrs)","HO FILE\nTARDE","FDS","FDS","LCK B767\n- LIM-MIA\n- LA 2694 (13:30-19:35 hrs)","Acompañamiento de Servicio B767*\n- MIA-LIM\n- LA 2699 (23:15-05:00 hrs)","Blanco","HO FILE"],"bg":["#ffc000","#0000ff","#0000ff","#0000ff","#0000ff","#e88888","#d9d9d9","#f7caac","#c9daf8","#c9daf8","#0000ff","#0000ff","#ffc000","#ffc000","#ffc000","#ffffff","#ffffff","#0000ff","#0000ff","#ffc000","#ffc000","#ffc000","#ffc000","#999999","#0000ff","#0000ff","#ffc000","#ffc000","#ffc000","#999999"],"fg":["#000000","#ffffff","#ffffff","#ffffff","#ffffff","#000000","#000000","#000000","#000000","#000000","#ffffff","#ffffff","#000000","#000000","#000000","#000000","#000000","#ffffff","#ffffff","#000000","#000000","#000000","#000000","#000000","#ffffff","#ffffff","#000000","#000000","#000000","#000000"]},{"bp":"2843319","nombre":"Karen Santa Cruz","dias":["LCK A320F\r\nLIM-CUZ-LIM\r\nLA 2007 (09:10-10:35 hrs)\r\nLA 2008 (11:20-12:55 hrs)\r\nLCK A320F\r\nLIM-CUZ-LIM\r\nLA 2232 (13:55-15:20 hrs)\r\nLA 2197 (15:55-17:35 hrs)","DO","DO","DO","DO","AUDITORÍA\nIOSA","AUDITORÍA\nIOSA","AUDITORÍA\nIOSA","AUDITORÍA\nIOSA","AUDITORÍA\nIOSA","DO","DO","DO","LCK B767\n- LIM-ATL\n- LA 2482 (12:05-19:35 hrs)","Habilitación B767*\n- ATL-LIM\n- LA 2483 (22:15-05:00 hrs)","Blanco","HO FILE\n(No tocar)","DO","CUMP","CUMP","Situaciones de Emergencia A320F\nTripulación de Mando\nLP\n(08:30-17:30 hrs)","RTI: PRÁCTICA\nA320F / B767 / B787\n(08:30-17:30 hrs)\nINS APOYO","Ditching Presencial A320F + HANDS ON\nTripulación de Mando\nLP\n(08:30-17:30 hrs)","LCK A320F\r\nLIM-CUZ-LIM\r\nLA 2007 (09:10-10:35 hrs)\r\nLA 2008 (11:20-12:55 hrs)\r\nLCK A320F\r\nLIM-AQP-LIM\r\nLA 2055 (13:50-15:35 hrs)\r\nLA 2056 (16:15-17:50 hrs)","DO","DO","LCK B767\n- LIM-MIA\n- LA 2698 (08:15-14:20 hrs)","Chequeo DGAC B767\n- MIA-LIM\n- LA 2695 (16:10-22:00 hrs)","HO FILE TARDE MTC","Chequeo DGAC B767\n- LIM-SCL\n- LA 2413 (12:05-15:35 hrs)\nChequeo DGAC B767\n- SCL-LIM\n- LA 2412 (17:05-20:55 hrs)"],"bg":["#f7caac","#ffffff","#ffffff","#ffffff","#ffffff","#ffff00","#ffff00","#ffff00","#ffff00","#ffff00","#ffffff","#ffffff","#ffffff","#ffc000","#ffc000","#ffc000","#999999","#ffffff","#ffc0cb","#ffc0cb","#ff4b4f","#cce0f4","#ff4b4f","#f7caac","#ffffff","#ffffff","#ffc000","#ffc000","#999999","#ffc000"],"fg":["#000000","#000000","#000000","#000000","#000000","#000000","#000000","#000000","#000000","#000000","#000000","#000000","#000000","#000000","#000000","#000000","#000000","#000000","#000000","#000000","#ffffff","#000000","#ffffff","#000000","#000000","#000000","#000000","#000000","#000000","#000000"]},{"bp":"3779550","nombre":"Jennifert Acurio","dias":["Acompañamiento de Servicio B767\n- MIA-LIM\n- LA 2481 (15:55-21:40 hrs)","DO","DO","DO","DO","LCK ALUMNA B787 (CST)\n- LIM-SCL\n- LA 2697 (09:35-13:00 hrs)\nLCK ALUMNA B787 (CST)\n- SCL-LIM\n- LA 2696 (16:00-19:45 hrs)","RESERVA IET\nTARDE","VACACIONES","VACACIONES","VACACIONES","VACACIONES","VACACIONES","VACACIONES","VACACIONES","VACACIONES","Inicial G6","Chequeo DGAC B767\n- LIM-SCL\n- LA 2413 (12:05-15:35 hrs)\nChequeo DGAC B767\n- SCL-LIM\n- LA 2412 (17:05-20:55 hrs)","DO","DO","LCK B767\n- LIM-MIA\n- LA 2698 (08:15-14:20 hrs)","Chequeo LATAM B767\n- MIA-LIM\n- LA 2695 (21:50-02:30 hrs)","Blanco","Chequeo DGAC INICIAL G3*\nLIM - CUZ - LIM\nLA2266 (11:10 - 12:35)\nLA2267 (13:10 - 14:45)","Inicial G4 CHEQUEO LATAM\nLIM-PIU-LIM\nLA2306 09:30-11:15\nLA2307 11:55-13:25\nLIM-PIU-LIM\nLA2338 15:00-16:45\nLA2339 17:20-18:50","DO","DO","LCK A320F\r\nLIM-AQP-LIM\r\nLA 2123 (09:15-10:50 hrs)\r\nLA 2124 (11:30-13:10 hrs)\r\nLCK A320F\r\nLIM-CJA-LIM\r\nLA 2295 (14:05-15:30 hrs)\r\nLA 2294 (16:10-17:15 hrs)","LCK B767\n- LIM-ATL\n- LA 2482 (12:05-19:35 hrs)","Acompañamiento de Servicio B767\n- ATL-LIM\n- LA 2483 (22:15-05:00 hrs)","Blanco"],"bg":["#ffc000","#ffffff","#ffffff","#ffffff","#ffffff","#e88888","#d9d9d9","#ffffcc","#ffffcc","#ffffcc","#ffffcc","#ffffcc","#ffffcc","#ffffcc","#ffffcc","#b4a7d6","#ffc000","#ffffff","#ffffff","#ffc000","#ffc000","#ffc000","#93c47d","#ffc0cb","#ffffff","#ffffff","#f7caac","#ffc000","#ffc000","#ffc000"],"fg":["#000000","#000000","#000000","#000000","#000000","#000000","#000000","#000000","#000000","#000000","#000000","#000000","#000000","#000000","#000000","#000000","#000000","#000000","#000000","#000000","#000000","#000000","#000000","#000000","#000000","#000000","#000000","#000000","#000000","#000000"]},{"bp":"29530","nombre":"Jazmin Guerra","dias":["Habilitación B787 (CST)\n- LIM-SCL\n- LA 2697 (09:35-13:00 hrs)\nHabilitación B787 (CST)\n- SCL-LIM\n- LA 2696 (16:00-19:45 hrs)","DO","DO","DO","DO","Chequeo DGAC INICIAL G3\nLIM-CIX-LIM\nLA2274 09:35 -11:10\nLA2275 11:45 -13:05","Chequeo DGAC INICIAL G3\nLIM-AQP-LIM\nLA2043 12:50 -14:25\nLA2044 15:00 -16:40","Inicial G5\n(Recuperatorio)","TTT REVA SVC","TTT REVA SVC","DO","DO","HO FILE\nMTC","Reentrenamiento A320F + Acompañamiento de Servicio A320F*\nLIM-CUZ-LIM\n2028/2029","Inicial G6","LCK B767\n- LIM-SCL\n- LA 2413 (12:05-15:35 hrs)\nLCK B767\n- SCL-LIM\n- LA 2412 (17:05-20:55 hrs)","Chequeo LATAM INICIAL G3\nLIM - TCQ - LIM\nLA2215 (16:30 - 18:20)\nLA2216 (18:55 - 20:50)","DO","DO","LCK A320F\r\nLIM-CIX-LIM\r\nLA 2274 (09:35-11:10 hrs)\r\nLA 2275 (11:45-13:05 hrs)\r\nLCK A320F\r\nLIM-CJA-LIM\r\nLA 2295 (14:05-15:30 hrs)\r\nLA 2294 (16:10-17:15 hrs)","Recalificación B767*\n- LIM-ATL\n- LA 2482 (12:05-19:35 hrs)","LCK B767\n- ATL-LIM\n- LA 2483 (22:15-05:00 hrs)","Blanco","Chequeo DGAC B767\n- LIM-SCL\n- LA 2413 (12:05-15:35 hrs)\nChequeo DGAC B767\n- SCL-LIM\n- LA 2412 (17:05-20:55 hrs)","DO","DO","LCK A320F\nLIM-CIX-LIM\nLA 2274 (09:35-11:10 hrs)\nLA 2275 (11:45-13:05 hrs)\nLCK A320F\nLIM-TPP-LIM\nLA 2087 (14:00-15:30 hrs)\nLA 2088 (16:05-17:30 hrs)","Inicial G6\nVISITA GUIADA","Inicial G6\nVISITA GUIADA","Inicial G6\nVISITA GUIADA"],"bg":["#e88888","#ffffff","#ffffff","#ffffff","#ffffff","#93c47d","#93c47d","#00b0f0","#c9daf8","#c9daf8","#ffffff","#ffffff","#999999","#f7caac","#b4a7d6","#ffc000","#93c47d","#ffffff","#ffffff","#f7caac","#ffc000","#ffc000","#ffc000","#ffc000","#ffffff","#ffffff","#f7caac","#b4a7d6","#b4a7d6","#b4a7d6"],"fg":["#000000","#000000","#000000","#000000","#000000","#000000","#000000","#000000","#000000","#000000","#000000","#000000","#000000","#000000","#000000","#000000","#000000","#000000","#000000","#000000","#000000","#000000","#000000","#000000","#000000","#000000","#000000","#000000","#000000","#000000"]},{"bp":"3217561","nombre":"Claudia Flores","dias":["Chequeo DGAC INICIAL G3\nLIM-CIX-LIM\nLA2312 13:25 -15:00\nLA2313 15:40-17:00","DO","DO","DO","DO","HO FILE","CUMP","VACACIONES","VACACIONES","VACACIONES","VACACIONES","VACACIONES","VACACIONES","VACACIONES","VACACIONES","VACACIONES","VACACIONES","VACACIONES","VACACIONES","VACACIONES","VACACIONES","VACACIONES","HO MTC","LCK ALUMNA B787 (CCM)\n- LIM-SCL\n- LA 2697 (09:35-13:00 hrs)\nLCK ALUMNA B787 (CCM)\n- SCL-LIM\n- LA 2696 (16:00-19:45 hrs)","DO","DO","Chequeo Renovación IDE A320F\nLIM-PIU-LIM\nLA 2306 (09:30-11:15 hrs)\nLA 2307 (11:55-13:25 hrs)","PRO CAB","Chequeo DGAC B767\n- LIM-MIA\n- LA 2694 (13:30-19:35 hrs)","LCK B767\n- MIA-LIM\n- LA 2695 (16:10-22:00 hrs)"],"bg":["#93c47d","#ffffff","#ffffff","#ffffff","#ffffff","#999999","#ffc0cb","#ffffcc","#ffffcc","#ffffcc","#ffffcc","#ffffcc","#ffffcc","#ffffcc","#ffffcc","#ffffcc","#ffffcc","#ffffcc","#ffffcc","#ffffcc","#ffffcc","#ffffcc","#999999","#e88888","#ffffff","#ffffff","#f7caac","#ffe599","#ffc000","#ffc000"],"fg":["#000000","#000000","#000000","#000000","#000000","#000000","#000000","#000000","#000000","#000000","#000000","#000000","#000000","#000000","#000000","#000000","#000000","#000000","#000000","#000000","#000000","#000000","#000000","#000000","#000000","#000000","#000000","#000000","#000000","#000000"]},{"bp":"71348","nombre":"Karla Moz","dias":["VACACIONES","VACACIONES","VACACIONES","VACACIONES","VACACIONES","VACACIONES","VACACIONES","VACACIONES","VACACIONES","VACACIONES","VACACIONES","VACACIONES","VACACIONES","VACACIONES","VACACIONES","LP","LP","DO","DO","LP","LP","LP","LP","LP","DO","DO","LP","LP","LP","LP"],"bg":["#ffffcc","#ffffcc","#ffffcc","#ffffcc","#ffffcc","#ffffcc","#ffffcc","#ffffcc","#ffffcc","#ffffcc","#ffffcc","#ffffcc","#ffffcc","#ffffcc","#ffffcc","#ffffff","#ffffff","#ffffff","#ffffff","#ffffff","#ffffff","#ffffff","#ffffff","#ffffff","#ffffff","#ffffff","#ffffff","#ffffff","#ffffff","#ffffff"],"fg":["#000000","#000000","#000000","#000000","#000000","#000000","#000000","#000000","#000000","#000000","#000000","#000000","#000000","#000000","#000000","#000000","#000000","#000000","#000000","#000000","#000000","#000000","#000000","#000000","#000000","#000000","#000000","#000000","#000000","#000000"]},{"bp":"967092","nombre":"Erika Dávila","dias":["TALLER VOLUNTARIO DE SEGURIDAD","DO","DO","DO","DO","Inicial G6","Inicial G4","Inicial G6","TTT REVA SVC","TTT REVA SVC","DO","DO","Inicial G4 CHEQUEO LATAM\nLIM-CUZ-LIM\nLA2130 08:00-09:20\nLA2129 10:05-11:40\nLIM-PIU-LIM\nLA2308 13:00-14:45\nLA2309 15:25-16:55","Reva de Servicio\n(08:30-17:30 hrs)\nDÍA 1\nSVC 2","RTI: PRÁCTICA\nA320F / B767 / B787\n(08:30-17:30 hrs) \nINS TITULAR","RTI: PRÁCTICA\nB787\n(08:30-17:30 hrs)\nINS APOYO TM","Reentrenamiento B787\n- LIM-SCL\n- LA 2697 (09:35-13:00 hrs)\nHabilitación B787\n- SCL-LIM\n- LA 2696 (16:00-19:45 hrs)","DO","DO","Inicial G5","Reva de Servicio\n(08:30-17:30 hrs)\nDÍA 1","RTI: PRÁCTICA\nA320F / B767 / B787\n(08:30-17:30 hrs)\nINS TITULAR","RTI: PRÁCTICA\nA320F / B767 / B787\n(08:30-17:30 hrs)\nINS TITULAR","Reentrenamiento A320F + Acompañamiento de Servicio A320F*\nLIM-TBP-LIM\nLA 2052 (10:15-12:15 hrs)\nLA 2051 (12:55-14:35 hrs)","DO","DO","Chequeo LATAM B767\n- LIM-MIA\n- LA 2698 (08:15-14:20 hrs)","Chequeo LATAM B767\n- MIA-LIM\n- LA 2695 (16:10-22:00 hrs)","HO FILE TARDE MTC","Reentrenamiento A320F\nLIM-CIX-LIM\nLA2274/LA2275"],"bg":["#ffff00","#ffffff","#ffffff","#ffffff","#ffffff","#b4a7d6","#ffc0cb","#b4a7d6","#c9daf8","#c9daf8","#ffffff","#ffffff","#ffc0cb","#2f5496","#cce0f4","#cce0f4","#e88888","#ffffff","#ffffff","#00b0f0","#2f5496","#cce0f4","#cce0f4","#f7caac","#ffffff","#ffffff","#ffc000","#ffc000","#999999","#f7caac"],"fg":["#000000","#000000","#000000","#000000","#000000","#000000","#000000","#000000","#000000","#000000","#000000","#000000","#000000","#ffffff","#000000","#000000","#000000","#000000","#000000","#000000","#ffffff","#000000","#000000","#000000","#000000","#000000","#000000","#000000","#000000","#000000"]},{"bp":"2369641","nombre":"Elizabeth Torres","dias":["LCK A320F + Habilitación A320F\nLIM-AQP-LIM\nLA 2123 (09:15-10:50 hrs)\nLA 2124 (11:30-13:10 hrs)","DO","DO","DO","DO","LCK A320F\nLIM-TCQ-LIM\nLA 2067 (13:45-15:40 hrs)\nLA 2068 (16:20-18:15 hrs)","Reva de Servicio\n(08:30-17:30 hrs)\nDÍA 1","LCK A320F + Habiltiación A320F\nLIM-TPP-LIM\nLA 2087 (14:00-15:30 hrs)\nLA 2088 (16:05-17:30 hrs)","TTT REVA SVC","TTT REVA SVC","DO","DO","Inicial G7","LCK B767\n- LIM-MIA\n- LA 2698 (08:15-14:20 hrs)","Chequeo DGAC B767\n- MIA-LIM\n- LA 2481 (15:55-21:40 hrs)","Inicial G7 TARDE","LCK B767\n- LIM-SCL\n- LA 2413 (12:05-15:35 hrs)\nLCK B767\n- SCL-LIM\n- LA 2412 (17:05-20:55 hrs)","DO","DO","LCK A320F + Habilitación A320F*\nLIM-AQP-LIM\nLA 2123 (09:15-10:50 hrs)\nLA 2124 (11:30-13:10 hrs)","LCK B767\n- LIM-MIA\n- LA 2698 (08:15-14:20 hrs)","Chequeo DGAC B767\n- MIA-LIM\n- LA 2481 (15:55-21:40 hrs)","HO FILE\nTARDE","Inicial G4 CHEQUEO LATAM\nLIM-CUZ-LIM\nLA2130 08:00-09:20\nLA2129 10:05-11:40\nLIM-PIU-LIM\nLA2308 13:00-14:45\nLA2309 15:25-16:55","DO","DO","Recalificación A320F* + Acompañamiento de Servicio A320F*\nLIM-CUZ-LIM\nLA 2238 (10:10-11:35 hrs)\nLA 2239 (12:10-13:45 hrs)","TTT CRM\nALUMNO","HO FILE MTC","RTI: PRÁCTICA\nA320F / B767 / B787\n(08:30-17:30 hrs)\nINS APOYO"],"bg":["#f7caac","#ffffff","#ffffff","#ffffff","#ffffff","#f7caac","#2f5496","#f7caac","#c9daf8","#c9daf8","#ffffff","#ffffff","#a2c4c9","#ffc000","#ffc000","#a2c4c9","#ffc000","#ffffff","#ffffff","#f7caac","#ffc000","#ffc000","#999999","#ffc0cb","#ffffff","#ffffff","#f7caac","#ffff00","#999999","#cce0f4"],"fg":["#000000","#000000","#000000","#000000","#000000","#000000","#ffffff","#000000","#000000","#000000","#000000","#000000","#000000","#000000","#000000","#000000","#000000","#000000","#000000","#000000","#000000","#000000","#000000","#000000","#000000","#000000","#000000","#000000","#000000","#000000"]},{"bp":"2369624","nombre":"Patricia Najar","dias":["Habilitación A320F (CST)\nLIM-AQP-LIM\nLA 2103 (05:50-07:20 hrs)\nLA 2102 (08:00-09:40 hrs)\nLCK A320F\nLIM-PEM-LIM\nLA 2260 (10:20-12:05 hrs)\nLA 2261 (12:45-14:20 hrs)","DO","DO","DO","DO","Chequeo LATAM INICIAL G3\nLIM-CUZ-LIM\nLA 2130 (08:00-09:20 hrs)\nLA 2219 (10:05-11:40 hrs)\nLIM-PIU-LIM\nLA 2308 (13:00-14:45hrs)\nLA 2309 (15:25-16:55 hrs)","Inicial G6","TTT CRM","LCK A320F\nLIM-CUZ-LIM\nLA 2007 (09:10-10:35 hrs)\nLA 2008 (11:20-12:55 hrs)\nLCK A320F\nLIM-CUZ-LIM\nLA 2232 (13:55-15:20 hrs)\nLA 2197 (15:55-17:35 hrs)","Curso Estandarización","DO","DO","LCK B767\n- LIM-MIA\n- LA 2698 (08:15-14:20 hrs)","Chequeo LATAM B767\n- MIA-LIM\n- LA 2695 (16:10-22:00 hrs)","Inicial G7 TARDE","VACACIONES","VACACIONES","VACACIONES","VACACIONES","VACACIONES","VACACIONES","VACACIONES","HO FILE\n(NO TOCAR)","LCK B767\n- LIM-SCL\n- LA 2413 (12:05-15:35 hrs)\nLCK B767\n- SCL-LIM\n- LA 2412 (17:05-20:55 hrs)","DO","DO","Inicial G7","LCK B767\n- LIM-MIA\n- LA 2698 (08:15-14:20 hrs)","Recalificación B767\n- MIA-LIM\n- LA 2481 (15:55-21:40 hrs)","HO TARDE FILE MTC"],"bg":["#f7caac","#ffffff","#ffffff","#ffffff","#ffffff","#93c47d","#b4a7d6","#ffff00","#f7caac","#ffff00","#ffffff","#ffffff","#ffc000","#ffc000","#a2c4c9","#ffffcc","#ffffcc","#ffffcc","#ffffcc","#ffffcc","#ffffcc","#ffffcc","#999999","#ffc000","#ffffff","#ffffff","#a2c4c9","#ffc000","#ffc000","#999999"],"fg":["#000000","#000000","#000000","#000000","#000000","#000000","#000000","#000000","#000000","#000000","#000000","#000000","#000000","#000000","#000000","#000000","#000000","#000000","#000000","#000000","#000000","#000000","#000000","#000000","#000000","#000000","#000000","#000000","#000000","#000000"]},{"bp":"3134911","nombre":"Javier Zapata","dias":["HO FILE\nTARDE REVISION MTC","DO","DO","DO","DO","LCK A320F*\nLIM-TPP-LIM\nLA 2087 (14:00-15:30 hrs)\nLA 2088 (16:05-17:30 hrs)","RTI: VIRTUAL\nA320F / B767\n(08:30-17:30 hrs)\nINS TITULAR","LCK A320F\nLIM-TCQ-LIM\nLA 2067 (13:45-15:40 hrs)\nLA 2068 (16:20-18:15 hrs)","CURSO CRM \nRENOVACIÓN IDE","Reva de Servicio\n(08:30-17:30 hrs)\nDÍA 2","DO","DO","LCK A320F* + Acompañamiento de Servicio A320F*\nLIM-AQP-LIM\nLA 2123 (09:15-10:50 hrs)\nLA 2124 (11:30-13:10 hrs)","Inicial G7","Acompañamiento de Servicio B767\n- LIM-MIA\n- LA 2694 (13:30-19:35 hrs)","LCK B767\n- MIA-LIM\n- LA 2695 (16:10-22:00 hrs)","HO FILE\nTARDE","DO","DO","Inicial G5","Inicial G3","Acompañamiento de Servicio B767\n- LIM-ATL\n- LA 2482 (12:05-19:35 hrs)","LCK B767\n- ATL-LIM\n- LA 2483 (22:15-05:00 hrs)","Blanco","DO","DO","Inicial G4 CHEQUEO LATAM\nLIM-TQC-LIM\nLA2245 08:10-10:00\nLA2244 10:45-12:40\nLIM-CIX-LIM\nLA2312 13:25-15:00\nLA2313 15:40-17:00","HO FILE MTC","HO FILE MTC","LCK ALUMNO B767 (CCM)\n- LIM-SCL\n- LA 2413 (12:05-15:35 hrs)\nLCK ALUMNO B767 (CCM)\n- SCL-LIM\n- LA 2412 (17:05-20:55 hrs)"],"bg":["#999999","#ffffff","#ffffff","#ffffff","#ffffff","#f7caac","#cce0f4","#f7caac","#fff2cc","#2f5496","#ffffff","#ffffff","#f7caac","#a2c4c9","#ffc000","#ffc000","#999999","#ffffff","#ffffff","#00b0f0","#93c47d","#ffc000","#ffc000","#ffc000","#ffffff","#ffffff","#ffc0cb","#999999","#999999","#ffc000"],"fg":["#000000","#000000","#000000","#000000","#000000","#000000","#000000","#000000","#000000","#ffffff","#000000","#000000","#000000","#000000","#000000","#000000","#000000","#000000","#000000","#000000","#000000","#000000","#000000","#000000","#000000","#000000","#000000","#000000","#000000","#000000"]},{"bp":"3750335","nombre":"Jefferson Mendez","dias":["Chequeo DGAC INICIAL G3\nLIM-CUZ-LIM\nLA2028 15:30 -16:55\nLA2029 17:30-19:10","DO","DO","DO","DO","LCK B767\n- LIM-ATL\n- LA 2482 (12:05-19:35 hrs)","Habilitación B767\n- ATL-LIM\n- LA 2483 (22:15-05:00 hrs)","Blanco","CURSO CRM \nRENOVACIÓN IDE","DO","VACACIONES","VACACIONES","VACACIONES","VACACIONES","VACACIONES","VACACIONES","VACACIONES","VACACIONES","VACACIONES","VACACIONES","VACACIONES","VACACIONES","VACACIONES","VACACIONES","VACACIONES","VACACIONES","VACACIONES","VACACIONES","VACACIONES","VACACIONES"],"bg":["#93c47d","#ffffff","#ffffff","#ffffff","#ffffff","#ffc000","#ffc000","#ffc000","#fff2cc","#ffffff","#ffffcc","#ffffcc","#ffffcc","#ffffcc","#ffffcc","#ffffcc","#ffffcc","#ffffcc","#ffffcc","#ffffcc","#ffffcc","#ffffcc","#ffffcc","#ffffcc","#ffffcc","#ffffcc","#ffffcc","#ffffcc","#ffffcc","#ffffcc"],"fg":["#000000","#000000","#000000","#000000","#000000","#000000","#000000","#000000","#000000","#000000","#000000","#000000","#000000","#000000","#000000","#000000","#000000","#000000","#000000","#000000","#000000","#000000","#000000","#000000","#000000","#000000","#000000","#000000","#000000","#000000"]},{"bp":"3852423","nombre":"Gabriela Ungaro","dias":["Chequeo LATAM INICIAL G3\nLIM-AQP-LIM\nLA2119 08:30 -10:00\nLA2118 10:55-12:35\nLIM-TPP-LIM\nLA2207 13:15-14:45\nLA2208 15:20-17:10","DO","DO","DO","DO","LCK B767\n- LIM-MIA\n- LA 2698 (08:15-14:20 hrs)","Reentrenamiento B767 + Chequeo LATAM B767\n- MIA-LIM\n- LA 2695 (16:10-22:00 hrs)","Inicial G5\nTARDE","RTI: PRÁCTICA\nA320F / B767\n(08:30-17:30 hrs)\nINS APOYO","RTI: PRÁCTICA\nA320F / B767\n(08:30-17:30 hrs)\nINS APOYO","DO","DO","LCK A320F\r\nLIM-CIX-LIM\r\nLA 2274 (09:35-11:10 hrs)\r\nLA 2275 (11:45-13:05 hrs)\r\nLCK A320F\r\nLIM-TPP-LIM\r\nLA 2087 (14:00-15:30 hrs)\r\nLA 2088 (16:05-17:30 hrs)","Reva de Servicio\n(08:30-17:30 hrs)\nDÍA 1\nSVC 1","Reva de Servicio\n(08:30-17:30 hrs)\nDÍA 2\nSVC 1","LCK B767\n- LIM-MIA\n- LA 2698 (08:15-14:20 hrs)","Chequeo DGAC B767\n- MIA-LIM\n- LA 2481 (15:55-21:40 hrs)","DO","DO","LCK A320F\nLIM-CUZ-LIM\nLA 2238 (10:10-11:35 hrs)\nLA 2239 (12:10-13:45 hrs)\nLCK A320F + Habilitación A320F\nLIM-CJA-LIM\nLA 2297 (15:15-16:40 hrs)\nLA 2296 (17:20-18:25 hrs)","Inicial G4 CHEQUEO DGAC\nLIM-PEM-LIM\nLA2023 12:15-13:50\nLA2024 14:30-16:10","LCK B767\n- LIM-MIA\n- LA 2694 (13:30-19:35 hrs)","LCK B767\n- MIA-LIM\n- LA 2695 (16:10-22:00 hrs)","Recalificación A320F + Hab. A320F\nLIM-CJA-LIM\n2297/2296","DO","DO","Inicial G4 CHEQUEO LATAM\nLIM-AQP-LIM\nLA2119 08:30-10:00\nLA2118 10:55-12:35\nLIM-CUZ-LIM\nLA2232 13:55-15:20\nLA2233 15:55-17:35","Inicial G3","Inicial G3\nGraduación","LCK B767\n- LIM-SCL\n- LA 2413 (12:05-15:35 hrs)\nLCK B767\n- SCL-LIM\n- LA 2412 (17:05-20:55 hrs)"],"bg":["#93c47d","#ffffff","#ffffff","#ffffff","#ffffff","#ffc000","#ffc000","#00b0f0","#cce0f4","#cce0f4","#ffffff","#ffffff","#f7caac","#2f5496","#2f5496","#ffc000","#ffc000","#ffffff","#ffffff","#f4cccc","#ffc0cb","#ffc000","#ffc000","#f7caac","#ffffff","#ffffff","#ffc0cb","#93c47d","#93c47d","#ffc000"],"fg":["#000000","#000000","#000000","#000000","#000000","#000000","#000000","#000000","#000000","#000000","#000000","#000000","#000000","#ffffff","#ffffff","#000000","#000000","#000000","#000000","#000000","#000000","#000000","#000000","#000000","#000000","#000000","#000000","#000000","#000000","#000000"]},{"bp":"2604360","nombre":"Mariella Carrasco","dias":["Tripulación Practice Boarding","Tripulación Practice Boarding","Tripulación Practice Boarding","DO","DO","AUDITORÍA\nIOSA","AUDITORÍA\nIOSA","AUDITORÍA\nIOSA","AUDITORÍA\nIOSA","AUDITORÍA\nIOSA","CUMP","CUMP","Habilitación B767\n- LIM-ATL\n- LA 2482 (12:05-19:35 hrs)","LCK B767\n- ATL-LIM\n- LA 2483 (22:15-05:00 hrs)","Blanco","LDS","DO","DO","DO","DO","Inicial G4 CHEQUEO LATAM\nLIM-TBP-LIM\nLA2052 10:15-12:15\nLA2051 12:55-14:35","Inicial G4 CHEQUEO DGAC\nLIM-CUZ-LIM\nLA2007 09:10-10:35\nLA2008 11:20-12:55\n Inicial G4 CHEQUEO DGAC\nLIM-CUZ-LIM\nLA2232 13:55-15:20\nLA2197 15:55-17:55","Inicial G6","LCK A320F\r\nLIM-AQP-LIM\r\nLA 2123 (09:15-10:50 hrs)\r\nLA 2124 (11:30-13:10 hrs)\r\nLCK A320F\r\nLIM-CIX-LIM\r\nLA 2312 (14:00-15:30 hrs)\r\nLA 2313 (16:05-17:30 hrs)","DO","DO","Habilitación B767*\n- LIM-ATL\n- LA 2482 (12:05-19:35 hrs)","LCK B767\n- ATL-LIM\n- LA 2483 (22:15-05:00 hrs)","Blanco","LCK A320F\nLIM-AQP-LIM*\nLA 2123 (09:15-10:50 hrs)\nLA 2124 (11:30-13:10 hrs)\nLCK A320F\nLIM-CJA-LIM\nLA 2295 (14:05-15:30 hrs)\nLA 2294 (16:10-17:15 hrs)"],"bg":["#ffffff","#ffffff","#ffffff","#ffffff","#ffffff","#ffff00","#ffff00","#ffff00","#ffff00","#ffff00","#ffc0cb","#ffc0cb","#ffc000","#ffc000","#ffc000","#ffffff","#ffffff","#ffffff","#ffffff","#ffffff","#ffc0cb","#ffc0cb","#b4a7d6","#f7caac","#ffffff","#ffffff","#ffc000","#ffc000","#ffc000","#f7caac"],"fg":["#000000","#000000","#000000","#000000","#000000","#000000","#000000","#000000","#000000","#000000","#000000","#000000","#000000","#000000","#000000","#000000","#000000","#000000","#000000","#000000","#000000","#000000","#000000","#000000","#000000","#000000","#000000","#000000","#000000","#000000"]},{"bp":"2823133","nombre":"Cesar Campos","dias":["HO TARDE - REVISION MTC","DO","DO","DO","DO","TALLER VOLUNTARIO DE SEGURIDAD","TTT CRM","TTT CRM\nINSTRUCTOR","RTI: PRÁCTICA\nA320F\n(08:30-17:30 hrs)\nINS APOYO TM","TTT REVA SVC","DO","DO","Inicial G4 CHEQUEO LATAM\nLIM-AQP-LIM\nLA2119 08:30-10:00\nLA2118 10:55-12:35\nLIM-TPP-LIM\nLA2087 14:00-15:30\nLA2088 16:05-17:30","Inicial G6","RTI: PRÁCTICA\nA320F / B767 / B787\n(08:30-17:30 hrs)\nINS APOYO","RTI: PRÁCTICA\nA320F / B767 / B787\n(08:30-17:30 hrs)\nINS APOYO","Inicial G6","DO","DO","Inicial G6","RRVV CAE","RTI: VIRTUAL\nA320F / B767\n(08:30-17:30 hrs)\nINS TITULAR","Inicial G4 CHEQUEO LATAM\nLIM-CUZ-LIM\nLA2130 08:00-09:20\nLA2129 10:05-11:40\nLIM-PIU-LIM\nLA2308 13:00-14:45\nLA2309 15:25-16:55","RTI: PRÁCTICA\nA320F / B767\n(08:30-17:30 hrs)\nINS TITULAR","DO","DO","TALLER VOLUNTARIO DE SEGURIDAD","Reva de Servicio\n(08:30-17:30 hrs)\nDÍA 1\nSVC GRUPO 2","Reva de Servicio\n(08:30-17:30 hrs)\nDÍA 2\nSVC GRUPO 2","Reva de Servicio\n(08:30-17:30 hrs)\nDÍA 2\nSVC 2"],"bg":["#999999","#ffffff","#ffffff","#ffffff","#ffffff","#ffff00","#ffff00","#ffff00","#cce0f4","#c9daf8","#ffffff","#ffffff","#ffc0cb","#b4a7d6","#cce0f4","#cce0f4","#b4a7d6","#ffffff","#ffffff","#b4a7d6","#999999","#cce0f4","#ffc0cb","#cce0f4","#ffffff","#ffffff","#ffff00","#2f5496","#2f5496","#2f5496"],"fg":["#000000","#000000","#000000","#000000","#000000","#000000","#000000","#000000","#000000","#000000","#000000","#000000","#000000","#000000","#000000","#000000","#000000","#000000","#000000","#000000","#000000","#000000","#000000","#000000","#000000","#000000","#000000","#ffffff","#ffffff","#ffffff"]},{"bp":"3189967","nombre":"Kevin Segovia","dias":["HABILITACIÓN A320F (CCM)\nLIM-AQP-CUZ\nLA 2111 (11:40-13:15 hrs)\nLA 2321 (14:00-14:55 hrs)\nCUZ-AQP-LIM\nLA 2322 (15:40-16:45 hrs)\nLA 2110 (17:50-19:30 hrs)","DO","DO","DO","DO","AUDITORÍA\nIOSA","AUDITORÍA\nIOSA","AUDITORÍA\nIOSA","Inicial G6","RTI: PRÁCTICA\nB767\n(08:30-17:30 hrs)\nINS APOYO TM","DO","DO","Chequeo LATAM B767\n- LIM-MIA\n- LA 2698 (08:15-14:20 hrs)","Habilitación B767\n- MIA-LIM\n- LA 2695 (16:10-22:00 hrs)","HO FILE TARDE\nMTC","CUMP","CUMP","DO","DO","Inicial G4 CHEQUEO LATAM\nLIM-TPP-LIM\nLA2085 08:25-09:55\nLA2086 10:40-12:00\nLIM-JUL-LIM\nLA2207 13:15-14:45\nLA2208 15:20-17:10","Inicial G4 CHEQUEO LATAM\nLIM-IQT-LIM\nLA2234 13:35-15:30\nLA2235 16:05-17:55","Reva de Servicio\n(08:30-17:30 hrs)\nDÍA 2","Inicial G4 CHEQUEO LATAM\nLIM-IQT-LIM\nLA2019 11:35-13:30\nLA2018 14:05-15:55","RTI: PRÁCTICA\nA320F / B767\n(08:30-17:30 hrs)\nINS APOYO","DO","DO","TALLER VOLUNTARIO DE SEGURIDAD","Reva de Servicio\n(08:30-17:30 hrs)\nDÍA 1\nSVC GRUPO 1","Reva de Servicio\n(08:30-17:30 hrs)\nDÍA 2\nSVC GRUPO 1","Inicial G5 CHEQUEO LATAM\nLIM-TQC-LIM\nLA2245 08:10-10:00\nLA2244 10:45-12:40\nReentrenamiento A320F*\nLIM-CJA-LIM\nLA2295 14:05-15:30\nLA2294 16:10-17:15"],"bg":["#f7caac","#ffffff","#ffffff","#ffffff","#ffffff","#ffff00","#ffff00","#ffff00","#b4a7d6","#cce0f4","#ffffff","#ffffff","#ffc000","#ffc000","#999999","#ffc0cb","#ffc0cb","#ffffff","#ffffff","#ffc0cb","#ffc0cb","#2f5496","#ffc0cb","#cce0f4","#ffffff","#ffffff","#ffff00","#2f5496","#2f5496","#00b0f0"],"fg":["#000000","#000000","#000000","#000000","#000000","#000000","#000000","#000000","#000000","#000000","#000000","#000000","#000000","#000000","#000000","#000000","#000000","#000000","#000000","#000000","#000000","#ffffff","#000000","#000000","#000000","#000000","#000000","#ffffff","#ffffff","#000000"]},{"bp":"2415373","nombre":"Milagros Salas","dias":["Inicial G5","DO","DO","DO","DO","Inicial G5\nVISITA GUIADA","Inicial G5\nVISITA GUIADA","Reva de Servicio\n(08:30-17:30 hrs)\nDÍA 2","TTT REVA SVC","TTT REVA SVC","DO","DO","Inicial G5","Inicial G5","HB6\nCurso B767\n(08:30-17:30hrs)","Reva de Servicio\n(08:30-17:30 hrs)\nDÍA 1\nSVC 1","Inicial G5","DO","DO","Chequeo LATAM B767\n- LIM-MIA\n- LA 2698 (08:15-14:20 hrs)","Habilitación B767\n- MIA-LIM\n- LA 2695 (21:50-02:30 hrs)","Blanco","Reva de Servicio\n(08:30-17:30 hrs)\nDÍA 1","Reva de Servicio\n(08:30-17:30 hrs)\nDÍA 2","DO","DO","Inicial G6","Inicial G7","Inicial G7","DO"],"bg":["#00b0f0","#ffffff","#ffffff","#ffffff","#ffffff","#00b0f0","#00b0f0","#2f5496","#c9daf8","#c9daf8","#ffffff","#ffffff","#00b0f0","#00b0f0","#a8d08d","#2f5496","#00b0f0","#ffffff","#ffffff","#ffc000","#ffc000","#ffc000","#2f5496","#2f5496","#ffffff","#ffffff","#b4a7d6","#a2c4c9","#a2c4c9","#ffffff"],"fg":["#000000","#000000","#000000","#000000","#000000","#000000","#000000","#ffffff","#000000","#000000","#000000","#000000","#000000","#000000","#000000","#ffffff","#000000","#000000","#000000","#000000","#000000","#000000","#ffffff","#ffffff","#000000","#000000","#000000","#000000","#000000","#000000"]},{"bp":"2440915","nombre":"Judith Fernandez","dias":["TALLER VOLUNTARIO DE SEGURIDAD","DO","DO","DO","DO","Chequeo LATAM B767\n- LIM-MIA\n- LA 2698 (08:15-14:20 hrs)","Chequeo LATAM B767\n- MIA-LIM\n- LA 2695 (16:10-22:00 hrs)","TTT CRM","TTT REVA SVC","TTT REVA SVC","DO","DO","Inicial G6","RTI: VIRTUAL\nA320F / B767 / B787\n(08:30-17:30 hrs)\nINS TITULAR","Reva de Servicio\n(08:30-17:30 hrs)\nDÍA 2\nSVC 2","RTI: PRÁCTICA\nA320F / B767 / B787\n(08:30-17:30 hrs)\nINS TITULAR","Reva de Servicio\n(08:30-17:30 hrs)\nDÍA 2\nSVC 1","DO","DO","Inicial G7","RTI: VIRTUAL\nA320F / B767 / B787\n(08:30-17:30 hrs)\nINS TITULAR","Inicial G6","RTI: PRÁCTICA\nA320F / B767 / B787\n(08:30-17:30 hrs)\nINS APOYO","Inicial G6","DO","DO","Inicial G4 CHEQUEO LATAM\nLIM-CUZ-LIM\nLA2130 08:00-09:20\nLA2129 10:05-11:40\nLIM-PIU-LIM\nLA2308 13:00-14:45\nLA2309 15:25-16:55","RTI: VIRTUAL\nA320F / B767\n(08:30-17:30 hrs)\nINS TITULAR","HO FILE MTC","RTI: PRÁCTICA\nA320F / B767\n(08:30-17:30 hrs)\nINS TITULAR"],"bg":["#ffff00","#ffffff","#ffffff","#ffffff","#ffffff","#ffc000","#ffc000","#ffff00","#c9daf8","#c9daf8","#ffffff","#ffffff","#b4a7d6","#cce0f4","#2f5496","#cce0f4","#2f5496","#ffffff","#ffffff","#a2c4c9","#cce0f4","#b4a7d6","#cce0f4","#b4a7d6","#ffffff","#ffffff","#ffc0cb","#cce0f4","#999999","#cce0f4"],"fg":["#000000","#000000","#000000","#000000","#000000","#000000","#000000","#000000","#000000","#000000","#000000","#000000","#000000","#000000","#ffffff","#000000","#ffffff","#000000","#000000","#000000","#000000","#000000","#000000","#000000","#000000","#000000","#000000","#000000","#000000","#000000"]},{"bp":"3796947","nombre":"Rafael Nieto","dias":["B","B","B","DO","DO","B","B","B","B","B","DO","DO","B","B","B","B","B","DO","DO","B","B","B","B","B","DO","DO","B","B","B","B"],"bg":["#ffffff","#ffffff","#ffffff","#ffffff","#ffffff","#ffffff","#ffffff","#ffffff","#ffffff","#ffffff","#ffffff","#ffffff","#ffffff","#ffffff","#ffffff","#ffffff","#ffffff","#ffffff","#ffffff","#ffffff","#ffffff","#ffffff","#ffffff","#ffffff","#ffffff","#ffffff","#ffffff","#ffffff","#ffffff","#ffffff"],"fg":["#000000","#000000","#000000","#000000","#000000","#000000","#000000","#000000","#000000","#000000","#000000","#000000","#000000","#000000","#000000","#000000","#000000","#000000","#000000","#000000","#000000","#000000","#000000","#000000","#000000","#000000","#000000","#000000","#000000","#000000"]},{"bp":"3841387","nombre":"Gianfranco Celiz","dias":["Reva de Servicio\n(08:30-17:30 hrs)\nDÍA 2","DO","DO","DO","DO","TALLER VOLUNTARIO DE SEGURIDAD","TTT CRM","RTI: VIRTUAL\nA320F / B767\n(08:30-17:30 hrs)\nINS TITULAR","RTI: PRÁCTICA\nA320F / B767\n(08:30-17:30 hrs)\nINS TITULAR","RTI: PRÁCTICA\nA320F / B767\n(08:30-17:30 hrs)\nINS TITULAR","DO","DO","HB6\nCurso B767\n(08:30-17:30hrs)","HB6\nCurso B767\n(08:30-17:30hrs)","HB6\nCurso B767\n(08:30-17:30hrs)","Reva de Servicio\n(08:30-17:30 hrs)\nDÍA 1\nSVC 2","Reva de Servicio\n(08:30-17:30 hrs)\nDÍA 2\nSVC 2","DO","DO","HANDS ON B767","Inicial G7","Inicial G7","Inicial G7","Inicial G7","DO","DO","Inicial G3","TTT CRM\nINSTRUCTOR","DESCANSO MÉDICO","Inicial G7"],"bg":["#2f5496","#ffffff","#ffffff","#ffffff","#ffffff","#ffff00","#ffff00","#cce0f4","#cce0f4","#cce0f4","#ffffff","#ffffff","#a8d08d","#a8d08d","#a8d08d","#2f5496","#2f5496","#ffffff","#ffffff","#ffe599","#a2c4c9","#a2c4c9","#a2c4c9","#a2c4c9","#ffffff","#ffffff","#93c47d","#ffff00","#e6b8af","#a2c4c9"],"fg":["#ffffff","#000000","#000000","#000000","#000000","#000000","#000000","#000000","#000000","#000000","#000000","#000000","#000000","#000000","#000000","#ffffff","#ffffff","#000000","#000000","#000000","#000000","#000000","#000000","#000000","#000000","#000000","#000000","#000000","#000000","#000000"]}]} | C5: 46318.36 | D5: Google Sheet
A6: 2026-05 | B6: {"mes":"2026-05","fuente":"05 -Rol Instructores LP MAYO","hoja":"MAYO","instructores":[{"bp":"2713993","nombre":"Fiorella Ruiz","dias":["FERIADO","FDS","FDS","Inicial G6","VACACIONES","LCK A320F\r\nLIM-CUZ-LIM\r\nLA 2013 (08:40-10:00 hrs)\r\nLA 2014 (10:40-12:15 hrs)\r\nLCK A320F\r\nLIM-CIX-LIM\r\nLA 2312 (13:25-15:00 hrs)\r\nLA 2313 (15:40-17:00 hrs)","LCK A320F\nLIM-AQP-LIM\nLA 2123 (09:15-10:50 hrs)\nLA 2124 (11:30-13:10 hrs)\nLCK A320F\nLIM-TPP-LIM\nLA 2087 (14:00-15:30 hrs)\nLA 2088 (16:05-17:30 hrs)","CURSO REFRESCO INSPECTOR\nB767","FDS","FDS","Inicial G5\nInicial G4 CHEQUEO DGAC + HAB A320F\nLIM-AQP-LIM\nLA2119 08:30-10:00\nLA2118 10:55-12:35\nLIM-CIX-LIM*\nLA2312 13:25-15:00\nLA2313 15:40-17:00*","Reentrenamiento A320F + Recalificación A320F\nLIM-CIX-LIM\nLA2312/LA2313","RTI: PRÁCTICA\nA320F / B767 / B787\n(08:30-17:30 hrs)\nINS APOYO","RTI: PRÁCTICA\nA320F / B767 / B787\n(08:30-17:30 hrs)\nINS APOYO","LCK B767\n- LIM-SCL\n- LA 2413 (12:20-15:45 hrs)\nLCK B767\n- SCL-LIM\n- LA 2412 (17:10-20:50 hrs)","FDS","FDS","VACACIONES","HANDS ON B787","Habilitación B767\n- LIM-MIA\n- LA 2694 (13:30-19:35 hrs)","Blanco","LCK B767\n- MIA-LIM\n- LA 2693 (00:45-06:30 hrs)","FDS","FDS","TALLER VOLUNTARIO DE SEGURIDAD","PERMISO JEFATURA","Inicial G6 Chequeo LATAM\nLIM-PEM-LIM\nLA2260 10:20-12:05\nLA2261 12:45-14:20\r\nLIM-JUL-LIM\nLA2211 15:45-17:20\nLA2212 18:00-19:45","HO FILE\nPRE IOSA 2026","HO FILE\nPRE IOSA 2026","FDS","FDS"],"bg":["#0000ff","#0000ff","#0000ff","#b4a7d6","#ffffcc","#f7caac","#f7caac","#d9ead3","#0000ff","#0000ff","#00b0f0","#f7caac","#cce0f4","#cce0f4","#ffc000","#0000ff","#0000ff","#ffffcc","#ffff00","#ffc000","#ffc000","#ffc000","#0000ff","#0000ff","#ffff00","#999999","#b4a7d6","#999999","#999999","#0000ff","#0000ff"],"fg":["#ffffff","#ffffff","#ffffff","#000000","#000000","#000000","#000000","#000000","#ffffff","#ffffff","#000000","#000000","#000000","#000000","#000000","#ffffff","#ffffff","#000000","#000000","#000000","#000000","#000000","#ffffff","#ffffff","#000000","#000000","#000000","#000000","#000000","#ffffff","#ffffff"]},{"bp":"2396710","nombre":"Sebastian Correa","dias":["FERIADO","FDS","FDS","Inicial G7","Inicial G7","Inicial G7\nVISITA GUIADA","Inicial G7\nVISITA GUIADA","Inicial G7\nVISITA GUIADA","FDS","FDS","Inicial G5\nInicial G4 CHEQUEO DGAC\nLIM-PIU-LIM\nLA2306 09:30-11:15\nLA2307 11:55-13:25","LCK B787\n- LIM-SCL\n- LA 2697 (09:35-13:00 hrs)\nLCK B787\n- SCL-LIM\n- LA 2696 (16:00-19:45 hrs)","HO FILE TARDE","RTI: PRÁCTICA\nA320F / B767 / B787\n(08:30-17:30 hrs)\nINS APOYO TM","LCK B787\n- LIM-SCL\n- LA 2697 (09:35-13:00 hrs)\nHabilitación B787\n- SCL-LIM\n- LA 2696 (16:00-19:45 hrs)","FDS","FDS","Blanco","LCK B767\n- LIM-MIA\n- LA 2480 (00:15-06:20 hrs)","Habilitación B767\n- MIA-LIM\n- LA 2481 (15:55-21:40 hrs)","HO FILE TARDE","HO PPT","FDS","FDS","Blanco","LCK B767\n- LIM-MIA\n- LA 2480 (00:15-06:20 hrs)","Reentrenamienito B767\n- MIA-LIM\n- LA 2481 (15:55-21:40 hrs)","Inicial G6 Chequeo DGAC\n (TARDE)\nLIM-TPP-LIM\nLA2087 14:00-15:30\nLA2088 16:05-17:30","LCK B787\n- LIM-SCL\n- LA 2697 (09:35-13:00 hrs)\nLCK B787\n- SCL-LIM\n- LA 2696 (16:00-19:45 hrs)","FDS","FDS"],"bg":["#0000ff","#0000ff","#0000ff","#2f5496","#2f5496","#2f5496","#2f5496","#2f5496","#0000ff","#0000ff","#00b0f0","#e88888","#999999","#cce0f4","#e88888","#0000ff","#0000ff","#ffc000","#ffc000","#ffc000","#999999","#999999","#0000ff","#0000ff","#ffc000","#ffc000","#ffc000","#b4a7d6","#e88888","#0000ff","#0000ff"],"fg":["#ffffff","#ffffff","#ffffff","#000000","#000000","#000000","#000000","#000000","#ffffff","#ffffff","#000000","#000000","#000000","#000000","#000000","#ffffff","#ffffff","#000000","#000000","#000000","#000000","#000000","#ffffff","#ffffff","#000000","#000000","#000000","#000000","#000000","#ffffff","#ffffff"]},{"bp":"1271571","nombre":"Christian Rondon","dias":["FERIADO","FDS","FDS","LCK ALUMNO B767 (CST)\n- LIM-MIA\n- LA 2698 (08:15-14:20 hrs)","Habilitación B767 (CST)\n- MIA-LIM\n- LA 2481 (15:55-21:40 hrs)","HO FILE TARDE","Habilitación B787 (CST)\n- LIM-SCL\n- LA 2697 (09:35-13:00 hrs)\nLCK B787\n- SCL-LIM\n- LA 2696 (16:00-19:45 hrs)","REUNIÓN INSTRUCTORES\nTARDE","FDS","FDS","VACACIONES","VACACIONES","VACACIONES","VACACIONES","VACACIONES","VACACIONES","VACACIONES","LCK B767\n- LIM-MIA\n- LA 2694 (13:30-19:35 hrs)","Habilitación B767*\n- MIA-LIM\n- LA 2699 (23:15-05:00 hrs)","Blanco","Inicial G6 Chequeo LATAM\nLIM-CUZ-LIM\nLA2130 08:10-09:30\nLA2129 10:05-11:40\r\nLIM-PIU-LIM\nLA2308 13:00-14:45\nLA2309 15:25-16:55","LCK B767\n- LIM-SCL\n- LA 2413 (12:05-15:35 hrs)\nLCK B767\n- SCL-LIM\r\n- LA 2412 (17:00-20:50 hrs)","FDS","FDS","LCK B787\n- LIM-SCL\n- LA 2697 (09:35-13:00 hrs)\nLCK B787\n- SCL-LIM\n- LA 2696 (16:00-19:45 hrs)","HO TARDE\nPIE","LCK B787\n- LIM-SCL\n- LA 2697 (09:35-13:00 hrs)\nLCK B787\n- SCL-LIM\n- LA 2696 (16:00-19:45 hrs)","HO FILE\nTARDE","Inicial G8","FDS","FDS"],"bg":["#0000ff","#0000ff","#0000ff","#ffc000","#ffc000","#999999","#e88888","#ffffff","#0000ff","#0000ff","#ffffcc","#ffffcc","#ffffcc","#ffffcc","#ffffcc","#ffffcc","#ffffcc","#ffc000","#ffc000","#ffc000","#b4a7d6","#ffc000","#0000ff","#0000ff","#e88888","#999999","#e88888","#999999","#ff4b4f","#0000ff","#0000ff"],"fg":["#ffffff","#ffffff","#ffffff","#000000","#000000","#000000","#000000","#000000","#ffffff","#ffffff","#000000","#000000","#000000","#000000","#000000","#000000","#000000","#000000","#000000","#000000","#000000","#000000","#ffffff","#ffffff","#000000","#000000","#000000","#000000","#000000","#ffffff","#ffffff"]},{"bp":"2843319","nombre":"Karen Santa Cruz","dias":["DO","DO","DO","LCK B767\n- LIM-MIA\n- LA 2698 (08:15-14:20 hrs)","LCK B767\n- MIA-LIM\n- LA 2481 (15:55-21:40 hrs)","HO FILE TARDE","Habilitación B787 (CST)\n- LIM-SCL\n- LA 2697 (09:35-13:00 hrs)\nLCK ALUMNO B787 (CST)\n- SCL-LIM\n- LA 2696 (16:00-19:45 hrs)","REUNIÓN INSTRUCTORES\nTARDE","DO","DO","CURSO 50% \nDÍA 6","Inicial G7","Inicial G7","Inicial G7","DO","DO","DO","DO","Reva de Servicio\n(08:30-17:30 hrs)\nDÍA 1\nSVC 1","Reva de Servicio\n(08:30-17:30 hrs)\nDÍA 2\nSVC 1","HO FILE\nPRE IOSA 2026","LCK ALUMNO B767 (CCM)\n- LIM-SCL\n- LA 2413 (12:05-15:35 hrs)\nLCK ALUMNO B767 (CCM)\n- SCL-LIM\n- LA 2412 (17:00-20:50 hrs)","DO","DO","HO FILE","Inicial G8","LCK A320F\nLIM-CIX-LIM\nLA 2312 (13:25-15:00 hrs)\nLA 2313 (15:40-17:00 hrs)","HO FILE\nPRE IOSA 2026","HO FILE\nPRE IOSA 2026","DO","DO"],"bg":["#ffffff","#ffffff","#ffffff","#ffc000","#ffc000","#999999","#e88888","#ffffff","#ffffff","#ffffff","#ffe599","#2f5496","#2f5496","#2f5496","#ffffff","#ffffff","#ffffff","#ffffff","#2f5496","#2f5496","#999999","#ffc000","#ffffff","#ffffff","#999999","#ff4b4f","#f7caac","#999999","#999999","#ffffff","#ffffff"],"fg":["#000000","#000000","#000000","#000000","#000000","#000000","#000000","#000000","#000000","#000000","#000000","#000000","#000000","#000000","#000000","#000000","#000000","#000000","#ffffff","#ffffff","#000000","#000000","#000000","#000000","#000000","#000000","#000000","#000000","#000000","#000000","#000000"]},{"bp":"3779550","nombre":"Jennifert Acurio","dias":["DO","DO","DO","Reent. A320F + Inicial G4 CHEQUEO DGAC\nLIM-CIX-LIM\nLA2274 09:35-11:10\nLA2275 11:45-13:05","Inicial G5\nInicial G4 CHEQUEO LATAM\nLIM-CUZ-LIM\nLA2130 08:10-09:30\nLA2129 10:05-11:40\nLIM-PIU-LIM\nLA2087 13:00-14:45\nLA2088 15:25-16:55","CAPACITACION RRVV\nALUMNO","HANDS ON B767","REUNIÓN INSTRUCTORES","DO","DO","TALLER VOLUNTARIO DE SEGURIDAD","Blanco","LCK B767\n- LIM-MIA\n- LA 2480 (00:15-06:20 hrs)","Habilitación B767\n- MIA-LIM\n- LA 2695 (16:10-22:00 hrs)","DO","DO","DO","DO","HO FILE","Blanco","LCK B767 \n- LIM-MIA\n- LA 2480 (00:15-06:20 hrs)","Acompañamiento de Servicio B767\n- MIA-LIM\n- LA 2481 (19:00-00:00 hrs)","Blanco","DO","DO","HO FILE","Inicial G8","HO FILE","HO FILE","DO","DO"],"bg":["#ffffff","#ffffff","#ffffff","#ffc0cb","#00b0f0","#d0e0e3","#ffff00","#ffffff","#ffffff","#ffffff","#ffff00","#ffc000","#ffc000","#ffc000","#ffffff","#ffffff","#ffffff","#ffffff","#999999","#ffc000","#ffc000","#ffc000","#ffc000","#ffffff","#ffffff","#999999","#ff4b4f","#999999","#999999","#ffffff","#ffffff"],"fg":["#000000","#000000","#000000","#000000","#000000","#000000","#000000","#000000","#000000","#000000","#000000","#000000","#000000","#000000","#000000","#000000","#000000","#000000","#000000","#000000","#000000","#000000","#000000","#000000","#000000","#000000","#000000","#000000","#000000","#000000","#000000"]},{"bp":"29530","nombre":"Jazmin Guerra","dias":["DO","DO","DO","CURSO 50% \nDÍA 1","Inicial G5\nInicial G4 CHEQUEO LATAM\nLIM-IQT-LIM\nLA2041 08:00-09:00\nLA2042 10:30-12:20\nLIM-TPP-LIM\nLA2087 13:25-14:55\nLA2088 15:35-17:00","CAPACITACION RRVV\nALUMNO","LCK ALUMNO B767 (CCM)\n- LIM-SCL\n- LA 2413 (12:05-15:35 hrs)\nLCK ALUMNO B767 (CCM)\n- SCL-LIM\n- LA 2412 (17:00-20:50 hrs)","REUNIÓN INSTRUCTORES\nTARDE","DO","DO","TALLER VOLUNTARIO DE SEGURIDAD","LCK B767\n- LIM-MIA\n- LA 2698 (08:15-14:20 hrs)","Acompañamiento de Servicio B767\n- MIA-LIM\n- LA 2699 (23:15-05:00 hrs)","Blanco","LCK ALUMNO B787 (CST)\n- LIM-SCL\n- LA 2697 (09:35-13:00 hrs)\nLCK ALUMNO B787 (CST)\n- SCL-LIM\n- LA 2696 (16:00-19:45 hrs)","DO","DO","TALLER VOLUNTARIO DE SEGURIDAD","Reva de Servicio\n(08:30-17:30 hrs)\nDÍA 1\nSVC 2","Reva de Servicio\n(08:30-17:30 hrs)\nDÍA 2\nSVC 2","LCK B767\n- LIM-SCL\n- LA 2413 (12:05-15:35 hrs)\nLCK B767\n- SCL-LIM\r\n- LA 2412 (17:00-20:50 hrs)","DO","DO","VACACIONES","VACACIONES","VACACIONES","VACACIONES","VACACIONES","VACACIONES","VACACIONES","VACACIONES"],"bg":["#ffffff","#ffffff","#ffffff","#ffe599","#00b0f0","#d0e0e3","#ffc000","#ffffff","#ffffff","#ffffff","#ffff00","#ffc000","#ffc000","#ffc000","#e88888","#ffffff","#ffffff","#ffff00","#2f5496","#2f5496","#ffc000","#ffffff","#ffffff","#ffffcc","#ffffcc","#ffffcc","#ffffcc","#ffffcc","#ffffcc","#ffffcc","#ffffcc"],"fg":["#000000","#000000","#000000","#000000","#000000","#000000","#000000","#000000","#000000","#000000","#000000","#000000","#000000","#000000","#000000","#000000","#000000","#000000","#ffffff","#ffffff","#000000","#000000","#000000","#000000","#000000","#000000","#000000","#000000","#000000","#000000","#000000"]},{"bp":"3217561","nombre":"Claudia Flores","dias":["DO","DO","DO","DO","Reva de Servicio\n(08:30-17:30 hrs)\nDÍA 1","Reva de Servicio\n(08:30-17:30 hrs)\nDÍA 2","Reentrenamiento A320F + Pasajero A320F\nLIM-CIX-LIM\nLA2274/LA2275","REUNIÓN INSTRUCTORES","DO","DO","LCK B767\n- LIM-MIA\n- LA 2694 (13:30-19:35 hrs)","Chequeo LATAM B767\n- MIA-LIM\n- LA 2699 (23:15-05:00 hrs)","Blanco","LCK ALUMNO B767 (CCM)\n- LIM-SCL\n- LA 2413 (12:05-15:35 hrs)\nLCK ALUMNO B767 (CCM)\n- SCL-LIM\n- LA 2412 (17:00-20:50 hrs)","B","DO","DO","TALLER VOLUNTARIO DE SEGURIDAD","Blanco","Reentrenamiento B767*\n- LIM-MIA\n- LA 2480 (00:15-06:20 hrs)","LCK B767\n- MIA-LIM\n- LA 2695 (18:20-00:00 hrs)","Blanco","DO","DO","LCK B767\n- LIM-MIA\n- LA 2698 (08:15-14:20 hrs)","Recalificación B767\n- MIA-LIM\n- LA 2481 (15:55-21:40 hrs)","Reunión Embajadores","HO FILE\nPRE IOSA 2026","HO FILE\nPRE IOSA 2026","DO","DO"],"bg":["#ffffff","#ffffff","#ffffff","#ffffff","#2f5496","#2f5496","#f7caac","#ffffff","#ffffff","#ffffff","#ffc000","#ffc000","#ffc000","#ffc000","#ffffff","#ffffff","#ffffff","#ffff00","#ffc000","#ffc000","#ffc000","#ffc000","#ffffff","#ffffff","#ffc000","#ffc000","#ffff00","#999999","#999999","#ffffff","#ffffff"],"fg":["#000000","#000000","#000000","#000000","#ffffff","#ffffff","#000000","#000000","#000000","#000000","#000000","#000000","#000000","#000000","#000000","#000000","#000000","#000000","#000000","#000000","#000000","#000000","#000000","#000000","#000000","#000000","#000000","#000000","#000000","#000000","#000000"]},{"bp":"71348","nombre":"Karla Moz","dias":["LP","LP","LP","LP","LP","LP","LP","LP","LP","LP","LP","LP","LP","LP","LP","LP","LP","LP","LP","LP","LP","LP","LP","LP","LP","LP","LP","LP","LP","LP","LP"],"bg":["#ffffff","#ffffff","#ffffff","#ffffff","#ffffff","#ffffff","#ffffff","#ffffff","#ffffff","#ffffff","#ffffff","#ffffff","#ffffff","#ffffff","#ffffff","#ffffff","#ffffff","#ffffff","#ffffff","#ffffff","#ffffff","#ffffff","#ffffff","#ffffff","#ffffff","#ffffff","#ffffff","#ffffff","#ffffff","#ffffff","#ffffff"],"fg":["#000000","#000000","#000000","#000000","#000000","#000000","#000000","#000000","#000000","#000000","#000000","#000000","#000000","#000000","#000000","#000000","#000000","#000000","#000000","#000000","#000000","#000000","#000000","#000000","#000000","#000000","#000000","#000000","#000000","#000000","#000000"]},{"bp":"967092","nombre":"Erika Dávila","dias":["DO","DO","DO","DO","CURSO 50% \nDÍA 2","CAPACITACION RRVV\nALUMNO","RTI: PRÁCTICA\nA320F / B767\n(08:30-17:30 hrs)\nINS APOYO","REUNIÓN INSTRUCTORES","DO","DO","Inicial G6","Inicial G6","RTI: PRÁCTICA\nA320F / B767 / B787\n(08:30-17:30 hrs)\nINS TITULAR","CURSO 50% \nDÍA 8","HO FILE","DO","DO","Habilitación B767 (CCM)\n- LIM-LAX\n- LA 2476 (12:00-19:00 hrs)","Habilitación B767 (CCM)\n- LAX-LIM\n- LA 2477 (21:30-08:05 hrs)","Blanco","Reva de Servicio\n(08:30-17:30 hrs)\nDÍA 1","Reva de Servicio\n(08:30-17:30 hrs)\nDÍA 2","DO","DO","HO PPT","HO PPT","HABILITACIÓN A320F (CST)\nLIM-CJA-LIM\nLA 2299 (11:35-13:00 hrs)\nLA 2298 (13:45-14:55 hrs)","Inicial G8","CURSO 50% \nDIA 9","DO","DO"],"bg":["#ffffff","#ffffff","#ffffff","#ffffff","#ffe599","#d0e0e3","#cce0f4","#ffffff","#ffffff","#ffffff","#b4a7d6","#b4a7d6","#cce0f4","#ffe599","#999999","#ffffff","#ffffff","#ffc000","#ffc000","#ffc000","#2f5496","#2f5496","#ffffff","#ffffff","#999999","#999999","#f4cccc","#ff4b4f","#ffe599","#ffffff","#ffffff"],"fg":["#000000","#000000","#000000","#000000","#000000","#000000","#000000","#000000","#000000","#000000","#000000","#000000","#000000","#000000","#000000","#000000","#000000","#000000","#000000","#000000","#ffffff","#ffffff","#000000","#000000","#000000","#000000","#000000","#000000","#000000","#000000","#000000"]},{"bp":"2369641","nombre":"Elizabeth Torres","dias":["DO","DO","DO","Curso Refreso IDE","LCK A320F\nLIM-CUZ-LIM\nLA 2007 (09:10-10:35 hrs)\nLA 2008 (11:20-12:55 hrs)\nLCK A320F + Habilitación A320F\nLIM-CUZ-LIM\nLA 2232 (13:55-15:20 hrs)\nLA 2233 (15:55-17:35 hrs)","Inicial G6","LCK A320F\r\nLIM-CUZ-LIM\r\nLA 2013 (08:40-10:00 hrs)\r\nLA 2014 (10:40-12:15 hrs)\r\nLCK A320F\r\nLIM-CIX-LIM\r\nLA 2312 (13:25-15:00 hrs)\r\nLA 2313 (15:40-17:00 hrs)","REUNIÓN INSTRUCTORES","DO","DO","Blanco","LCK B767\n- LIM-MIA\n- LA 2480 (00:15-06:20 hrs)","Habilitación B767\n- MIA-LIM\n- LA 2481 (15:55-21:40 hrs)","CURSO DE ESTANDARIZACIÓN TARDE","DO","DO","DO","DO","LCK B767\n- LIM-MIA\n- LA 2698 (08:15-14:20 hrs)","Acompañamiento de Servicio B767 - MIA-LIM\n- LA 2699 (23:15-05:00 hrs)","Blanco","HO FILE","DO","DO","TALLER VOLUNTARIO DE SEGURIDAD","HANDS ON B767","Inicial G7 Chequeo LATAM\nLIM-AQP-LIM\nLA2119 08:30-10:00\nLA2118 10:55-12:35\r\nLIM-AQP-LIM\nLA2055 13:50-15:35\nLA2056 16:10-17:50","Inicial G6 Chequeo LATAM\nLIM-IQT-LIM\nLA2019 11:35-13:30\nLA2038 14:05-15:55","Graduación \nInicial G4&G5","DO","DO"],"bg":["#ffffff","#ffffff","#ffffff","#d0e0e3","#f7caac","#b4a7d6","#f7caac","#ffffff","#ffffff","#ffffff","#ffc000","#ffc000","#ffc000","#ffff00","#ffffff","#ffffff","#ffffff","#ffffff","#ffc000","#ffc000","#ffc000","#999999","#ffffff","#ffffff","#ffff00","#ffff00","#2f5496","#b4a7d6","#00b0f0","#ffffff","#ffffff"],"fg":["#000000","#000000","#000000","#000000","#000000","#000000","#000000","#000000","#000000","#000000","#000000","#000000","#000000","#000000","#000000","#000000","#000000","#000000","#000000","#000000","#000000","#000000","#000000","#000000","#000000","#000000","#ffffff","#000000","#000000","#000000","#000000"]},{"bp":"2369624","nombre":"Patricia Najar","dias":["DO","DO","DO","Curso Refreso IDE","HO FILE","LCK A320F\nLIM-CIX-LIM\nLA 2274 (09:35-11:10 hrs)\nLA 2275 (11:45-13:05 hrs)\nLCK A320F\nLIM-CUZ-LIM\nLA 2232 (13:55-15:20 hrs)\nLA 2233 (15:55-17:35 hrs)","DO","DO","DO","DO","LCK A320F\r\nLIM-CUZ-LIM\r\nLA 2013 (08:40-10:00 hrs)\r\nLA 2014 (10:40-12:15 hrs)\r\nLCK A320F\r\nLIM-CIX-LIM\r\nLA 2312 (13:25-15:00 hrs)\r\nLA 2313 (15:40-17:00 hrs)","Inicial G7","LCK B767\n- LIM-MIA\n- LA 2694 (13:30-19:35 hrs)","Blanco","Habilitación B767\n- MIA-LIM\n- LA 2693 (00:45-06:30 hrs)","DO","DO","RTI","RTI: VIRTUAL\nA320F / B767\n(08:30-17:30 hrs)\nINS TITULAR\n**Se habilita","RTI","RTI: VIRTUAL\nA320F / B767\n(08:30-17:30 hrs)\nINS TITULAR\n**Se habilita","Inicial G7","DO","DO","LCK A320F\nLIM-CIX-LIM\nLA 2312 (13:25-15:00 hrs)\nLA 2313 (15:40-17:00 hrs)","HANDS ON B767","LCK A320F\r\nLIM-CIX-LIM\r\nLA 2274 (09:35-11:10 hrs)\r\nLA 2275 (11:45-13:05 hrs)\r\nLCK A320F\r\nLIM-CUZ-LIM\r\nLA 2232 (13:55-15:20 hrs)\r\nLA 2233 (15:55-17:35 hrs)","HO FILE\nPRE IOSA 2026","HO FILE\nPRE IOSA 2026","DO","DO"],"bg":["#ffffff","#ffffff","#ffffff","#d0e0e3","#999999","#f7caac","#ffffff","#ffffff","#ffffff","#ffffff","#f7caac","#2f5496","#ffc000","#ffc000","#ffc000","#ffffff","#ffffff","#ffffff","#cce0f4","#ffffff","#cce0f4","#2f5496","#ffffff","#ffffff","#f7caac","#ffff00","#f7caac","#999999","#999999","#ffffff","#ffffff"],"fg":["#000000","#000000","#000000","#000000","#000000","#000000","#000000","#000000","#000000","#000000","#000000","#000000","#000000","#000000","#000000","#000000","#000000","#000000","#000000","#000000","#000000","#000000","#000000","#000000","#000000","#000000","#000000","#000000","#000000","#000000","#000000"]},{"bp":"3134911","nombre":"Javier Zapata","dias":["DO","DO","DO","Curso Refreso IDE","LCK B767\n- LIM-MIA\n- LA 2698 (08:15-14:20 hrs)","Habilitación B767*\n- MIA-LIM\n- LA 2699 (23:15-05:00 hrs)","Blanco","REUNIÓN INSTRUCTORES","DO","DO","Inicial G6","Inicial G6","Inicial G7","Inicial G7","Chequeo DGAC B767\n- LIM-SCL\n- LA 2413 (12:20-15:45 hrs)\nChequeo DGAC B767\n- SCL-LIM\n- LA 2412 (17:10-20:50 hrs)","DO","DO","LCK B767\n- LIM-MIA\n- LA 2698 (08:15-14:20 hrs)","Reentrenamiento B767\n- MIA-LIM\n- LA 2481 (15:55-21:40 hrs)","HO FILE","Inicial G7","DO","DO","DO","DO","HO PPT","Blanco","LCK B767 - LIM-MIA\n- LA 2480 (00:15-06:20 hrs)","Acompañamiento de Servicio B767\n- MIA-LIM\n- LA 2481 (15:55-21:40 hrs)","DO","DO"],"bg":["#ffffff","#ffffff","#ffffff","#d0e0e3","#ffc000","#ffc000","#ffc000","#ffffff","#ffffff","#ffffff","#b4a7d6","#b4a7d6","#2f5496","#2f5496","#ffc000","#ffffff","#ffffff","#ffc000","#ffc000","#999999","#2f5496","#ffffff","#ffffff","#ffffff","#ffffff","#999999","#ffc000","#ffc000","#ffc000","#ffffff","#ffffff"],"fg":["#000000","#000000","#000000","#000000","#000000","#000000","#000000","#000000","#000000","#000000","#000000","#000000","#000000","#000000","#000000","#000000","#000000","#000000","#000000","#000000","#000000","#000000","#000000","#000000","#000000","#000000","#000000","#000000","#000000","#000000","#000000"]},{"bp":"3750335","nombre":"Jefferson Mendez","dias":["DO","DO","DO","Curso Refreso IDE","HABILITACIÓN A320F (CCM)\nLIM-UIO-LIM\nLA 2382 (08:45-11:05 hrs)\nLA 2383 (12:15-14:30 hrs)","Inicial G4 CHEQUEO DGAC\nLIM-CUZ-LIM\nLA2077 09:45-11:10\nLA2078 11:50-13:25","Inicial G4 CHEQUEO DGAC\nLIM-PIU-LIM\nLA2306 09:30-11:15\nLA2307 11:55-13:25","CURSO 50% \nDÍA 5","DO","DO","LCK B767\n- LIM-MIA\n- LA 2698 (08:15-14:20 hrs)","Habilitación B767\n- MIA-LIM\n- LA 2481 (15:55-21:40 hrs)","HO MTC TARDE","RTI: PRÁCTICA\nA320F / B767 / B787\n(08:30-17:30 hrs)\nINS TITULAR","LCK ALUMNO B767 (CCM)\n- LIM-SCL\n- LA 2413 (12:05-15:35 hrs)\nLCK ALUMNO B767 (CCM)\n- SCL-LIM\n- LA 2412 (17:00-20:50 hrs)","DO","DO","LCK A320F\r\nLIM-AQP-LIM\r\nLA 2123 (09:15-10:50 hrs)\r\nLA 2124 (11:30-13:10 hrs)\r\nLCK A320F\r\nLIM-CJA-LIM\r\nLA 2295 (14:05-15:30 hrs)\r\nLA 2294 (16:10-17:15 hrs)","HO FILE","Reentrenamiento A320F*\nLIM-CUZ-LIM\nLA 2013 (08:40-10:00 hrs)\nLA 2014 (10:40-12:15 hrs)\nReentrenamiento A320F\nLIM-CIX-LIM\nLA 2312 (13:25-15:00 hrs)\nLA 2313 (15:40-17:00 hrs)","Inicial G7","DO","DO","DO","DO","LCK A320F\nLIM-CUZ-LIM\nLA 2013 (08:40-10:00 hrs)\nLA 2014 (10:40-12:15 hrs)\nReentrenamiento A320F*\nLIM-TPP-LIM\nLA 2087 (13:25-14:55 hrs)\nLA 2088 (15:35-17:00 hrs)","Inicial G6 Chequeo LATAM\nLIM-TCQ-LIM\nLA2071 10:30-12:25\nLA2072 13:00-14:55","HO FILE","Inicial G6 Chequeo DGAC\nLIM-CIX-LIM\nLA2312 14:00-15:30\nLA2313 16:05-17:30","DO","DO"],"bg":["#ffffff","#ffffff","#ffffff","#d0e0e3","#f4cccc","#ffc0cb","#ffc0cb","#ffe599","#ffffff","#ffffff","#ffc000","#ffc000","#999999","#cce0f4","#ffc000","#ffffff","#ffffff","#f7caac","#999999","#f7caac","#2f5496","#ffffff","#ffffff","#ffffff","#ffffff","#f7caac","#b4a7d6","#999999","#b4a7d6","#ffffff","#ffffff"],"fg":["#000000","#000000","#000000","#000000","#000000","#000000","#000000","#000000","#000000","#000000","#000000","#000000","#000000","#000000","#000000","#000000","#000000","#000000","#000000","#000000","#000000","#000000","#000000","#000000","#000000","#000000","#000000","#000000","#000000","#000000","#000000"]},{"bp":"3852423","nombre":"Gabriela Ungaro","dias":["DO","DO","DO","Inicial G6","Inicial G6","Inicial G4 CHEQUEO DGAC\nLIM-PIU-LIM\nLA2306 09:30-11:15\nLA2307 11:55-13:25","LCK B767\n- LIM-SCL\n- LA 2413 (12:05-15:35 hrs)\nLCK B767\n- SCL-LIM\r\n- LA 2412 (17:00-20:50 hrs)","REUNIÓN INSTRUCTORES\nTARDE","DO","DO","LCK A320F\r\nLIM-CIX-LIM\r\nLA 2274 (09:35-11:10 hrs)\r\nLA 2275 (11:45-13:05 hrs)\r\nLCK A320F\r\nLIM-CUZ-LIM\r\nLA 2232 (13:55-15:20 hrs)\r\nLA 2233 (15:55-17:35 hrs)","HO FILE","LCK A320F\r\nLIM-CUZ-LIM\r\nLA 2013 (08:40-10:00 hrs)\r\nLA 2014 (10:40-12:15 hrs)\r\nLCK A320F\r\nLIM-CIX-LIM\r\nLA 2312 (13:25-15:00 hrs)\r\nLA 2313 (15:40-17:00 hrs)","RTI: PRÁCTICA\nA320F / B767 / B787\n(08:30-17:30 hrs)\nINS APOYO","DO","VACACIONES","VACACIONES","VACACIONES","VACACIONES","VACACIONES","VACACIONES","VACACIONES","VACACIONES","DO","Inicial G8","HO PPT","LCK B767\n- MIA-LIM\n- LA 2694 (13:30-19:35 hrs)","Blanco","Habilitación B767\n- LIM-MIA\n- LA 2693 (00:45-06:30 hrs)","DO","DO"],"bg":["#ffffff","#ffffff","#ffffff","#b4a7d6","#b4a7d6","#ffc0cb","#ffc000","#ffffff","#ffffff","#ffffff","#f7caac","#999999","#f7caac","#cce0f4","#ffffff","#ffffcc","#ffffcc","#ffffcc","#ffffcc","#ffffcc","#ffffcc","#ffffcc","#ffffcc","#ffffff","#ff4b4f","#999999","#ffc000","#ffc000","#ffc000","#ffffff","#ffffff"],"fg":["#000000","#000000","#000000","#000000","#000000","#000000","#000000","#000000","#000000","#000000","#000000","#000000","#000000","#000000","#000000","#000000","#000000","#000000","#000000","#000000","#000000","#000000","#000000","#000000","#000000","#000000","#000000","#000000","#000000","#000000","#000000"]},{"bp":"2604360","nombre":"Mariella Carrasco","dias":["DO","DO","DO","Acompañamiento de Servicio B767\n- LIM-MIA\n- LA 2694 (13:30-19:35 hrs)","LCK B767 B767\n- MIA-LIM\n- LA 2699 (23:15-05:00 hrs)","Blanco","RTI: PRÁCTICA\nA320F / B767\n(08:30-17:30 hrs)\nINS APOYO TM","REUNIÓN INSTRUCTORES","DO","DO","AUDITORIA AEP\nLIM-AEP\nLA 2380 (09:30-14:00 hrs)","AUDITORIA AEP\nAEP-LIM\nLA 2368 (18:05-23:00 hrs)","HO MTC TARDE","LCK B767\n- LIM-SCL\n- LA 2413 (12:05-15:35 hrs)\nLCK B767\n- SCL-LIM\r\n- LA 2412 (17:00-20:50 hrs)","DO","VACACIONES","VACACIONES","VACACIONES","VACACIONES","VACACIONES","VACACIONES","VACACIONES","VACACIONES","DO","Inicial G6 Chequeo Latam\nLIM-PEM-LIM\nLA2260 10:20-12:05\nLA2261 12:45-14:20\nLIM-JUL-LIM\nLA2211 15:45-17:20\nLA2212 18:00-19:45","Blanco","Acompañamiento de Servicio B767\n- LIM-MIA\n- LA 2480 (00:15-06:20 hrs)","LCK B767\n- MIA-LIM\n- LA 2695 (16:10-22:00 hrs)","HO FILE\nTARDE \nPRE IOSA","DO","DO"],"bg":["#ffffff","#ffffff","#ffffff","#ffc000","#ffc000","#ffc000","#cce0f4","#ffffff","#ffffff","#ffffff","#ffff00","#ffff00","#999999","#ffc000","#ffffff","#ffffcc","#ffffcc","#ffffcc","#ffffcc","#ffffcc","#ffffcc","#ffffcc","#ffffcc","#ffffff","#b4a7d6","#ffc000","#ffc000","#ffc000","#999999","#ffffff","#ffffff"],"fg":["#000000","#000000","#000000","#000000","#000000","#000000","#000000","#000000","#000000","#000000","#000000","#000000","#000000","#000000","#000000","#000000","#000000","#000000","#000000","#000000","#000000","#000000","#000000","#000000","#000000","#000000","#000000","#000000","#000000","#000000","#000000"]},{"bp":"2823133","nombre":"Cesar Campos","dias":["DO","DO","DO","DO","HO MTC","CAPACITACION RRVV\nINSTRUCTOR","RTI: PRÁCTICA\nA320F / B767\n(08:30-17:30 hrs)\nINS APOYO","Reva de Servicio\n(08:30-17:30 hrs)\nDÍA 2","DO","DO","TTT CRM","Reva de Servicio\n(08:30-17:30 hrs)\nDÍA 1","Reva de Servicio\n(08:30-17:30 hrs)\nDÍA 2","HABILITACIÓN A320F (CCM)\nLIM-CUZ-LIM\nLA 2130 (08:10-09:30 hrs)\nLA 2129 (10:05-11:40 hrs)\nLIM-PIU-LIM\nLA 2308 (13:00-14:45 hrs)\nLA 2309 (15:25-16:55 hrs)","Inicial G6","DO","DO","CURSO DE ESTANDARIZACIÓN TARDE","HO FILE","HO FILE","RTI: PRÁCTICA\nA320F / B767\n(08:30-17:30 hrs)\nINS APOYO TM","CERTIFICACIÓN INS EXTERNO","DO","DO","Inicial G4 & G5\nTaller de Servicio\nDía 4","Inicial G6 Chequeo Latam\nLIM-CUZ-LIM\nLA2130 08:10-09:30\nLA2129 10:05-11:40\nLIM-PIU-LIM\nLA2308 13:00-14:45\nLA2309 15:25-16:55","Inicial G4 & G5\nTaller de Servicio\nDía 5","Inicial G7 Chequeo LATAM\nLIM-TCQ-LIM\nLA2071 10:30-12:25\nLA2072 13:00-14:55","CERTIFICACIÓN INS EXTERNO","DO","DO"],"bg":["#ffffff","#ffffff","#ffffff","#ffffff","#999999","#d0e0e3","#cce0f4","#2f5496","#ffffff","#ffffff","#ffff00","#2f5496","#2f5496","#f4cccc","#b4a7d6","#ffffff","#ffffff","#ffff00","#999999","#999999","#cce0f4","#d0e0e3","#ffffff","#ffffff","#00b0f0","#b4a7d6","#00b0f0","#2f5496","#d0e0e3","#ffffff","#ffffff"],"fg":["#000000","#000000","#000000","#000000","#000000","#000000","#000000","#ffffff","#000000","#000000","#000000","#ffffff","#ffffff","#000000","#000000","#000000","#000000","#000000","#000000","#000000","#000000","#000000","#000000","#000000","#000000","#000000","#000000","#ffffff","#000000","#000000","#000000"]},{"bp":"3189967","nombre":"Kevin Segovia","dias":["DO","DO","DO","DO","Inicial G5 CHEQUEO LATAM\nLIM-TCQ-LIM\nLA2071 10:15-12:25\nLA2072 12:55-14:55","CURSO 50% \nDÍA 3","Reva de Servicio\n(08:30-17:30 hrs)\nDÍA 1","REUNIÓN INSTRUCTORES","DO","DO","AUDITORIA \nPROCAB","CURSO 50% \nDÍA 7","Inicial G4 & G5\nTaller de Servicio\nDía 1","Reentrenamiento A320F + Pasajero A320F","HO FILE","DO","DO","HO FILE","Inicial G4 & G5\nTaller de Servicio\nDía 2","Inicial G4 & G5\nTaller de Servicio\nDía 3","HO FILE","CERTIFICACIÓN INS EXTERNO","DO","DO","Inicial G6 Chequeo LATAM\nLIM-PIU-LIM\nLA2306 09:30-11:15\nLA2307 11:55-13:25\r\nLIM-PIU-LIM\nLA2338 15:00-16:45\nLA2339 17:20-18:50","Inicial G7 Chequeo LATAM\nLIM-TCQ-LIM\nLA2067 13:45-15:40\nLA2068 16:20-18:15","Inicial G6 Chequeo LATAM\nLIM-TPP-LIM\nLA2085 08:25-09:55\nLA2086 10:40-12:00\r\nLIM-IQT-LIM\nLA2234 13:35-15:30\nLA2235 16:05-17:55","HO FILE\nPRE IOSA 2026","CERTIFICACIÓN INS EXTERNO","DO","DO"],"bg":["#ffffff","#ffffff","#ffffff","#ffffff","#00b0f0","#ffe599","#2f5496","#ffffff","#ffffff","#ffffff","#ffff00","#ffe599","#00b0f0","#f7caac","#999999","#ffffff","#ffffff","#999999","#00b0f0","#00b0f0","#999999","#d0e0e3","#ffffff","#ffffff","#b4a7d6","#2f5496","#b4a7d6","#999999","#d0e0e3","#ffffff","#ffffff"],"fg":["#000000","#000000","#000000","#000000","#000000","#000000","#ffffff","#000000","#000000","#000000","#000000","#000000","#000000","#000000","#000000","#000000","#000000","#000000","#000000","#000000","#000000","#000000","#000000","#000000","#000000","#ffffff","#000000","#000000","#000000","#000000","#000000"]},{"bp":"2415373","nombre":"Milagros Salas","dias":["VACACIONES","VACACIONES","VACACIONES","VACACIONES","VACACIONES","VACACIONES","VACACIONES","VACACIONES","VACACIONES","VACACIONES","VACACIONES","VACACIONES","VACACIONES","VACACIONES","VACACIONES","VACACIONES","VACACIONES","VACACIONES","VACACIONES","VACACIONES","VACACIONES","VACACIONES","VACACIONES","VACACIONES","VACACIONES","VACACIONES","VACACIONES","VACACIONES","VACACIONES","DO","DO"],"bg":["#ffffcc","#ffffcc","#ffffcc","#ffffcc","#ffffcc","#ffffcc","#ffffcc","#ffffcc","#ffffcc","#ffffcc","#ffffcc","#ffffcc","#ffffcc","#ffffcc","#ffffcc","#ffffcc","#ffffcc","#ffffcc","#ffffcc","#ffffcc","#ffffcc","#ffffcc","#ffffcc","#ffffcc","#ffffcc","#ffffcc","#ffffcc","#ffffcc","#ffffcc","#ffffff","#ffffff"],"fg":["#000000","#000000","#000000","#000000","#000000","#000000","#000000","#000000","#000000","#000000","#000000","#000000","#000000","#000000","#000000","#000000","#000000","#000000","#000000","#000000","#000000","#000000","#000000","#000000","#000000","#000000","#000000","#000000","#000000","#000000","#000000"]},{"bp":"2440915","nombre":"Judith Fernandez","dias":["DO","DO","DO","DO","Inicial G6","Inicial G6","CURSO 50% \nDÍA 4","REUNIÓN INSTRUCTORES","DO","DO","Inicial G7","RTI: VIRTUAL\nA320F / B767 / B787\n(08:30-17:30 hrs)\nINS TITULAR","HABILITACIÓN A320F (CCM)\nLIM-UIO-LIM\nLA 2382 (08:45-11:05 hrs)\nLA 2383 (12:15-14:30 hrs)","Reva de Servicio\n(08:30-17:30 hrs)\nDÍA 1","Reva de Servicio\n(08:30-17:30 hrs)\nDÍA 2","DO","DO","Habilitación B767 (CCM)\n- LIM-ATL\n- LA 2482 (12:05-20:35 hrs)","Habilitación B767 (CCM)\n- ATL-LIM\n- LA 2483 (23:15-05:00 hrs)","Blanco","Inicial G6 Chequeo LATAM\nLIM-CUZ-LIM\nLA2013 08:40-10:00\nLA2014 10:40-12:15\r\nLIM-AQP-LIM\nLA2055 13:50-15:35\nLA2056 16:10-17:50","HO FILE","DO","DO","RTI","RTI: VIRTUAL\nA320F / B767\n(08:30-17:30 hrs)\nINS TITULAR\n**Se habilita","RTI ALUMNO","RTI: VIRTUAL\nA320F / B767\n(08:30-17:30 hrs)\nINS TITULAR\n**Se habilita","CERTIFICACIÓN INS EXTERNO","DO","DO"],"bg":["#ffffff","#ffffff","#ffffff","#ffffff","#b4a7d6","#b4a7d6","#ffe599","#ffffff","#ffffff","#ffffff","#2f5496","#cce0f4","#f4cccc","#2f5496","#2f5496","#ffffff","#ffffff","#ffc000","#ffc000","#ffc000","#b4a7d6","#999999","#ffffff","#ffffff","#ffffff","#cce0f4","#ffffff","#cce0f4","#d0e0e3","#ffffff","#ffffff"],"fg":["#000000","#000000","#000000","#000000","#000000","#000000","#000000","#000000","#000000","#000000","#000000","#000000","#000000","#ffffff","#ffffff","#000000","#000000","#000000","#000000","#000000","#000000","#000000","#000000","#000000","#000000","#000000","#000000","#000000","#000000","#000000","#000000"]},{"bp":"3796947","nombre":"Rafael Nieto","dias":["SICK","SICK","SICK","SICK","SICK","SICK","SICK","SICK","SICK","SICK","SICK","SICK","SICK","SICK","SICK","SICK","SICK","SICK","SICK","SICK","SICK","SICK","SICK","SICK","SICK","SICK","SICK","SICK","SICK","SICK","SICK"],"bg":["#ffffff","#ffffff","#ffffff","#ffffff","#ffffff","#ffffff","#ffffff","#ffffff","#ffffff","#ffffff","#ffffff","#ffffff","#ffffff","#ffffff","#ffffff","#ffffff","#ffffff","#ffffff","#ffffff","#ffffff","#ffffff","#ffffff","#ffffff","#ffffff","#ffffff","#ffffff","#ffffff","#ffffff","#ffffff","#ffffff","#ffffff"],"fg":["#000000","#000000","#000000","#000000","#000000","#000000","#000000","#000000","#000000","#000000","#000000","#000000","#000000","#000000","#000000","#000000","#000000","#000000","#000000","#000000","#000000","#000000","#000000","#000000","#000000","#000000","#000000","#000000","#000000","#000000","#000000"]},{"bp":"3841387","nombre":"Gianfranco Celiz","dias":["DO","DO","DO","RTI","RTI: VIRTUAL\nA320F / B767\n(08:30-17:30 hrs)\nINS TITULAR\n**Se habilita","RTI","RTI: VIRTUAL\nA320F / B767\n(08:30-17:30 hrs)\nINS TITULAR\n**Se habilita","REUNIÓN INSTRUCTORES","DO","DO","Habilitación B767 (CCM)\n- LIM-ATL\n- LA 2482 (12:05-20:35 hrs)","Habilitación B767 (CCM)\n- ATL-LIM\n- LA 2483 (23:15-05:00 hrs)","Blanco","CURSO DE ESTANDARIZACIÓN TARDE","Inicial G7","DO","DO","DO","DO","HO FILE","RTI: PRÁCTICA\nA320F / B767\n(08:30-17:30 hrs)\nINS APOYO","CERTIFICACIÓN INS EXTERNO","DO","DO","Inicial G6 Chequeo LATAM\nLIM-CUZ-LIM\nLA2077 09:45-11:10\nLA2078 11:50-13:25\r\nLIM-AQP-LIM\nLA2113 15:05-16:40\nLA2112 17:15-18:55","Inicial G7 Chequeo LATAM\nLIM-PEM-LIM\nLA2023 12:05-13:50\nLA2024 14:30-16:10","Curso de Estandarización \nTarde","RTI: PRÁCTICA\nA320F / B767\n(08:30-17:30 hrs)\nINS APOYO","CERTIFICACIÓN INS EXTERNO","DO","DO"],"bg":["#ffffff","#ffffff","#ffffff","#ffffff","#cce0f4","#ffffff","#cce0f4","#ffffff","#ffffff","#ffffff","#ffc000","#ffc000","#ffc000","#ffff00","#2f5496","#ffffff","#ffffff","#ffffff","#ffffff","#999999","#cce0f4","#d0e0e3","#ffffff","#ffffff","#b4a7d6","#2f5496","#ffff00","#cce0f4","#d0e0e3","#ffffff","#ffffff"],"fg":["#000000","#000000","#000000","#000000","#000000","#000000","#000000","#000000","#000000","#000000","#000000","#000000","#000000","#000000","#000000","#000000","#000000","#000000","#000000","#000000","#000000","#000000","#000000","#000000","#000000","#f3f3f3","#000000","#000000","#000000","#000000","#000000"]}]} | C6: 46318.36 | D6: Google Sheet
